Workbook

Sheet Cover
A3: FINNISH ONSHORE WIND PROJECT
A5: Project Finance Model
A8: MODEL OVERVIEW
A9: Item | B9: Value | C9: Unit | D9: Status
A10: Model version | B10: 1.8 | C10: - | D10: nominal, two scenario switches, horizon to 2058, scenario and break-even snapshots, Sources & Checks, standalone BESS tab; BESS CAPEX-saving grid and snapshot checks
A11: Valuation date | B11: 2026 | C11: year | D11: Input
A12: Project COD | B12: =Inputs!B9 -> 2028 | C12: year | D12: Input
A13: Project lifetime | B13: =Inputs!B8 -> 25 | C13: years | D13: Input
A14: Installed capacity | B14: =Inputs!B7 -> 100 | C14: MW | D14: Input
A15: PPA mode | B15: Yes | C15: - | D15: Input
A16: Capture-rate scenario | B16: Base | C16: - | D16: Input
A17: Market price scenario | B17: Base | C17: - | D17: Input
A19: WORKBOOK MAP
A20: Tab | B20: Purpose
A21: Inputs | B21: Core technical, commercial and financing assumptions; every assumption has source/status fields.
A22: Prices | B22: Market-price inputs, capture-rate scenarios and PPA switch.
A23: Production | B23: Annual wind generation (integrated BESS logic switched off; see BESS tab).
A24: Revenue | B24: Merchant/PPA revenue build-up.
A25: Cashflow | B25: Project and equity cash-flow bridge.
A26: Financing | B26: DSCR-based debt sizing and debt schedule.
A27: Taxes | B27: Taxable income, loss carryforward and corporate tax.
A28: Outputs | B28: IRR, NPV, LCOE, DSCR, PPA indifference price, scenario grids and break-even PPA price.
A29: Checks | B29: Model integrity and source-status checks.
A30: Changelog | B30: List of corrections and structural changes since v1.0, plus open items.
A31: Sources & Checks | B31: Validation checks against sources and hand calculations; log of AI use.
A32: BESS | B32: Standalone co-located battery: inputs with sources, cash flows, NPV/IRR, scenario snapshot.

Sheet Inputs
A1: INPUTS
A3: Blue cells are intended for user inputs. Green = sourced/verified. Yellow = own assumption / to verify. Grey = formula.
A5: PROJECT
A6: Parameter | B6: Value | C6: Unit | D6: Source / reference | E6: Status | F6: Base / scenario | G6: Notes | H6: Model use
A7: Installed capacity | B7: 100 | C7: MW | D7: Scaled to typical small Finnish project size. Reference projects: Honkakangas 105 MW and Rajamäenkylä 367 MW (OX2 press release, 1 Apr 2025), Pahkakoski 186 MW (NIB loan, 14 Dec 2023), Lestijärvi 455 MW, the largest Finnish wind farm built to date (Renewables Finland, wind power statistics 2025). | E7: own assumption | G7: Replace with project size. | H7: Production
A8: Project lifetime | B8: 25 | C8: years | D8: Renewables Finland / Finnish Wind Power Association, "Tuulivoimalan purkamisen kustannukset", 9 Aug 2023: calculated lifetime 35 years for turbines from the 2020s, 20-30 years for older ones. Base case 25 years chosen conservatively; sensitivity 20 and 30 years. Industry association source; lease and permit duration not checked. Danish Energy Agency (2026), sheet 20: technical lifetime 27 years (2025) and 30 years from 2030, depending on wind conditions and turbine design class. | E8: source-based | G8: Economic operating life. | H8: Production, Cashflow
A9: Commercial operation date | B9: 2028 | C9: year | D9: FID assumed in H2 2026, construction about 15 to 24 months. Reference: OX2 FID 1 Apr 2025 with completion 2027 (Honkakangas) and 2028 (Rajamäenkylä); NIB loan Pahkakosken Energia Oy 14 Dec 2023 with completion expected Aug 2025. Danish Energy Agency (2026), sheet 20: construction time 1.5 years from FID to commissioning; planning from idea to construction start typically 2 to 3 years. | E9: own assumption | G9: COD assumption. | H9: Production, Cashflow
A10: Net capacity factor | B10: 0.35 | C10: % | D10: OX2 press release, 1 Apr 2025: about 1.6 TWh per year from 472 MW = 38.7 % (own calculation; probability level not stated). NIB loan Pahkakosken Energia Oy, 14 Dec 2023: 516 GWh per year at 90 % probability for 186 MW = 31.7 % (P90). Own analysis of ENTSO-E data: Finnish fleet average 26-30 % (2023-2025, older turbines). 35 % chosen as net P50 estimate between the sources; sensitivity 32 to 38 %. Danish Energy Agency (2026), sheet 20: 3,500 full load hours (capacity factor 40.0 %) for 2025, average for expected Danish wind farm locations including wake losses; 3,600 hours for 2030. | E10: source-based | G10: Use net output factor after availability/losses. | H10: Production
A11: Curtailment | B11: 0.05 | C11: % | D11: Own analysis of Finnish day-ahead prices and ENTSO-E wind generation (Actual Generation per Production Type, FI) (project data; https://transparency.entsoe.eu/, accesed 1.10.2026): share of wind energy produced in negative-price hours 8.2 % (2023), 11.5 % (2024), 6.5 % (2025), 1.8 % (last 12 months to Sep 2026). Base 5 % chosen between the recent value and the 2023-2025 average (8.8 %); future share is a judgement within this range. Sensitivity 2 to 10 %. Capture rates are taken from the curtailed variant to avoid double counting | E11: source-based | G11: Base case corresponds to a PPA with no settlement in negative-price hours (seller bears the lost volume). Newer contracts keep settling with a EUR 0/MWh floor but at a lower strike; Modo Energy (Oct 2025, Spanish solar PPAs) estimates a price difference of at least about EUR 3/MWh between the two structures. 5 % curtailment × EUR 50/MWh = about EUR 2.5/MWh (own calculation), i.e. broadly equivalent. Sensitivity B11 = 0 only valid together with a lower PPA price. Grid curtailment by Fingrid not included. | H11: Production
A12: CAPEX
A13: Parameter | B13: Value | C13: Unit | D13: Source / reference | E13: Status | F13: Base / scenario | G13: Notes | H13: Model use
A14: Wind CAPEX | B14: 1500 | C14: €/kW | D14: OX2 press release, FID 1 Apr 2025: more than EUR 700m for 472 MW (about 1.48 EUR m/MW, lower bound). NIB loan Pahkakosken Energia Oy, 14 Dec 2023: capex EUR 230m for 186 MW (1.24 EUR m/MW). WindEurope Autumn 2026, p. 19: EU onshore nearly EUR 6bn for 3.8 GW (about 1.58 EUR m/MW, own calculation from rounded figures). 1,500 EUR/kW selected between the 2025 OX2 FIDs (1.44-1.48 EUR m/MW: Dec 2025, about EUR 400m for 277 MW; Apr 2025, more than EUR 700m for 472 MW) and WindEurope 2026 (about 1.58 EUR m/MW). Cross-check: IRENA (2026), Fig. 2.4: Finland TIC 2025 USD 1,480/kW. | E14: source-based | G14: Base 1,500 EUR/kW in real 2026 EUR. Sensitivity 1,250 to 1,650 EUR/kW. Treated as all-in investment at FID (row 16 stays empty); scope of the sources not stated, to verify. | H14: Cashflow (CAPEX)
A15: BESS CAPEX | C15: €/kWh | E15: n/a | G15: Not used: integrated BESS switched off (B24 = 0); battery evaluated standalone in tab BESS. Only used if BESS capacity > 0. Enter in real 2026 EUR; indexed with inflation (B63). | H15: Cashflow (CAPEX)
A16: Development / other CAPEX | B16: 0 | C16: €/kW | D16: Assumed to be 0 and all CAPEX covered in row 14 | E16: own assumption | G16: Optional project-specific allowance. Enter in real 2026 EUR; indexed with inflation (B63). | H16: Cashflow (CAPEX)
A17: OPEX & LEASE
A18: Parameter | B18: Value | C18: Unit | D18: Source / reference | E18: Status | F18: Base / scenario | G18: Notes | H18: Model use
A19: Fixed OPEX | B19: 39000 | C19: €/MW/year | D19: Value 39,000 EUR/MW/yr = 39 EUR/kW/yr (compare B19 + B21 = 44 EUR/kW/yr). Generic O&M about 35 EUR/kW/yr: NREL, Cost of Wind Energy Review 2024 Edition, US land-based reference plant (3.3 MW) about USD 43/kW/yr (scope not checked); Wind Energy - The Facts (EWEA): O&M 1.2-1.5 EUR cent/kWh over turbine life (Germany, Spain, UK, Denmark) = about 37-46 EUR/kW/yr at 35 % capacity factor (own calculation). Nordic cross-checks: Danish Energy Agency, Technology Data for Generation of Electricity and District Heating, version 0019 (Aug 2026), sheet 20 Onshore turbines, 2025 values in 2020 prices: fixed O&M 17.4 kEUR/MW/yr plus variable O&M 2.06 EUR/MWh = about 24.6 EUR/kW/yr at 3,500 full load hours (own calculation; land rent and property tax not included; not inflated to 2026); Paaso and Khosravi (2021), Energy Engineering 118(4), Aalto University, use O&M of 2 % of investment cost per year citing the Finnish Wind Power Association (2020; original page no longer available) = 31 EUR/kW/yr at 1,550 EUR/kW (own calculation; scope not stated). European study: KIC InnoEnergy / BVG Associates, "Future renewable energy costs: onshore wind", Sep 2014 (50 MW reference wind farm): OPEX 42 EUR/kW/yr (high wind site) and 36 EUR/kW/yr (low wind site) in real end-2013 prices, including land lease and community funds, excluding insurance and transmission charges; not inflated to 2026. Plus Finnish property tax about 4 EUR/kW/yr: Megatuuli Oy, Honkalankangas project presentation, 8 Nov 2021: about 30,000 EUR per turbine per year, 640,000 EUR per turbine over 30 years (age reduction); about 3-5 EUR/kW/yr at 6.5 MW per turbine (own calculation). The US source may already include property tax. Property tax cross-check: Renewables Finland, "Effects to the economy" (page last updated 24 Sep 2024, accessed 2 Oct 2026): power plant property tax rate max. 3.1 % (wind farms > 10 MVA); tax base = foundation, tower and nacelle shell only (about 30 % of turbine investment cost); first-year taxable value 75 %, age discount 2.5 % p.a. down to a floor of 40 %; observed first-year property tax EUR 20,000-35,000 per turbine. At 6.5 MW per turbine = about 3-5.4 EUR/kW in year 1 (own calculation); formula example at EUR 1m/MW gives about 7 EUR/kW. Lifetime average about 70 % of year 1 because of the age discount (own calculation). About 4 EUR/kW/yr kept, indexed with inflation (simplification: age discount and construction cost index not modelled separately). No Finnish primary O&M measurement found. | E19: source-based | G19: All O&M entered as fixed (variable OPEX = 0). Sensitivity band +/-30 % on B19 + B21 (about 31,000 to 57,000 EUR/MW/yr). No real cost decline assumed. Enter in real 2026 EUR; indexed with inflation (B63). | H19: Cashflow
A20: Variable OPEX | B20: 0 | C20: €/MWh | D20: Variable OPEX assumed to be small and included in fixed OPEX | E20: own assumption | G20: Optional variable cost. Enter in real 2026 EUR; indexed with inflation (B63). | H20: Cashflow
A21: Land lease / rent | B21: 5000 | C21: €/MW/year | D21: Value 5,000 EUR/MW/yr = 5 EUR/kW/yr. Finnish Forest Association, "Wind power generates profits from state-owned land", 12 Sep 2014: landowners are paid EUR 5,000 to 15,000 per year per turbine (media ballpark figure quoted by Metsähallitus, actual rate not disclosed), equal to about 0.8 to 5.0 kEUR/MW/yr for 3 to 6.5 MW turbines (own calculation). Second anchor: cost split in Wind Energy - The Facts (EWEA), land rent about 13 % of O&M = about 5 EUR/kW/yr (own calculation). Value set at the upper end of the Finnish range (conservative). Qualitative support: Renewables Finland: lease higher than forestry return; Megatuuli Oy, 8 Nov 2021: up to two to three times forestry income. Lease contracts are not public; media figure from 2014. | E21: source-based | G21: Document local lease basis. Enter in real 2026 EUR; indexed with inflation (B63). | H21: Cashflow
A22: BESS
A23: Parameter | B23: Value | C23: Unit | D23: Source / reference | E23: Status | F23: Base / scenario | G23: Notes | H23: Model use
A24: BESS energy capacity | B24: 0 | C24: MWh | E24: own assumption | G24: Set to 0 if no BESS. v1.7: kept at 0; the BESS is evaluated standalone in tab BESS. | H24: Production, Cashflow
A25: BESS round-trip efficiency | B25: 0.85 | C25: % | E25: n/a | G25: Not used: integrated BESS switched off (B24 = 0); battery evaluated standalone in tab BESS. Only relevant if BESS is modelled. | H25: Production, Revenue
A26: BESS cycles | B26: 0 | C26: cycles/year | E26: n/a | G26: Not used: integrated BESS switched off (B24 = 0); battery evaluated standalone in tab BESS.Full-load discharge cycles per year; drives BESS arbitrage volume (Production). | H26: Production, Revenue
A27: TAX
A28: Parameter | B28: Value | C28: Unit | D28: Source / reference | E28: Status | F28: Base / scenario | G28: Notes | H28: Model use
A29: Corporate income tax rate | B29: 0.2 | C29: % | D29: vero.fi, Your tax handbook in Finland: 20 % (accessed 1 Oct 2026) | E29: verified | G29: Current law 20 %. Government budget proposal for 2027 of 17 Sep 2026 (valtioneuvosto.fi): 18 % from 2027, loss carry-forward 25 years; not yet law. Loss carry-forward modelled without expiry, consistent with Government proposal HE 151/2026 (25 years for losses from tax year 2026). Own sensitivity: current-law 10-year expiry about −1.2 EUR m NPV; 18 % rate about +0.2 EUR m. | H29: Taxes
A30: FINANCING
A31: Parameter | B31: Value | C31: Unit | D31: Source / reference | E31: Status | F31: Base / scenario | G31: Notes | H31: Model use
A32: Target minimum DSCR | B32: 1.3 | C32: x | D32: Typical minimum DSCR on P50: 1.25-1.35x contracted, 1.40-1.50x with significant merchant exposure (Intellifields, renewable energy financial model guide, 2026); 1.35-1.45x contracted renewables, 1.60x+ merchant (ibinterviewquestions.com, Aug 2026). Secondary sources, no Finnish term sheet available. 1.30x chosen for 100 % PPA over the full debt tenor (B44 = B34) with an investment-grade offtaker. | E32: own assumption | F32: Base (merchant case), PPA case: 1.4 | G32: Single DSCR applied to all debt years. Scenario-dependent, set manually: 1.30 (100 % PPA, PPA tenor = debt tenor), 1.40 (65 % PPA), 1.60 (merchant, together with WACC 7 %). P90 sizing not modelled. Sensitivity 1.25 to 1.40. | H32: Financing
A33: Debt interest rate | B33: 0.0575 | C33: % | D33: EUR 10-year interest rate swap (vs 6M EURIBOR) about 3.7 % (Investing.com / BlueGamma, 28-29 Sep 2026). Lending margin 2.0 %: IRENA, "The cost of financing for renewable power", May 2023 (global baseline for large private infrastructure debt). as a proxy; the sculpted 15-year loan has an average life of about 8.7 years (own calculation from Financing), so the 10Y swap is slightly conservative.. All-in 5.75 % nominal; sensitivity 4.75 to 6.75 %. Hedging cost, fees and Finland-specific margin not checked (accessed 2 Oct 2026) | E33: source-based | G33: Debt rate enters project NPV only via the WACC (B38), which is not linked to this cell. When varying B33, adjust B38 by about 0.38 pp per 1 pp change (47 % gearing × (1 - 20 % tax), see D38) | H33: Financing
A34: Debt tenor | B34: 15 | C34: years | D34: Typical tenor for contracted onshore wind 15-18 years (Intellifields, 2026). 15 years = lower end, leaves 10-year tail to the 25-year life; sensitivity 18 years. Debt tenor equal to the 15-year PPA | E34: own assumption | G34: Debt tenor from first drawdown/COD. | H34: Financing
A35: Debt sizing horizon | B35: 15 | C35: years | D35: set equal to debt tenor | E35: own assumption | G35: Years of CFADS used for sizing; limited to the debt tenor. | H35: Financing
A36: RETURNS
A37: Parameter | B37: Value | C37: Unit | D37: Source / reference | E37: Status | F37: Base / scenario | G37: Notes | H37: Model use
A38: Discount rate / WACC | B38: 0.06 | C38: % | D38: CAPM build-up (own calculation): risk-free 3.58 % (Finland 10Y government bond, 18 Aug 2026, Trading Economics); equity risk premium 4.23 % (Damodaran, implied ERP, Jan 2026); unlevered beta 0.47 (Damodaran, Green & Renewable Energy, US dataset, Jan 2026), relevered at 47 % gearing = 0.80; cost of equity about 7.0 %. WACC = 53 % × 7.0 % + 47 % × 5.75 % × (1 - 20 %) = about 5.9 % nominal after tax. Cross-check: IRENA (2026), ch. 1: about 3 % real for fully contracted projects; merchant WACC roughly double (citing BNEF 2026). 6 % used for the PPA case, 7 % for the merchant case. | E38: own assumption | G38: Nominal WACC (cash flows are nominal). Used for project NPV and LCOE. Scenario-dependent: about 6 % nominal for the PPA case (Cover!B15 = Yes), 7 % for the merchant case; set manually together with B32. Affects NPV and LCOE only, not the cash flows. Sensitivity 5 to 8 %. Model run: 1 pp lower WACC reduces LCOE by about 3 EUR/MWh (own calculation) | H38: Outputs
A39: Target equity IRR | B39: 0.1 | C39: % | D39: CAPM cost of equity about 7.0 % (see D38) plus own premium of 2-3 pp for a single unlisted asset with construction and volume risk = 9-10 %. 10 % used (upper end). Sensitivity 8 to 12 %. | E39: own assumption | G39: Beta from Damodaran US dataset (European dataset not checked); no Finland country risk premium added (AA-rated, to verify). | H39: Checks
A40: PPA price | B40: 50 | C40: €/MWh | D40: Upper end of observed market levels: LevelTen Energy PPA Price Index Europe Q1 2026, top-quartile (P25) wind offers EUR 49.95/MWh, Finland and Portugal only, seller offers not transactions (via SR Inc NZCB Europe VPPA Opportunity Index 2026 Q1). Lower reference: KYOS PPA Insights No. 19 (Jun 2026), Finland, 2027-2036: onshore wind capture price 36.1 EUR/MWh, P25 PPA estimate 28.9 EUR/MWh (baseload 60.0 EUR/MWh). Pexapark Euro Composite Jul 2026: EUR 45/MWh (all technologies, Europe). Break-even PPA implied by recent OX2 FIDs about 62-67 EUR/MWh (own model runs, see Sources & Checks). Fixed nominal; sensitivity 25 to 80 EUR/MWh (accessed 2 Oct 2026). Model break-even for this 100 MW case: 70.35 (NPV = 0) and 73.94 EUR/MWh (equity IRR 10 %), Outputs rows 28-32. LevelTen Q2 2026 (23 Jul 2026): Finnish wind prices held steady (leveltenenergy.com, accessed 4 Oct 2026). | E40: own assumption | G40: Fixed nominal (B64 = No). Chosen as upper bound for robustness, not as a data-centre premium. Break-even PPA price for the base case: see Outputs / Sources & Checks. | H40: Revenue
A41: PPA STRUCTURE
A42: Parameter | B42: Value | C42: Unit | D42: Source / reference | E42: Status | F42: Base / scenario | G42: Notes | H42: Model use
A43: PPA volume share | B43: 1 | C43: % of net generation | D43: Both recent Finnish FIDs are fully contracted: OX2 Rajamäenkylä/Honkakangas (472 MW, 1 Apr 2025): long-term PPA with one multinational corporate offtaker (Amazon per DatacenterDynamics); OX2 Kannisto/Korkeamaa/Salo-Ylikoski (277 MW, 16 Dec 2025): long-term corporate VPPAs with several offtakers. Base 100 %; sensitivity 65 % (project brief) | E43: source-based | G43: Share of wind volume sold under the PPA while PPA mode = Yes. Remainder is merchant. | H43: Prices
A44: PPA tenor | B44: 15 | C44: years from COD | D44: Base 15 years: Google wind PPAs in Europe of 15 years (Renner Energies onshore portfolio, Belgium, DatacenterDynamics, Jul 2026). Google's Finnish wind PPAs to date are 10 years (VALOREM Matkussaari, signed 2024, press release Sep 2026). The 22-year Google-Fortum PPA (9 Sep 2026) covers existing nuclear baseload (Loviisa), not a wind reference. Sensitivity 10 and 20 years (accessed 2 Oct 2026). | E44: source-based | G44: Data-centre offtaker case (corporate pay-as-produced PPA). Model run: 20 instead of 15 years improves NPV by only about EUR 5m, because a fixed nominal price loses real value in later years (own calculation). After PPA expiry: merchant sales at the selected capture rate, used as a proxy for re-contracting at market value (a follow-on PPA would be priced at the then-expected capture price less a hedging discount, KYOS Jun 2025: about 20 %). Lenders give no credit to uncontracted re-contracting. | H44: Prices
A45: BESS (SIMPLIFIED REVENUE STACK, GRID-CHARGED)
A46: Parameter | B46: Value | C46: Unit | D46: Source / reference | E46: Status | F46: Base / scenario | G46: Notes | H46: Model use
A47: BESS power capacity | C47: MW | E47: n/a | G47: Not used: integrated BESS switched off (B24 = 0); battery evaluated standalone in tab BESS. Set to 0 if no BESS. Needed for reserve revenue and BESS fixed OPEX. v1.7: kept at 0; the BESS is evaluated standalone in tab BESS. | H47: Revenue
A48: BESS net arbitrage margin | C48: €/MWh discharged | E48: n/a | G48: Not used: integrated BESS switched off (B24 = 0); battery evaluated standalone in tab BESS | H48: Revenue
A49: BESS reserve-market revenue | C49: €/MW/year | E49: n/a | G49: Not used: integrated BESS switched off (B24 = 0); battery evaluated standalone in tab BESS | H49: Revenue
A50: BESS fixed OPEX | C50: €/MW/year | E50: n/a | G50: Not used: integrated BESS switched off (B24 = 0); battery evaluated standalone in tab BESS | H50: Revenue
A51: BESS operating life | B51: 15 | C51: years | D51: Project brief (approx. 15 years) | E51: own assumption | G51: Replacement CAPEX falls in the year after this life (if the project runs longer). Still used: operating life of the standalone BESS (BESS!B23). Do not delete. | H51: Cashflow
A52: BESS replacement CAPEX | C52: % of initial BESS CAPEX | E52: n/a | G52: Not used: integrated BESS switched off (B24 = 0); battery evaluated standalone in tab BESS | H52: Cashflow
A53: END OF LIFE, TAX AND FINANCING (ADDITIONAL)
A54: Parameter | B54: Value | C54: Unit | D54: Source / reference | E54: Status | F54: Base / scenario | G54: Notes | H54: Model use
A55: Decommissioning cost net of salvage | B55: 20 | C55: €/kW | D55: Renewables Finland (Finnish Wind Power Association), "Tuulivoimalan purkamisen kustannukset", 9 Aug 2023 (cost data AFRY Finland, Havator): scrap revenue from recycled materials of a steel-tower turbine 69,500-117,500 EUR per turbine (2023 prices, 10 turbines dismantled at once). SYKE, "Maatuulivoimaloiden purkamiskustannusten ja purkamisen rahoitusmallien arviointi", 9 Jun 2025: tower removal 132,400-167,400 EUR, ground-slab foundation removal to 2 m depth 36,700-70,400 EUR, landscaping 3,900-4,400 EUR per turbine (gross, ex VAT). Net of scrap revenue 55,500-172,700 EUR per turbine (lowest cost with highest revenue to highest cost with lowest revenue), converted at 6.5 MW per turbine (own calculation, average of Finnish installations 2025) = 8.5-27 EUR/kW. | E55: source-based | G55: Base 20 EUR/kW: upper-middle of the 8.5-27 EUR/kW range (tower and foundation to 2 m, net of scrap revenue). Sensitivity band 5 to 75 EUR/kW: low = tower removal and foundation covered only (net about 1-13), high = full removal of foundations and lift-field structures (net about 46-97). Scrap revenue 25+ years ahead is uncertain (SYKE excludes it in its estimates). Legal scope still open (government bill planned for autumn 2026). Incurred in the last operating year, not tax-deducted. Enter in real 2026 EUR; indexed with inflation (B63) | H55: Cashflow
A56: Tax depreciation rate (declining balance) | B56: 0.235 | C56: % of opening tax book value | D56: KPMG Law, "Taxation of wind power – 2023" (Mar 2023), Finland, p. 55: wind power plant split into components for tax depreciation; tower (frame body and engine room) = construction, max. 20 % p.a.; rotor, gearbox and generator = movable fixed assets, max. 25 % p.a. (declining balance, EVL 30 §). Structure share about 30 % of turbine cost (Renewables Finland, "Effects to the economy", accessed 2 Oct 2026). Blended rate 0.3 × 20 % + 0.7 × 25 % = 23.5 % applied to all CAPEX (own calculation; simplification, balance-of-plant split not checked). Sensitivity 25 %. Source from 2023, current law not re-checked. | E56: source-based | G56: Applied to CAPEX incl. replacement CAPEX from the year after spend. | H56: Taxes
A57: Interest deduction cap | B57: 0.25 | C57: % of adjusted taxable income (EBITDA) | D57: vero.fi, Your tax handbook in Finland (accessed 1 Oct 2026) | E57: verified | G57: Applies above the threshold below. Disallowed interest is not carried forward (conservative). | H57: Taxes
A58: Interest deduction threshold | B58: 500000 | C58: €/year | D58: vero.fi, Your tax handbook in Finland (accessed 1 Oct 2026) | E58: verified | G58: Net interest up to this amount is fully deductible. Simplification (conservative): the €3m safe harbour for net interest paid to unrelated parties and the balance-sheet exemption are not applied (vero.fi tax handbook). Effect: project NPV unchanged (unlevered tax); equity IRR +0.06 pp. | H58: Taxes
A59: Maximum gearing | B59: 0.75 | C59: debt / initial CAPEX | D59: OX2 Rajamäenkylä and Honkakangas (472 MW): EUR 600m debt vs total investment over EUR 700m = max. about 85 % (own calculation, upper bound; facility may include non-term tranches), with corporate PPAs (DLA Piper, 4 Apr 2025). 75 % chosen as conservative cap for a partly merchant project; in practice the DSCR constraint is expected to bind. | E59: source-based | G59: Caps the DSCR-sized debt. Binds only at high PPA prices (break-even at 10 % equity IRR, Outputs row 31). | H59: Financing
A61: INFLATION AND INDEXATION
A62: Parameter | B62: Value | C62: Unit | D62: Source / reference | E62: Status | F62: Base / scenario | G62: Notes | H62: Model use
A63: Inflation rate | B63: 0.02 | C63: % p.a. | D63: ECB staff macroeconomic projections, Sep 2026: euro area HICP inflation 3.0 % (2026), 2.5 % (2027), 2.1 % (2028). ECB Survey of Professional Forecasters Q3 2026 (press release 24 Jul 2026): longer-term expectation (2031) 2.0 %. ECB target: 2 % in the medium term (monetary policy decision, 10 Sep 2026). Flat 2.0 % applied over the whole horizon for simplicity; the higher near-term rates (about +0.5 pp in 2027) are not modelled. Euro area figures, no Finland-specific long-term forecast used (accessed 2 Oct 2026) | E63: source-based | G63: Indexes real 2026 prices and costs to nominal. WACC and debt rate are nominal. | H63: Prices, Revenue, Cashflow, Financing
A64: PPA price indexed to inflation? | B64: No | C64: Yes / No | D64: Fixed nominal price is the European norm for corporate PPAs: fixed-price PPAs valued by buyers as a hedge against wholesale price volatility (S&P Global Market Intelligence, Apr 2025); corporate PPAs use fixed or floor pricing (Bird & Bird, International Corporate PPA Report 2025/26). Share of escalated or CPI-indexed deals not found in public sources (to verify). Indexed case (Yes) only comparable with a lower start price: at 2 % inflation and 6 % discount rate over 15 years, EUR 50/MWh fixed nominal is equivalent in present value to about EUR 45/MWh indexed (own calculation). Indexation shifts inflation risk to the buyer; it is not an upside on its own. | E64: source-based | G64: No = fixed nominal PPA price. Yes = PPA price entered in real 2026 EUR and indexed. | H64: Prices
A66: MARKET PRICES AND CAPTURE RATES (FI DAY-AHEAD, TIME-WEIGHTED, REAL 2026 EUR)
A67: Parameter | B67: Value | C67: Unit | D67: Source / reference | E67: Status | F67: Base / scenario | G67: Notes | H67: Model use
A68: Market price 2026 (observed start value) | B68: 55.78 | C68: €/MWh | D68: Own analysis of Finnish day-ahead prices (project data; https://transparency.entsoe.eu/, accessed 1 Oct 2026): time-weighted average Oct 2025-Sep 2026 = 55.78 EUR/MWh (calendar years, nominal: 2023 56.47; 2024 45.57; 2025 40.47 EUR/MWh). | E68: source-based | F68: All scenarios | G68: Common 2026 start value of all three paths; observed nominal value treated as real 2026 EUR. Level raised by the 2026 energy price shock (ECB staff projections, Sep 2026). | H68: Prices
A69: Market price 2028 (futures anchor) | B69: 53.84 | C69: €/MWh | D69: EEX Finnish Power Future (FI, base, year), Cal-28 settlement 56.02 EUR/MWh nominal, trading day 1 Oct 2026 (eex.com market data, accessed 2 Oct 2026). Real 2026 EUR: 56.02 / (1 + B63)^2 = 53.84 EUR/MWh (own calculation). Further curve for cross-check: Cal-27 62.54, Cal-29 53.29, Cal-30 52.68, Cal-31 52.57, Cal-32 53.28 EUR/MWh nominal. Liquidity not checked; forward prices include a risk premium and the 2026 energy price shock. | E69: source-based | F69: All scenarios | G69: Futures anchor for 2028; all three paths pass through this value. Futures are nominal: enter futures price / (1 + B63)^2 to convert to real 2026 EUR. | H69: Prices
A70: Market price Base 2030 | B70: 48.67 | C70: €/MWh | D70: EEX Finnish Power Future (FI, base, year), Cal-30 settlement 52.68 EUR/MWh nominal, trading day 1 Oct 2026 (eex.com, accessed 2 Oct 2026); real 2026 EUR: 52.68 / (1 + B63)^4 = 48.67 EUR/MWh (own calculation). Cross-check: Lampela (2023), Table 5.2, model v27, scenario x1,2 (94 TWh, 15 GW): 39.0 EUR/MWh; model v36: 20.1. Market forward used for the near term, Lampela from 2040. | E70: source-based | F70: Base | G70: Base 2030 from futures, between the Lampela Low (34.7) and High (56.6) 2030 values. Far-dated futures are thinly traded. | H70: Prices
A71: Market price Base 2040 | B71: 39.8 | C71: €/MWh | D71: Lampela, S. (2023), "Long-term electricity price forecasting in Finland", MSc thesis, Tampere University, Nov 2023, Table 5.4 (model v27): scenario x1,2 = demand 115 TWh, wind 23 GW: 39.8 EUR/MWh. | E71: source-based | F71: Base | G71: Only model v27 available for 2040 and 2050; author stresses trends over exact values. | H71: Prices
A72: Market price Base 2050 | B72: 45.6 | C72: €/MWh | D72: Lampela, S. (2023), "Long-term electricity price forecasting in Finland", MSc thesis, Tampere University, Nov 2023, Table 5.5 (model v27): scenario x1,2 = demand 126 TWh (123 TWh in Table 4.4), wind 30 GW: 45.6 EUR/MWh. | E72: source-based | F72: Base | G72: Held flat in real terms after 2050. | H72: Prices
A73: Market price Low 2030 | B73: 34.7 | C73: €/MWh | D73: Lampela, S. (2023), "Long-term electricity price forecasting in Finland", MSc thesis, Tampere University, Nov 2023, Table 5.2 (model v27): scenario x1,3 = demand 94 TWh, wind 23 GW: 34.7 EUR/MWh (model v36: 15.8). | E73: source-based | F73: Low | G73: Low storyline: wind build-out outpaces demand. Model v27 produces no prices below about 14 EUR/MWh, so low cases are likely overstated. | H73: Prices
A74: Market price Low 2040 | B74: 32.6 | C74: €/MWh | D74: Lampela, S. (2023), "Long-term electricity price forecasting in Finland", MSc thesis, Tampere University, Nov 2023, Table 5.4 (model v27): scenario x1,3 = demand 115 TWh, wind 40 GW: 32.6 EUR/MWh. | E74: source-based | F74: Low | H74: Prices
A75: Market price Low 2050 | B75: 37.4 | C75: €/MWh | D75: Lampela, S. (2023), "Long-term electricity price forecasting in Finland", MSc thesis, Tampere University, Nov 2023, Table 5.5 (model v27): scenario x1,3 = demand 126 TWh, wind 50 GW: 37.4 EUR/MWh. | E75: source-based | F75: Low | G75: Held flat in real terms after 2050. | H75: Prices
A76: Market price High 2030 | B76: 56.6 | C76: €/MWh | D76: Lampela, S. (2023), "Long-term electricity price forecasting in Finland", MSc thesis, Tampere University, Nov 2023, Table 5.2 (model v27): scenario x2,2 = demand 105 TWh, wind 15 GW: 56.6 EUR/MWh (model v36: 34.5). | E76: source-based | F76: High | G76: High storyline: prices stay near today's level (observed 55.78 EUR/MWh, row 68). | H76: Prices
A77: Market price High 2040 | B77: 56.6 | C77: €/MWh | D77: Held at the 2030 High value. Thesis high-demand cells (2040: 85-152 EUR/MWh; 2050: 115-173 EUR/MWh) not used: the author flags the model as unreliable in high-demand scenarios (Lampela 2023, p. 81). | E77: own assumption | F77: High | H77: Prices
A78: Market price High 2050 | B78: 56.6 | C78: €/MWh | D78: Held at the 2030 High value (see row above). | E78: own assumption | F78: High | G78: Held flat in real terms after 2050. | H78: Prices
A79: Capture rate Low | B79: 0.5 | C79: % of time-weighted price | D79: Own analysis of ENTSO-E wind generation (Actual Generation per Production Type, FI) and Finnish day-ahead prices (project data; https://transparency.entsoe.eu/, accessed 1 Oct 2026): capture rate after curtailment of negative-price hours 80.6 % (2023), 74.5 % (2024), 59.1 % (2025), 63.0 % (Oct 2025-Sep 2026); average installed wind capacity rose from about 5.8 to 9.4 GW. | E79: own assumption | F79: Low | G79: Further cannibalisation as Finnish wind capacity grows. Flat over the operating life. | H79: Prices
A80: Capture rate Base | B80: 0.6 | C80: % of time-weighted price | D80: Own analysis of ENTSO-E wind generation (Actual Generation per Production Type, FI) and Finnish day-ahead prices (project data; https://transparency.entsoe.eu/, accessed 1 Oct 2026): capture rate after curtailment of negative-price hours 80.6 % (2023), 74.5 % (2024), 59.1 % (2025), 63.0 % (Oct 2025-Sep 2026); average installed wind capacity rose from about 5.8 to 9.4 GW. Base between 2025 (59.1 %) and the last 12 months (63.0 %). Cross-check: KYOS PPA Insights No. 19 (Jun 2026), Finland 2027-2036: wind capture 36.1 / baseload 60.0 EUR/MWh = 60.2 % (own calculation). Lowest onshore wind capture rate of all zones in the KYOS table (SE3 85 %, DK1 88 %, DE 83 %) | E80: source-based | F80: Base | G80: Flat over the operating life (no trend). Curtailed variant used to match curtailment in B11 (no double counting). | H80: Prices
A81: Capture rate High | B81: 0.7 | C81: % of time-weighted price | D81: Own analysis of ENTSO-E wind generation (Actual Generation per Production Type, FI) and Finnish day-ahead prices (project data; https://transparency.entsoe.eu/, accessed 1 Oct 2026): capture rate after curtailment of negative-price hours 80.6 % (2023), 74.5 % (2024), 59.1 % (2025), 63.0 % (Oct 2025-Sep 2026); average installed wind capacity rose from about 5.8 to 9.4 GW. | E81: own assumption | F81: High | G81: More flexibility (storage, demand response); still below the 2023-2024 levels (74.5-80.6 %). Flat over the operating life. | H81: Prices
A83: Notes on the price anchors: Lampela (2023) is a master's thesis using a neural network trained on data from 2017 to Jul 2022, not a power system model. Model versions v27 and v36 differ by up to about 20 EUR/MWh in 2030; against a Ramboll market model one scenario differs by about 70 EUR/MWh (Lampela 2023, abstract and Table 5.2). The thesis does not state the price basis (real or nominal, price year); values are used unadjusted as real 2026 EUR (to verify; read as 2023 EUR they would be roughly 7-8 % higher, own estimate). Prices interpolates linearly between anchor years and holds real prices flat after 2050 (own assumption). Market price and capture-rate scenarios are independent switches, although low prices and low capture rates tend to occur together. Base path uses EEX futures for 2028 and 2030 (market view) and Lampela from 2040 (fundamental view); the futures sit about 10 EUR/MWh above the Lampela Base 2030 value, suggesting the thesis understates today's price level.

Sheet Prices
A1: PRICES
A3: Capture-rate scenario | B3: =Cover!B16 -> Base
A4: PPA mode | B4: =Cover!B15 -> Yes
A5: Market price scenario | B5: =Cover!B17 -> Base
A6: ANNUAL MARKET PRICE & CAPTURE RATE INPUTS | R6: PRICE PATH ANCHORS (real 2026 EUR/MWh, linked to Inputs)
A7: Year | B7: Market price Base (real 2026 EUR/MWh) | C7: Low capture | D7: Base capture | E7: High capture | F7: Selected capture | G7: Realized price (nominal) | H7: PPA price (nominal) | I7: Selected revenue price (nominal) | J7: PPA volume share | K7: PPA window (1/0) | L7: Inflation index (2026 = 1) | M7: PPA index factor | N7: Market price Low (real 2026 EUR/MWh) | O7: Market price High (real 2026 EUR/MWh) | P7: Selected market price (real 2026 EUR/MWh) | R7: Anchor year | S7: Base | T7: Low | U7: High | V7: Inputs reference
A8: 2026 | B8: =IF($A8>=$R$12,S$12,INDEX(S$8:S$12,MATCH($A8,$R$8:$R$12,1))+(INDEX(S$8:S$12,MATCH($A8,$R$8:$R$12,1)+1)-INDEX(S$8:S$12,MATCH($A8,$R$8:$R$12,1)))*($A8-INDEX($R$8:$R$12,MATCH($A8,$R$8:$R$12,1)))/(INDEX($R$8:$R$12,MATCH($A8,$R$8:$R$12,1)+1)-INDEX($R$8:$R$12,MATCH($A8,$R$8:$R$12,1)))) -> 55.78 | C8: =Inputs!$B$79 -> 0.5 | D8: =Inputs!$B$80 -> 0.6 | E8: =Inputs!$B$81 -> 0.7 | F8: =IF($B$3="Low",C8,IF($B$3="High",E8,D8)) -> 0.6 | G8: =P8*F8*L8 -> 33.468 | H8: =Inputs!B40*M8 -> 50 | I8: =J8*H8+(1-J8)*G8 -> 33.468 | J8: =IF(AND($B$4="Yes",K8=1),Inputs!$B$43,0) -> 0 | K8: =IF(AND(A8>=Inputs!$B$9,A8<Inputs!$B$9+Inputs!$B$44),1,0) -> 0 | L8: =(1+Inputs!$B$63)^(A8-$A$8) -> 1 | M8: =IF(Inputs!$B$64="Yes",L8,1) -> 1 | N8: =IF($A8>=$R$12,T$12,INDEX(T$8:T$12,MATCH($A8,$R$8:$R$12,1))+(INDEX(T$8:T$12,MATCH($A8,$R$8:$R$12,1)+1)-INDEX(T$8:T$12,MATCH($A8,$R$8:$R$12,1)))*($A8-INDEX($R$8:$R$12,MATCH($A8,$R$8:$R$12,1)))/(INDEX($R$8:$R$12,MATCH($A8,$R$8:$R$12,1)+1)-INDEX($R$8:$R$12,MATCH($A8,$R$8:$R$12,1)))) -> 55.78 | O8: =IF($A8>=$R$12,U$12,INDEX(U$8:U$12,MATCH($A8,$R$8:$R$12,1))+(INDEX(U$8:U$12,MATCH($A8,$R$8:$R$12,1)+1)-INDEX(U$8:U$12,MATCH($A8,$R$8:$R$12,1)))*($A8-INDEX($R$8:$R$12,MATCH($A8,$R$8:$R$12,1)))/(INDEX($R$8:$R$12,MATCH($A8,$R$8:$R$12,1)+1)-INDEX($R$8:$R$12,MATCH($A8,$R$8:$R$12,1)))) -> 55.78 | P8: =IF($B$5="Low",N8,IF($B$5="High",O8,B8)) -> 55.78 | R8: 2026 | S8: =Inputs!$B$68 -> 55.78 | T8: =Inputs!$B$68 -> 55.78 | U8: =Inputs!$B$68 -> 55.78 | V8: Inputs 68 (all)
A9: 2027 | B9: =IF($A9>=$R$12,S$12,INDEX(S$8:S$12,MATCH($A9,$R$8:$R$12,1))+(INDEX(S$8:S$12,MATCH($A9,$R$8:$R$12,1)+1)-INDEX(S$8:S$12,MATCH($A9,$R$8:$R$12,1)))*($A9-INDEX($R$8:$R$12,MATCH($A9,$R$8:$R$12,1)))/(INDEX($R$8:$R$12,MATCH($A9,$R$8:$R$12,1)+1)-INDEX($R$8:$R$12,MATCH($A9,$R$8:$R$12,1)))) -> 54.81 | C9: =Inputs!$B$79 -> 0.5 | D9: =Inputs!$B$80 -> 0.6 | E9: =Inputs!$B$81 -> 0.7 | F9: =IF($B$3="Low",C9,IF($B$3="High",E9,D9)) -> 0.6 | G9: =P9*F9*L9 -> 33.54372 | H9: =Inputs!B40*M9 -> 50 | I9: =J9*H9+(1-J9)*G9 -> 33.54372 | J9: =IF(AND($B$4="Yes",K9=1),Inputs!$B$43,0) -> 0 | K9: =IF(AND(A9>=Inputs!$B$9,A9<Inputs!$B$9+Inputs!$B$44),1,0) -> 0 | L9: =(1+Inputs!$B$63)^(A9-$A$8) -> 1.02 | M9: =IF(Inputs!$B$64="Yes",L9,1) -> 1 | N9: =IF($A9>=$R$12,T$12,INDEX(T$8:T$12,MATCH($A9,$R$8:$R$12,1))+(INDEX(T$8:T$12,MATCH($A9,$R$8:$R$12,1)+1)-INDEX(T$8:T$12,MATCH($A9,$R$8:$R$12,1)))*($A9-INDEX($R$8:$R$12,MATCH($A9,$R$8:$R$12,1)))/(INDEX($R$8:$R$12,MATCH($A9,$R$8:$R$12,1)+1)-INDEX($R$8:$R$12,MATCH($A9,$R$8:$R$12,1)))) -> 54.81 | O9: =IF($A9>=$R$12,U$12,INDEX(U$8:U$12,MATCH($A9,$R$8:$R$12,1))+(INDEX(U$8:U$12,MATCH($A9,$R$8:$R$12,1)+1)-INDEX(U$8:U$12,MATCH($A9,$R$8:$R$12,1)))*($A9-INDEX($R$8:$R$12,MATCH($A9,$R$8:$R$12,1)))/(INDEX($R$8:$R$12,MATCH($A9,$R$8:$R$12,1)+1)-INDEX($R$8:$R$12,MATCH($A9,$R$8:$R$12,1)))) -> 54.81 | P9: =IF($B$5="Low",N9,IF($B$5="High",O9,B9)) -> 54.81 | R9: 2028 | S9: =IF(Inputs!$B$69="",S8+(S10-S8)*($R9-$R8)/($R10-$R8),Inputs!$B$69) -> 53.84 | T9: =IF(Inputs!$B$69="",T8+(T10-T8)*($R9-$R8)/($R10-$R8),Inputs!$B$69) -> 53.84 | U9: =IF(Inputs!$B$69="",U8+(U10-U8)*($R9-$R8)/($R10-$R8),Inputs!$B$69) -> 53.84 | V9: Inputs 69 (blank = interpolated)
A10: 2028 | B10: =IF($A10>=$R$12,S$12,INDEX(S$8:S$12,MATCH($A10,$R$8:$R$12,1))+(INDEX(S$8:S$12,MATCH($A10,$R$8:$R$12,1)+1)-INDEX(S$8:S$12,MATCH($A10,$R$8:$R$12,1)))*($A10-INDEX($R$8:$R$12,MATCH($A10,$R$8:$R$12,1)))/(INDEX($R$8:$R$12,MATCH($A10,$R$8:$R$12,1)+1)-INDEX($R$8:$R$12,MATCH($A10,$R$8:$R$12,1)))) -> 53.84 | C10: =Inputs!$B$79 -> 0.5 | D10: =Inputs!$B$80 -> 0.6 | E10: =Inputs!$B$81 -> 0.7 | F10: =IF($B$3="Low",C10,IF($B$3="High",E10,D10)) -> 0.6 | G10: =P10*F10*L10 -> 33.609082 | H10: =Inputs!B40*M10 -> 50 | I10: =J10*H10+(1-J10)*G10 -> 50 | J10: =IF(AND($B$4="Yes",K10=1),Inputs!$B$43,0) -> 1 | K10: =IF(AND(A10>=Inputs!$B$9,A10<Inputs!$B$9+Inputs!$B$44),1,0) -> 1 | L10: =(1+Inputs!$B$63)^(A10-$A$8) -> 1.0404 | M10: =IF(Inputs!$B$64="Yes",L10,1) -> 1 | N10: =IF($A10>=$R$12,T$12,INDEX(T$8:T$12,MATCH($A10,$R$8:$R$12,1))+(INDEX(T$8:T$12,MATCH($A10,$R$8:$R$12,1)+1)-INDEX(T$8:T$12,MATCH($A10,$R$8:$R$12,1)))*($A10-INDEX($R$8:$R$12,MATCH($A10,$R$8:$R$12,1)))/(INDEX($R$8:$R$12,MATCH($A10,$R$8:$R$12,1)+1)-INDEX($R$8:$R$12,MATCH($A10,$R$8:$R$12,1)))) -> 53.84 | O10: =IF($A10>=$R$12,U$12,INDEX(U$8:U$12,MATCH($A10,$R$8:$R$12,1))+(INDEX(U$8:U$12,MATCH($A10,$R$8:$R$12,1)+1)-INDEX(U$8:U$12,MATCH($A10,$R$8:$R$12,1)))*($A10-INDEX($R$8:$R$12,MATCH($A10,$R$8:$R$12,1)))/(INDEX($R$8:$R$12,MATCH($A10,$R$8:$R$12,1)+1)-INDEX($R$8:$R$12,MATCH($A10,$R$8:$R$12,1)))) -> 53.84 | P10: =IF($B$5="Low",N10,IF($B$5="High",O10,B10)) -> 53.84 | R10: 2030 | S10: =Inputs!$B$70 -> 48.67 | T10: =Inputs!$B$73 -> 34.7 | U10: =Inputs!$B$76 -> 56.6 | V10: Base 70 / Low 73 / High 76
A11: 2029 | B11: =IF($A11>=$R$12,S$12,INDEX(S$8:S$12,MATCH($A11,$R$8:$R$12,1))+(INDEX(S$8:S$12,MATCH($A11,$R$8:$R$12,1)+1)-INDEX(S$8:S$12,MATCH($A11,$R$8:$R$12,1)))*($A11-INDEX($R$8:$R$12,MATCH($A11,$R$8:$R$12,1)))/(INDEX($R$8:$R$12,MATCH($A11,$R$8:$R$12,1)+1)-INDEX($R$8:$R$12,MATCH($A11,$R$8:$R$12,1)))) -> 51.255 | C11: =Inputs!$B$79 -> 0.5 | D11: =Inputs!$B$80 -> 0.6 | E11: =Inputs!$B$81 -> 0.7 | F11: =IF($B$3="Low",C11,IF($B$3="High",E11,D11)) -> 0.6 | G11: =P11*F11*L11 -> 32.63533 | H11: =Inputs!B40*M11 -> 50 | I11: =J11*H11+(1-J11)*G11 -> 50 | J11: =IF(AND($B$4="Yes",K11=1),Inputs!$B$43,0) -> 1 | K11: =IF(AND(A11>=Inputs!$B$9,A11<Inputs!$B$9+Inputs!$B$44),1,0) -> 1 | L11: =(1+Inputs!$B$63)^(A11-$A$8) -> 1.061208 | M11: =IF(Inputs!$B$64="Yes",L11,1) -> 1 | N11: =IF($A11>=$R$12,T$12,INDEX(T$8:T$12,MATCH($A11,$R$8:$R$12,1))+(INDEX(T$8:T$12,MATCH($A11,$R$8:$R$12,1)+1)-INDEX(T$8:T$12,MATCH($A11,$R$8:$R$12,1)))*($A11-INDEX($R$8:$R$12,MATCH($A11,$R$8:$R$12,1)))/(INDEX($R$8:$R$12,MATCH($A11,$R$8:$R$12,1)+1)-INDEX($R$8:$R$12,MATCH($A11,$R$8:$R$12,1)))) -> 44.27 | O11: =IF($A11>=$R$12,U$12,INDEX(U$8:U$12,MATCH($A11,$R$8:$R$12,1))+(INDEX(U$8:U$12,MATCH($A11,$R$8:$R$12,1)+1)-INDEX(U$8:U$12,MATCH($A11,$R$8:$R$12,1)))*($A11-INDEX($R$8:$R$12,MATCH($A11,$R$8:$R$12,1)))/(INDEX($R$8:$R$12,MATCH($A11,$R$8:$R$12,1)+1)-INDEX($R$8:$R$12,MATCH($A11,$R$8:$R$12,1)))) -> 55.22 | P11: =IF($B$5="Low",N11,IF($B$5="High",O11,B11)) -> 51.255 | R11: 2040 | S11: =Inputs!$B$71 -> 39.8 | T11: =Inputs!$B$74 -> 32.6 | U11: =Inputs!$B$77 -> 56.6 | V11: Base 71 / Low 74 / High 77
A12: 2030 | B12: =IF($A12>=$R$12,S$12,INDEX(S$8:S$12,MATCH($A12,$R$8:$R$12,1))+(INDEX(S$8:S$12,MATCH($A12,$R$8:$R$12,1)+1)-INDEX(S$8:S$12,MATCH($A12,$R$8:$R$12,1)))*($A12-INDEX($R$8:$R$12,MATCH($A12,$R$8:$R$12,1)))/(INDEX($R$8:$R$12,MATCH($A12,$R$8:$R$12,1)+1)-INDEX($R$8:$R$12,MATCH($A12,$R$8:$R$12,1)))) -> 48.67 | C12: =Inputs!$B$79 -> 0.5 | D12: =Inputs!$B$80 -> 0.6 | E12: =Inputs!$B$81 -> 0.7 | F12: =IF($B$3="Low",C12,IF($B$3="High",E12,D12)) -> 0.6 | G12: =P12*F12*L12 -> 31.609184 | H12: =Inputs!B40*M12 -> 50 | I12: =J12*H12+(1-J12)*G12 -> 50 | J12: =IF(AND($B$4="Yes",K12=1),Inputs!$B$43,0) -> 1 | K12: =IF(AND(A12>=Inputs!$B$9,A12<Inputs!$B$9+Inputs!$B$44),1,0) -> 1 | L12: =(1+Inputs!$B$63)^(A12-$A$8) -> 1.0824322 | M12: =IF(Inputs!$B$64="Yes",L12,1) -> 1 | N12: =IF($A12>=$R$12,T$12,INDEX(T$8:T$12,MATCH($A12,$R$8:$R$12,1))+(INDEX(T$8:T$12,MATCH($A12,$R$8:$R$12,1)+1)-INDEX(T$8:T$12,MATCH($A12,$R$8:$R$12,1)))*($A12-INDEX($R$8:$R$12,MATCH($A12,$R$8:$R$12,1)))/(INDEX($R$8:$R$12,MATCH($A12,$R$8:$R$12,1)+1)-INDEX($R$8:$R$12,MATCH($A12,$R$8:$R$12,1)))) -> 34.7 | O12: =IF($A12>=$R$12,U$12,INDEX(U$8:U$12,MATCH($A12,$R$8:$R$12,1))+(INDEX(U$8:U$12,MATCH($A12,$R$8:$R$12,1)+1)-INDEX(U$8:U$12,MATCH($A12,$R$8:$R$12,1)))*($A12-INDEX($R$8:$R$12,MATCH($A12,$R$8:$R$12,1)))/(INDEX($R$8:$R$12,MATCH($A12,$R$8:$R$12,1)+1)-INDEX($R$8:$R$12,MATCH($A12,$R$8:$R$12,1)))) -> 56.6 | P12: =IF($B$5="Low",N12,IF($B$5="High",O12,B12)) -> 48.67 | R12: 2050 | S12: =Inputs!$B$72 -> 45.6 | T12: =Inputs!$B$75 -> 37.4 | U12: =Inputs!$B$78 -> 56.6 | V12: Base 72 / Low 75 / High 78
A13: 2031 | B13: =IF($A13>=$R$12,S$12,INDEX(S$8:S$12,MATCH($A13,$R$8:$R$12,1))+(INDEX(S$8:S$12,MATCH($A13,$R$8:$R$12,1)+1)-INDEX(S$8:S$12,MATCH($A13,$R$8:$R$12,1)))*($A13-INDEX($R$8:$R$12,MATCH($A13,$R$8:$R$12,1)))/(INDEX($R$8:$R$12,MATCH($A13,$R$8:$R$12,1)+1)-INDEX($R$8:$R$12,MATCH($A13,$R$8:$R$12,1)))) -> 47.783 | C13: =Inputs!$B$79 -> 0.5 | D13: =Inputs!$B$80 -> 0.6 | E13: =Inputs!$B$81 -> 0.7 | F13: =IF($B$3="Low",C13,IF($B$3="High",E13,D13)) -> 0.6 | G13: =P13*F13*L13 -> 31.653776 | H13: =Inputs!B40*M13 -> 50 | I13: =J13*H13+(1-J13)*G13 -> 50 | J13: =IF(AND($B$4="Yes",K13=1),Inputs!$B$43,0) -> 1 | K13: =IF(AND(A13>=Inputs!$B$9,A13<Inputs!$B$9+Inputs!$B$44),1,0) -> 1 | L13: =(1+Inputs!$B$63)^(A13-$A$8) -> 1.1040808 | M13: =IF(Inputs!$B$64="Yes",L13,1) -> 1 | N13: =IF($A13>=$R$12,T$12,INDEX(T$8:T$12,MATCH($A13,$R$8:$R$12,1))+(INDEX(T$8:T$12,MATCH($A13,$R$8:$R$12,1)+1)-INDEX(T$8:T$12,MATCH($A13,$R$8:$R$12,1)))*($A13-INDEX($R$8:$R$12,MATCH($A13,$R$8:$R$12,1)))/(INDEX($R$8:$R$12,MATCH($A13,$R$8:$R$12,1)+1)-INDEX($R$8:$R$12,MATCH($A13,$R$8:$R$12,1)))) -> 34.49 | O13: =IF($A13>=$R$12,U$12,INDEX(U$8:U$12,MATCH($A13,$R$8:$R$12,1))+(INDEX(U$8:U$12,MATCH($A13,$R$8:$R$12,1)+1)-INDEX(U$8:U$12,MATCH($A13,$R$8:$R$12,1)))*($A13-INDEX($R$8:$R$12,MATCH($A13,$R$8:$R$12,1)))/(INDEX($R$8:$R$12,MATCH($A13,$R$8:$R$12,1)+1)-INDEX($R$8:$R$12,MATCH($A13,$R$8:$R$12,1)))) -> 56.6 | P13: =IF($B$5="Low",N13,IF($B$5="High",O13,B13)) -> 47.783
A14: 2032 | B14: =IF($A14>=$R$12,S$12,INDEX(S$8:S$12,MATCH($A14,$R$8:$R$12,1))+(INDEX(S$8:S$12,MATCH($A14,$R$8:$R$12,1)+1)-INDEX(S$8:S$12,MATCH($A14,$R$8:$R$12,1)))*($A14-INDEX($R$8:$R$12,MATCH($A14,$R$8:$R$12,1)))/(INDEX($R$8:$R$12,MATCH($A14,$R$8:$R$12,1)+1)-INDEX($R$8:$R$12,MATCH($A14,$R$8:$R$12,1)))) -> 46.896 | C14: =Inputs!$B$79 -> 0.5 | D14: =Inputs!$B$80 -> 0.6 | E14: =Inputs!$B$81 -> 0.7 | F14: =IF($B$3="Low",C14,IF($B$3="High",E14,D14)) -> 0.6 | G14: =P14*F14*L14 -> 31.687508 | H14: =Inputs!B40*M14 -> 50 | I14: =J14*H14+(1-J14)*G14 -> 50 | J14: =IF(AND($B$4="Yes",K14=1),Inputs!$B$43,0) -> 1 | K14: =IF(AND(A14>=Inputs!$B$9,A14<Inputs!$B$9+Inputs!$B$44),1,0) -> 1 | L14: =(1+Inputs!$B$63)^(A14-$A$8) -> 1.1261624 | M14: =IF(Inputs!$B$64="Yes",L14,1) -> 1 | N14: =IF($A14>=$R$12,T$12,INDEX(T$8:T$12,MATCH($A14,$R$8:$R$12,1))+(INDEX(T$8:T$12,MATCH($A14,$R$8:$R$12,1)+1)-INDEX(T$8:T$12,MATCH($A14,$R$8:$R$12,1)))*($A14-INDEX($R$8:$R$12,MATCH($A14,$R$8:$R$12,1)))/(INDEX($R$8:$R$12,MATCH($A14,$R$8:$R$12,1)+1)-INDEX($R$8:$R$12,MATCH($A14,$R$8:$R$12,1)))) -> 34.28 | O14: =IF($A14>=$R$12,U$12,INDEX(U$8:U$12,MATCH($A14,$R$8:$R$12,1))+(INDEX(U$8:U$12,MATCH($A14,$R$8:$R$12,1)+1)-INDEX(U$8:U$12,MATCH($A14,$R$8:$R$12,1)))*($A14-INDEX($R$8:$R$12,MATCH($A14,$R$8:$R$12,1)))/(INDEX($R$8:$R$12,MATCH($A14,$R$8:$R$12,1)+1)-INDEX($R$8:$R$12,MATCH($A14,$R$8:$R$12,1)))) -> 56.6 | P14: =IF($B$5="Low",N14,IF($B$5="High",O14,B14)) -> 46.896
A15: 2033 | B15: =IF($A15>=$R$12,S$12,INDEX(S$8:S$12,MATCH($A15,$R$8:$R$12,1))+(INDEX(S$8:S$12,MATCH($A15,$R$8:$R$12,1)+1)-INDEX(S$8:S$12,MATCH($A15,$R$8:$R$12,1)))*($A15-INDEX($R$8:$R$12,MATCH($A15,$R$8:$R$12,1)))/(INDEX($R$8:$R$12,MATCH($A15,$R$8:$R$12,1)+1)-INDEX($R$8:$R$12,MATCH($A15,$R$8:$R$12,1)))) -> 46.009 | C15: =Inputs!$B$79 -> 0.5 | D15: =Inputs!$B$80 -> 0.6 | E15: =Inputs!$B$81 -> 0.7 | F15: =IF($B$3="Low",C15,IF($B$3="High",E15,D15)) -> 0.6 | G15: =P15*F15*L15 -> 31.709927 | H15: =Inputs!B40*M15 -> 50 | I15: =J15*H15+(1-J15)*G15 -> 50 | J15: =IF(AND($B$4="Yes",K15=1),Inputs!$B$43,0) -> 1 | K15: =IF(AND(A15>=Inputs!$B$9,A15<Inputs!$B$9+Inputs!$B$44),1,0) -> 1 | L15: =(1+Inputs!$B$63)^(A15-$A$8) -> 1.1486857 | M15: =IF(Inputs!$B$64="Yes",L15,1) -> 1 | N15: =IF($A15>=$R$12,T$12,INDEX(T$8:T$12,MATCH($A15,$R$8:$R$12,1))+(INDEX(T$8:T$12,MATCH($A15,$R$8:$R$12,1)+1)-INDEX(T$8:T$12,MATCH($A15,$R$8:$R$12,1)))*($A15-INDEX($R$8:$R$12,MATCH($A15,$R$8:$R$12,1)))/(INDEX($R$8:$R$12,MATCH($A15,$R$8:$R$12,1)+1)-INDEX($R$8:$R$12,MATCH($A15,$R$8:$R$12,1)))) -> 34.07 | O15: =IF($A15>=$R$12,U$12,INDEX(U$8:U$12,MATCH($A15,$R$8:$R$12,1))+(INDEX(U$8:U$12,MATCH($A15,$R$8:$R$12,1)+1)-INDEX(U$8:U$12,MATCH($A15,$R$8:$R$12,1)))*($A15-INDEX($R$8:$R$12,MATCH($A15,$R$8:$R$12,1)))/(INDEX($R$8:$R$12,MATCH($A15,$R$8:$R$12,1)+1)-INDEX($R$8:$R$12,MATCH($A15,$R$8:$R$12,1)))) -> 56.6 | P15: =IF($B$5="Low",N15,IF($B$5="High",O15,B15)) -> 46.009
A16: 2034 | B16: =IF($A16>=$R$12,S$12,INDEX(S$8:S$12,MATCH($A16,$R$8:$R$12,1))+(INDEX(S$8:S$12,MATCH($A16,$R$8:$R$12,1)+1)-INDEX(S$8:S$12,MATCH($A16,$R$8:$R$12,1)))*($A16-INDEX($R$8:$R$12,MATCH($A16,$R$8:$R$12,1)))/(INDEX($R$8:$R$12,MATCH($A16,$R$8:$R$12,1)+1)-INDEX($R$8:$R$12,MATCH($A16,$R$8:$R$12,1)))) -> 45.122 | C16: =Inputs!$B$79 -> 0.5 | D16: =Inputs!$B$80 -> 0.6 | E16: =Inputs!$B$81 -> 0.7 | F16: =IF($B$3="Low",C16,IF($B$3="High",E16,D16)) -> 0.6 | G16: =P16*F16*L16 -> 31.720569 | H16: =Inputs!B40*M16 -> 50 | I16: =J16*H16+(1-J16)*G16 -> 50 | J16: =IF(AND($B$4="Yes",K16=1),Inputs!$B$43,0) -> 1 | K16: =IF(AND(A16>=Inputs!$B$9,A16<Inputs!$B$9+Inputs!$B$44),1,0) -> 1 | L16: =(1+Inputs!$B$63)^(A16-$A$8) -> 1.1716594 | M16: =IF(Inputs!$B$64="Yes",L16,1) -> 1 | N16: =IF($A16>=$R$12,T$12,INDEX(T$8:T$12,MATCH($A16,$R$8:$R$12,1))+(INDEX(T$8:T$12,MATCH($A16,$R$8:$R$12,1)+1)-INDEX(T$8:T$12,MATCH($A16,$R$8:$R$12,1)))*($A16-INDEX($R$8:$R$12,MATCH($A16,$R$8:$R$12,1)))/(INDEX($R$8:$R$12,MATCH($A16,$R$8:$R$12,1)+1)-INDEX($R$8:$R$12,MATCH($A16,$R$8:$R$12,1)))) -> 33.86 | O16: =IF($A16>=$R$12,U$12,INDEX(U$8:U$12,MATCH($A16,$R$8:$R$12,1))+(INDEX(U$8:U$12,MATCH($A16,$R$8:$R$12,1)+1)-INDEX(U$8:U$12,MATCH($A16,$R$8:$R$12,1)))*($A16-INDEX($R$8:$R$12,MATCH($A16,$R$8:$R$12,1)))/(INDEX($R$8:$R$12,MATCH($A16,$R$8:$R$12,1)+1)-INDEX($R$8:$R$12,MATCH($A16,$R$8:$R$12,1)))) -> 56.6 | P16: =IF($B$5="Low",N16,IF($B$5="High",O16,B16)) -> 45.122
A17: 2035 | B17: =IF($A17>=$R$12,S$12,INDEX(S$8:S$12,MATCH($A17,$R$8:$R$12,1))+(INDEX(S$8:S$12,MATCH($A17,$R$8:$R$12,1)+1)-INDEX(S$8:S$12,MATCH($A17,$R$8:$R$12,1)))*($A17-INDEX($R$8:$R$12,MATCH($A17,$R$8:$R$12,1)))/(INDEX($R$8:$R$12,MATCH($A17,$R$8:$R$12,1)+1)-INDEX($R$8:$R$12,MATCH($A17,$R$8:$R$12,1)))) -> 44.235 | C17: =Inputs!$B$79 -> 0.5 | D17: =Inputs!$B$80 -> 0.6 | E17: =Inputs!$B$81 -> 0.7 | F17: =IF($B$3="Low",C17,IF($B$3="High",E17,D17)) -> 0.6 | G17: =P17*F17*L17 -> 31.718952 | H17: =Inputs!B40*M17 -> 50 | I17: =J17*H17+(1-J17)*G17 -> 50 | J17: =IF(AND($B$4="Yes",K17=1),Inputs!$B$43,0) -> 1 | K17: =IF(AND(A17>=Inputs!$B$9,A17<Inputs!$B$9+Inputs!$B$44),1,0) -> 1 | L17: =(1+Inputs!$B$63)^(A17-$A$8) -> 1.1950926 | M17: =IF(Inputs!$B$64="Yes",L17,1) -> 1 | N17: =IF($A17>=$R$12,T$12,INDEX(T$8:T$12,MATCH($A17,$R$8:$R$12,1))+(INDEX(T$8:T$12,MATCH($A17,$R$8:$R$12,1)+1)-INDEX(T$8:T$12,MATCH($A17,$R$8:$R$12,1)))*($A17-INDEX($R$8:$R$12,MATCH($A17,$R$8:$R$12,1)))/(INDEX($R$8:$R$12,MATCH($A17,$R$8:$R$12,1)+1)-INDEX($R$8:$R$12,MATCH($A17,$R$8:$R$12,1)))) -> 33.65 | O17: =IF($A17>=$R$12,U$12,INDEX(U$8:U$12,MATCH($A17,$R$8:$R$12,1))+(INDEX(U$8:U$12,MATCH($A17,$R$8:$R$12,1)+1)-INDEX(U$8:U$12,MATCH($A17,$R$8:$R$12,1)))*($A17-INDEX($R$8:$R$12,MATCH($A17,$R$8:$R$12,1)))/(INDEX($R$8:$R$12,MATCH($A17,$R$8:$R$12,1)+1)-INDEX($R$8:$R$12,MATCH($A17,$R$8:$R$12,1)))) -> 56.6 | P17: =IF($B$5="Low",N17,IF($B$5="High",O17,B17)) -> 44.235
A18: 2036 | B18: =IF($A18>=$R$12,S$12,INDEX(S$8:S$12,MATCH($A18,$R$8:$R$12,1))+(INDEX(S$8:S$12,MATCH($A18,$R$8:$R$12,1)+1)-INDEX(S$8:S$12,MATCH($A18,$R$8:$R$12,1)))*($A18-INDEX($R$8:$R$12,MATCH($A18,$R$8:$R$12,1)))/(INDEX($R$8:$R$12,MATCH($A18,$R$8:$R$12,1)+1)-INDEX($R$8:$R$12,MATCH($A18,$R$8:$R$12,1)))) -> 43.348 | C18: =Inputs!$B$79 -> 0.5 | D18: =Inputs!$B$80 -> 0.6 | E18: =Inputs!$B$81 -> 0.7 | F18: =IF($B$3="Low",C18,IF($B$3="High",E18,D18)) -> 0.6 | G18: =P18*F18*L18 -> 31.704582 | H18: =Inputs!B40*M18 -> 50 | I18: =J18*H18+(1-J18)*G18 -> 50 | J18: =IF(AND($B$4="Yes",K18=1),Inputs!$B$43,0) -> 1 | K18: =IF(AND(A18>=Inputs!$B$9,A18<Inputs!$B$9+Inputs!$B$44),1,0) -> 1 | L18: =(1+Inputs!$B$63)^(A18-$A$8) -> 1.2189944 | M18: =IF(Inputs!$B$64="Yes",L18,1) -> 1 | N18: =IF($A18>=$R$12,T$12,INDEX(T$8:T$12,MATCH($A18,$R$8:$R$12,1))+(INDEX(T$8:T$12,MATCH($A18,$R$8:$R$12,1)+1)-INDEX(T$8:T$12,MATCH($A18,$R$8:$R$12,1)))*($A18-INDEX($R$8:$R$12,MATCH($A18,$R$8:$R$12,1)))/(INDEX($R$8:$R$12,MATCH($A18,$R$8:$R$12,1)+1)-INDEX($R$8:$R$12,MATCH($A18,$R$8:$R$12,1)))) -> 33.44 | O18: =IF($A18>=$R$12,U$12,INDEX(U$8:U$12,MATCH($A18,$R$8:$R$12,1))+(INDEX(U$8:U$12,MATCH($A18,$R$8:$R$12,1)+1)-INDEX(U$8:U$12,MATCH($A18,$R$8:$R$12,1)))*($A18-INDEX($R$8:$R$12,MATCH($A18,$R$8:$R$12,1)))/(INDEX($R$8:$R$12,MATCH($A18,$R$8:$R$12,1)+1)-INDEX($R$8:$R$12,MATCH($A18,$R$8:$R$12,1)))) -> 56.6 | P18: =IF($B$5="Low",N18,IF($B$5="High",O18,B18)) -> 43.348
A19: 2037 | B19: =IF($A19>=$R$12,S$12,INDEX(S$8:S$12,MATCH($A19,$R$8:$R$12,1))+(INDEX(S$8:S$12,MATCH($A19,$R$8:$R$12,1)+1)-INDEX(S$8:S$12,MATCH($A19,$R$8:$R$12,1)))*($A19-INDEX($R$8:$R$12,MATCH($A19,$R$8:$R$12,1)))/(INDEX($R$8:$R$12,MATCH($A19,$R$8:$R$12,1)+1)-INDEX($R$8:$R$12,MATCH($A19,$R$8:$R$12,1)))) -> 42.461 | C19: =Inputs!$B$79 -> 0.5 | D19: =Inputs!$B$80 -> 0.6 | E19: =Inputs!$B$81 -> 0.7 | F19: =IF($B$3="Low",C19,IF($B$3="High",E19,D19)) -> 0.6 | G19: =P19*F19*L19 -> 31.67695 | H19: =Inputs!B40*M19 -> 50 | I19: =J19*H19+(1-J19)*G19 -> 50 | J19: =IF(AND($B$4="Yes",K19=1),Inputs!$B$43,0) -> 1 | K19: =IF(AND(A19>=Inputs!$B$9,A19<Inputs!$B$9+Inputs!$B$44),1,0) -> 1 | L19: =(1+Inputs!$B$63)^(A19-$A$8) -> 1.2433743 | M19: =IF(Inputs!$B$64="Yes",L19,1) -> 1 | N19: =IF($A19>=$R$12,T$12,INDEX(T$8:T$12,MATCH($A19,$R$8:$R$12,1))+(INDEX(T$8:T$12,MATCH($A19,$R$8:$R$12,1)+1)-INDEX(T$8:T$12,MATCH($A19,$R$8:$R$12,1)))*($A19-INDEX($R$8:$R$12,MATCH($A19,$R$8:$R$12,1)))/(INDEX($R$8:$R$12,MATCH($A19,$R$8:$R$12,1)+1)-INDEX($R$8:$R$12,MATCH($A19,$R$8:$R$12,1)))) -> 33.23 | O19: =IF($A19>=$R$12,U$12,INDEX(U$8:U$12,MATCH($A19,$R$8:$R$12,1))+(INDEX(U$8:U$12,MATCH($A19,$R$8:$R$12,1)+1)-INDEX(U$8:U$12,MATCH($A19,$R$8:$R$12,1)))*($A19-INDEX($R$8:$R$12,MATCH($A19,$R$8:$R$12,1)))/(INDEX($R$8:$R$12,MATCH($A19,$R$8:$R$12,1)+1)-INDEX($R$8:$R$12,MATCH($A19,$R$8:$R$12,1)))) -> 56.6 | P19: =IF($B$5="Low",N19,IF($B$5="High",O19,B19)) -> 42.461
A20: 2038 | B20: =IF($A20>=$R$12,S$12,INDEX(S$8:S$12,MATCH($A20,$R$8:$R$12,1))+(INDEX(S$8:S$12,MATCH($A20,$R$8:$R$12,1)+1)-INDEX(S$8:S$12,MATCH($A20,$R$8:$R$12,1)))*($A20-INDEX($R$8:$R$12,MATCH($A20,$R$8:$R$12,1)))/(INDEX($R$8:$R$12,MATCH($A20,$R$8:$R$12,1)+1)-INDEX($R$8:$R$12,MATCH($A20,$R$8:$R$12,1)))) -> 41.574 | C20: =Inputs!$B$79 -> 0.5 | D20: =Inputs!$B$80 -> 0.6 | E20: =Inputs!$B$81 -> 0.7 | F20: =IF($B$3="Low",C20,IF($B$3="High",E20,D20)) -> 0.6 | G20: =P20*F20*L20 -> 31.635531 | H20: =Inputs!B40*M20 -> 50 | I20: =J20*H20+(1-J20)*G20 -> 50 | J20: =IF(AND($B$4="Yes",K20=1),Inputs!$B$43,0) -> 1 | K20: =IF(AND(A20>=Inputs!$B$9,A20<Inputs!$B$9+Inputs!$B$44),1,0) -> 1 | L20: =(1+Inputs!$B$63)^(A20-$A$8) -> 1.2682418 | M20: =IF(Inputs!$B$64="Yes",L20,1) -> 1 | N20: =IF($A20>=$R$12,T$12,INDEX(T$8:T$12,MATCH($A20,$R$8:$R$12,1))+(INDEX(T$8:T$12,MATCH($A20,$R$8:$R$12,1)+1)-INDEX(T$8:T$12,MATCH($A20,$R$8:$R$12,1)))*($A20-INDEX($R$8:$R$12,MATCH($A20,$R$8:$R$12,1)))/(INDEX($R$8:$R$12,MATCH($A20,$R$8:$R$12,1)+1)-INDEX($R$8:$R$12,MATCH($A20,$R$8:$R$12,1)))) -> 33.02 | O20: =IF($A20>=$R$12,U$12,INDEX(U$8:U$12,MATCH($A20,$R$8:$R$12,1))+(INDEX(U$8:U$12,MATCH($A20,$R$8:$R$12,1)+1)-INDEX(U$8:U$12,MATCH($A20,$R$8:$R$12,1)))*($A20-INDEX($R$8:$R$12,MATCH($A20,$R$8:$R$12,1)))/(INDEX($R$8:$R$12,MATCH($A20,$R$8:$R$12,1)+1)-INDEX($R$8:$R$12,MATCH($A20,$R$8:$R$12,1)))) -> 56.6 | P20: =IF($B$5="Low",N20,IF($B$5="High",O20,B20)) -> 41.574
A21: 2039 | B21: =IF($A21>=$R$12,S$12,INDEX(S$8:S$12,MATCH($A21,$R$8:$R$12,1))+(INDEX(S$8:S$12,MATCH($A21,$R$8:$R$12,1)+1)-INDEX(S$8:S$12,MATCH($A21,$R$8:$R$12,1)))*($A21-INDEX($R$8:$R$12,MATCH($A21,$R$8:$R$12,1)))/(INDEX($R$8:$R$12,MATCH($A21,$R$8:$R$12,1)+1)-INDEX($R$8:$R$12,MATCH($A21,$R$8:$R$12,1)))) -> 40.687 | C21: =Inputs!$B$79 -> 0.5 | D21: =Inputs!$B$80 -> 0.6 | E21: =Inputs!$B$81 -> 0.7 | F21: =IF($B$3="Low",C21,IF($B$3="High",E21,D21)) -> 0.6 | G21: =P21*F21*L21 -> 31.579784 | H21: =Inputs!B40*M21 -> 50 | I21: =J21*H21+(1-J21)*G21 -> 50 | J21: =IF(AND($B$4="Yes",K21=1),Inputs!$B$43,0) -> 1 | K21: =IF(AND(A21>=Inputs!$B$9,A21<Inputs!$B$9+Inputs!$B$44),1,0) -> 1 | L21: =(1+Inputs!$B$63)^(A21-$A$8) -> 1.2936066 | M21: =IF(Inputs!$B$64="Yes",L21,1) -> 1 | N21: =IF($A21>=$R$12,T$12,INDEX(T$8:T$12,MATCH($A21,$R$8:$R$12,1))+(INDEX(T$8:T$12,MATCH($A21,$R$8:$R$12,1)+1)-INDEX(T$8:T$12,MATCH($A21,$R$8:$R$12,1)))*($A21-INDEX($R$8:$R$12,MATCH($A21,$R$8:$R$12,1)))/(INDEX($R$8:$R$12,MATCH($A21,$R$8:$R$12,1)+1)-INDEX($R$8:$R$12,MATCH($A21,$R$8:$R$12,1)))) -> 32.81 | O21: =IF($A21>=$R$12,U$12,INDEX(U$8:U$12,MATCH($A21,$R$8:$R$12,1))+(INDEX(U$8:U$12,MATCH($A21,$R$8:$R$12,1)+1)-INDEX(U$8:U$12,MATCH($A21,$R$8:$R$12,1)))*($A21-INDEX($R$8:$R$12,MATCH($A21,$R$8:$R$12,1)))/(INDEX($R$8:$R$12,MATCH($A21,$R$8:$R$12,1)+1)-INDEX($R$8:$R$12,MATCH($A21,$R$8:$R$12,1)))) -> 56.6 | P21: =IF($B$5="Low",N21,IF($B$5="High",O21,B21)) -> 40.687
A22: 2040 | B22: =IF($A22>=$R$12,S$12,INDEX(S$8:S$12,MATCH($A22,$R$8:$R$12,1))+(INDEX(S$8:S$12,MATCH($A22,$R$8:$R$12,1)+1)-INDEX(S$8:S$12,MATCH($A22,$R$8:$R$12,1)))*($A22-INDEX($R$8:$R$12,MATCH($A22,$R$8:$R$12,1)))/(INDEX($R$8:$R$12,MATCH($A22,$R$8:$R$12,1)+1)-INDEX($R$8:$R$12,MATCH($A22,$R$8:$R$12,1)))) -> 39.8 | C22: =Inputs!$B$79 -> 0.5 | D22: =Inputs!$B$80 -> 0.6 | E22: =Inputs!$B$81 -> 0.7 | F22: =IF($B$3="Low",C22,IF($B$3="High",E22,D22)) -> 0.6 | G22: =P22*F22*L22 -> 31.509153 | H22: =Inputs!B40*M22 -> 50 | I22: =J22*H22+(1-J22)*G22 -> 50 | J22: =IF(AND($B$4="Yes",K22=1),Inputs!$B$43,0) -> 1 | K22: =IF(AND(A22>=Inputs!$B$9,A22<Inputs!$B$9+Inputs!$B$44),1,0) -> 1 | L22: =(1+Inputs!$B$63)^(A22-$A$8) -> 1.3194788 | M22: =IF(Inputs!$B$64="Yes",L22,1) -> 1 | N22: =IF($A22>=$R$12,T$12,INDEX(T$8:T$12,MATCH($A22,$R$8:$R$12,1))+(INDEX(T$8:T$12,MATCH($A22,$R$8:$R$12,1)+1)-INDEX(T$8:T$12,MATCH($A22,$R$8:$R$12,1)))*($A22-INDEX($R$8:$R$12,MATCH($A22,$R$8:$R$12,1)))/(INDEX($R$8:$R$12,MATCH($A22,$R$8:$R$12,1)+1)-INDEX($R$8:$R$12,MATCH($A22,$R$8:$R$12,1)))) -> 32.6 | O22: =IF($A22>=$R$12,U$12,INDEX(U$8:U$12,MATCH($A22,$R$8:$R$12,1))+(INDEX(U$8:U$12,MATCH($A22,$R$8:$R$12,1)+1)-INDEX(U$8:U$12,MATCH($A22,$R$8:$R$12,1)))*($A22-INDEX($R$8:$R$12,MATCH($A22,$R$8:$R$12,1)))/(INDEX($R$8:$R$12,MATCH($A22,$R$8:$R$12,1)+1)-INDEX($R$8:$R$12,MATCH($A22,$R$8:$R$12,1)))) -> 56.6 | P22: =IF($B$5="Low",N22,IF($B$5="High",O22,B22)) -> 39.8
A23: 2041 | B23: =IF($A23>=$R$12,S$12,INDEX(S$8:S$12,MATCH($A23,$R$8:$R$12,1))+(INDEX(S$8:S$12,MATCH($A23,$R$8:$R$12,1)+1)-INDEX(S$8:S$12,MATCH($A23,$R$8:$R$12,1)))*($A23-INDEX($R$8:$R$12,MATCH($A23,$R$8:$R$12,1)))/(INDEX($R$8:$R$12,MATCH($A23,$R$8:$R$12,1)+1)-INDEX($R$8:$R$12,MATCH($A23,$R$8:$R$12,1)))) -> 40.38 | C23: =Inputs!$B$79 -> 0.5 | D23: =Inputs!$B$80 -> 0.6 | E23: =Inputs!$B$81 -> 0.7 | F23: =IF($B$3="Low",C23,IF($B$3="High",E23,D23)) -> 0.6 | G23: =P23*F23*L23 -> 32.607698 | H23: =Inputs!B40*M23 -> 50 | I23: =J23*H23+(1-J23)*G23 -> 50 | J23: =IF(AND($B$4="Yes",K23=1),Inputs!$B$43,0) -> 1 | K23: =IF(AND(A23>=Inputs!$B$9,A23<Inputs!$B$9+Inputs!$B$44),1,0) -> 1 | L23: =(1+Inputs!$B$63)^(A23-$A$8) -> 1.3458683 | M23: =IF(Inputs!$B$64="Yes",L23,1) -> 1 | N23: =IF($A23>=$R$12,T$12,INDEX(T$8:T$12,MATCH($A23,$R$8:$R$12,1))+(INDEX(T$8:T$12,MATCH($A23,$R$8:$R$12,1)+1)-INDEX(T$8:T$12,MATCH($A23,$R$8:$R$12,1)))*($A23-INDEX($R$8:$R$12,MATCH($A23,$R$8:$R$12,1)))/(INDEX($R$8:$R$12,MATCH($A23,$R$8:$R$12,1)+1)-INDEX($R$8:$R$12,MATCH($A23,$R$8:$R$12,1)))) -> 33.08 | O23: =IF($A23>=$R$12,U$12,INDEX(U$8:U$12,MATCH($A23,$R$8:$R$12,1))+(INDEX(U$8:U$12,MATCH($A23,$R$8:$R$12,1)+1)-INDEX(U$8:U$12,MATCH($A23,$R$8:$R$12,1)))*($A23-INDEX($R$8:$R$12,MATCH($A23,$R$8:$R$12,1)))/(INDEX($R$8:$R$12,MATCH($A23,$R$8:$R$12,1)+1)-INDEX($R$8:$R$12,MATCH($A23,$R$8:$R$12,1)))) -> 56.6 | P23: =IF($B$5="Low",N23,IF($B$5="High",O23,B23)) -> 40.38
A24: 2042 | B24: =IF($A24>=$R$12,S$12,INDEX(S$8:S$12,MATCH($A24,$R$8:$R$12,1))+(INDEX(S$8:S$12,MATCH($A24,$R$8:$R$12,1)+1)-INDEX(S$8:S$12,MATCH($A24,$R$8:$R$12,1)))*($A24-INDEX($R$8:$R$12,MATCH($A24,$R$8:$R$12,1)))/(INDEX($R$8:$R$12,MATCH($A24,$R$8:$R$12,1)+1)-INDEX($R$8:$R$12,MATCH($A24,$R$8:$R$12,1)))) -> 40.96 | C24: =Inputs!$B$79 -> 0.5 | D24: =Inputs!$B$80 -> 0.6 | E24: =Inputs!$B$81 -> 0.7 | F24: =IF($B$3="Low",C24,IF($B$3="High",E24,D24)) -> 0.6 | G24: =P24*F24*L24 -> 33.737581 | H24: =Inputs!B40*M24 -> 50 | I24: =J24*H24+(1-J24)*G24 -> 50 | J24: =IF(AND($B$4="Yes",K24=1),Inputs!$B$43,0) -> 1 | K24: =IF(AND(A24>=Inputs!$B$9,A24<Inputs!$B$9+Inputs!$B$44),1,0) -> 1 | L24: =(1+Inputs!$B$63)^(A24-$A$8) -> 1.3727857 | M24: =IF(Inputs!$B$64="Yes",L24,1) -> 1 | N24: =IF($A24>=$R$12,T$12,INDEX(T$8:T$12,MATCH($A24,$R$8:$R$12,1))+(INDEX(T$8:T$12,MATCH($A24,$R$8:$R$12,1)+1)-INDEX(T$8:T$12,MATCH($A24,$R$8:$R$12,1)))*($A24-INDEX($R$8:$R$12,MATCH($A24,$R$8:$R$12,1)))/(INDEX($R$8:$R$12,MATCH($A24,$R$8:$R$12,1)+1)-INDEX($R$8:$R$12,MATCH($A24,$R$8:$R$12,1)))) -> 33.56 | O24: =IF($A24>=$R$12,U$12,INDEX(U$8:U$12,MATCH($A24,$R$8:$R$12,1))+(INDEX(U$8:U$12,MATCH($A24,$R$8:$R$12,1)+1)-INDEX(U$8:U$12,MATCH($A24,$R$8:$R$12,1)))*($A24-INDEX($R$8:$R$12,MATCH($A24,$R$8:$R$12,1)))/(INDEX($R$8:$R$12,MATCH($A24,$R$8:$R$12,1)+1)-INDEX($R$8:$R$12,MATCH($A24,$R$8:$R$12,1)))) -> 56.6 | P24: =IF($B$5="Low",N24,IF($B$5="High",O24,B24)) -> 40.96
A25: 2043 | B25: =IF($A25>=$R$12,S$12,INDEX(S$8:S$12,MATCH($A25,$R$8:$R$12,1))+(INDEX(S$8:S$12,MATCH($A25,$R$8:$R$12,1)+1)-INDEX(S$8:S$12,MATCH($A25,$R$8:$R$12,1)))*($A25-INDEX($R$8:$R$12,MATCH($A25,$R$8:$R$12,1)))/(INDEX($R$8:$R$12,MATCH($A25,$R$8:$R$12,1)+1)-INDEX($R$8:$R$12,MATCH($A25,$R$8:$R$12,1)))) -> 41.54 | C25: =Inputs!$B$79 -> 0.5 | D25: =Inputs!$B$80 -> 0.6 | E25: =Inputs!$B$81 -> 0.7 | F25: =IF($B$3="Low",C25,IF($B$3="High",E25,D25)) -> 0.6 | G25: =P25*F25*L25 -> 34.899617 | H25: =Inputs!B40*M25 -> 50 | I25: =J25*H25+(1-J25)*G25 -> 34.899617 | J25: =IF(AND($B$4="Yes",K25=1),Inputs!$B$43,0) -> 0 | K25: =IF(AND(A25>=Inputs!$B$9,A25<Inputs!$B$9+Inputs!$B$44),1,0) -> 0 | L25: =(1+Inputs!$B$63)^(A25-$A$8) -> 1.4002414 | M25: =IF(Inputs!$B$64="Yes",L25,1) -> 1 | N25: =IF($A25>=$R$12,T$12,INDEX(T$8:T$12,MATCH($A25,$R$8:$R$12,1))+(INDEX(T$8:T$12,MATCH($A25,$R$8:$R$12,1)+1)-INDEX(T$8:T$12,MATCH($A25,$R$8:$R$12,1)))*($A25-INDEX($R$8:$R$12,MATCH($A25,$R$8:$R$12,1)))/(INDEX($R$8:$R$12,MATCH($A25,$R$8:$R$12,1)+1)-INDEX($R$8:$R$12,MATCH($A25,$R$8:$R$12,1)))) -> 34.04 | O25: =IF($A25>=$R$12,U$12,INDEX(U$8:U$12,MATCH($A25,$R$8:$R$12,1))+(INDEX(U$8:U$12,MATCH($A25,$R$8:$R$12,1)+1)-INDEX(U$8:U$12,MATCH($A25,$R$8:$R$12,1)))*($A25-INDEX($R$8:$R$12,MATCH($A25,$R$8:$R$12,1)))/(INDEX($R$8:$R$12,MATCH($A25,$R$8:$R$12,1)+1)-INDEX($R$8:$R$12,MATCH($A25,$R$8:$R$12,1)))) -> 56.6 | P25: =IF($B$5="Low",N25,IF($B$5="High",O25,B25)) -> 41.54
A26: 2044 | B26: =IF($A26>=$R$12,S$12,INDEX(S$8:S$12,MATCH($A26,$R$8:$R$12,1))+(INDEX(S$8:S$12,MATCH($A26,$R$8:$R$12,1)+1)-INDEX(S$8:S$12,MATCH($A26,$R$8:$R$12,1)))*($A26-INDEX($R$8:$R$12,MATCH($A26,$R$8:$R$12,1)))/(INDEX($R$8:$R$12,MATCH($A26,$R$8:$R$12,1)+1)-INDEX($R$8:$R$12,MATCH($A26,$R$8:$R$12,1)))) -> 42.12 | C26: =Inputs!$B$79 -> 0.5 | D26: =Inputs!$B$80 -> 0.6 | E26: =Inputs!$B$81 -> 0.7 | F26: =IF($B$3="Low",C26,IF($B$3="High",E26,D26)) -> 0.6 | G26: =P26*F26*L26 -> 36.094639 | H26: =Inputs!B40*M26 -> 50 | I26: =J26*H26+(1-J26)*G26 -> 36.094639 | J26: =IF(AND($B$4="Yes",K26=1),Inputs!$B$43,0) -> 0 | K26: =IF(AND(A26>=Inputs!$B$9,A26<Inputs!$B$9+Inputs!$B$44),1,0) -> 0 | L26: =(1+Inputs!$B$63)^(A26-$A$8) -> 1.4282462 | M26: =IF(Inputs!$B$64="Yes",L26,1) -> 1 | N26: =IF($A26>=$R$12,T$12,INDEX(T$8:T$12,MATCH($A26,$R$8:$R$12,1))+(INDEX(T$8:T$12,MATCH($A26,$R$8:$R$12,1)+1)-INDEX(T$8:T$12,MATCH($A26,$R$8:$R$12,1)))*($A26-INDEX($R$8:$R$12,MATCH($A26,$R$8:$R$12,1)))/(INDEX($R$8:$R$12,MATCH($A26,$R$8:$R$12,1)+1)-INDEX($R$8:$R$12,MATCH($A26,$R$8:$R$12,1)))) -> 34.52 | O26: =IF($A26>=$R$12,U$12,INDEX(U$8:U$12,MATCH($A26,$R$8:$R$12,1))+(INDEX(U$8:U$12,MATCH($A26,$R$8:$R$12,1)+1)-INDEX(U$8:U$12,MATCH($A26,$R$8:$R$12,1)))*($A26-INDEX($R$8:$R$12,MATCH($A26,$R$8:$R$12,1)))/(INDEX($R$8:$R$12,MATCH($A26,$R$8:$R$12,1)+1)-INDEX($R$8:$R$12,MATCH($A26,$R$8:$R$12,1)))) -> 56.6 | P26: =IF($B$5="Low",N26,IF($B$5="High",O26,B26)) -> 42.12
A27: 2045 | B27: =IF($A27>=$R$12,S$12,INDEX(S$8:S$12,MATCH($A27,$R$8:$R$12,1))+(INDEX(S$8:S$12,MATCH($A27,$R$8:$R$12,1)+1)-INDEX(S$8:S$12,MATCH($A27,$R$8:$R$12,1)))*($A27-INDEX($R$8:$R$12,MATCH($A27,$R$8:$R$12,1)))/(INDEX($R$8:$R$12,MATCH($A27,$R$8:$R$12,1)+1)-INDEX($R$8:$R$12,MATCH($A27,$R$8:$R$12,1)))) -> 42.7 | C27: =Inputs!$B$79 -> 0.5 | D27: =Inputs!$B$80 -> 0.6 | E27: =Inputs!$B$81 -> 0.7 | F27: =IF($B$3="Low",C27,IF($B$3="High",E27,D27)) -> 0.6 | G27: =P27*F27*L27 -> 37.323502 | H27: =Inputs!B40*M27 -> 50 | I27: =J27*H27+(1-J27)*G27 -> 37.323502 | J27: =IF(AND($B$4="Yes",K27=1),Inputs!$B$43,0) -> 0 | K27: =IF(AND(A27>=Inputs!$B$9,A27<Inputs!$B$9+Inputs!$B$44),1,0) -> 0 | L27: =(1+Inputs!$B$63)^(A27-$A$8) -> 1.4568112 | M27: =IF(Inputs!$B$64="Yes",L27,1) -> 1 | N27: =IF($A27>=$R$12,T$12,INDEX(T$8:T$12,MATCH($A27,$R$8:$R$12,1))+(INDEX(T$8:T$12,MATCH($A27,$R$8:$R$12,1)+1)-INDEX(T$8:T$12,MATCH($A27,$R$8:$R$12,1)))*($A27-INDEX($R$8:$R$12,MATCH($A27,$R$8:$R$12,1)))/(INDEX($R$8:$R$12,MATCH($A27,$R$8:$R$12,1)+1)-INDEX($R$8:$R$12,MATCH($A27,$R$8:$R$12,1)))) -> 35 | O27: =IF($A27>=$R$12,U$12,INDEX(U$8:U$12,MATCH($A27,$R$8:$R$12,1))+(INDEX(U$8:U$12,MATCH($A27,$R$8:$R$12,1)+1)-INDEX(U$8:U$12,MATCH($A27,$R$8:$R$12,1)))*($A27-INDEX($R$8:$R$12,MATCH($A27,$R$8:$R$12,1)))/(INDEX($R$8:$R$12,MATCH($A27,$R$8:$R$12,1)+1)-INDEX($R$8:$R$12,MATCH($A27,$R$8:$R$12,1)))) -> 56.6 | P27: =IF($B$5="Low",N27,IF($B$5="High",O27,B27)) -> 42.7
A28: 2046 | B28: =IF($A28>=$R$12,S$12,INDEX(S$8:S$12,MATCH($A28,$R$8:$R$12,1))+(INDEX(S$8:S$12,MATCH($A28,$R$8:$R$12,1)+1)-INDEX(S$8:S$12,MATCH($A28,$R$8:$R$12,1)))*($A28-INDEX($R$8:$R$12,MATCH($A28,$R$8:$R$12,1)))/(INDEX($R$8:$R$12,MATCH($A28,$R$8:$R$12,1)+1)-INDEX($R$8:$R$12,MATCH($A28,$R$8:$R$12,1)))) -> 43.28 | C28: =Inputs!$B$79 -> 0.5 | D28: =Inputs!$B$80 -> 0.6 | E28: =Inputs!$B$81 -> 0.7 | F28: =IF($B$3="Low",C28,IF($B$3="High",E28,D28)) -> 0.6 | G28: =P28*F28*L28 -> 38.587082 | H28: =Inputs!B40*M28 -> 50 | I28: =J28*H28+(1-J28)*G28 -> 38.587082 | J28: =IF(AND($B$4="Yes",K28=1),Inputs!$B$43,0) -> 0 | K28: =IF(AND(A28>=Inputs!$B$9,A28<Inputs!$B$9+Inputs!$B$44),1,0) -> 0 | L28: =(1+Inputs!$B$63)^(A28-$A$8) -> 1.4859474 | M28: =IF(Inputs!$B$64="Yes",L28,1) -> 1 | N28: =IF($A28>=$R$12,T$12,INDEX(T$8:T$12,MATCH($A28,$R$8:$R$12,1))+(INDEX(T$8:T$12,MATCH($A28,$R$8:$R$12,1)+1)-INDEX(T$8:T$12,MATCH($A28,$R$8:$R$12,1)))*($A28-INDEX($R$8:$R$12,MATCH($A28,$R$8:$R$12,1)))/(INDEX($R$8:$R$12,MATCH($A28,$R$8:$R$12,1)+1)-INDEX($R$8:$R$12,MATCH($A28,$R$8:$R$12,1)))) -> 35.48 | O28: =IF($A28>=$R$12,U$12,INDEX(U$8:U$12,MATCH($A28,$R$8:$R$12,1))+(INDEX(U$8:U$12,MATCH($A28,$R$8:$R$12,1)+1)-INDEX(U$8:U$12,MATCH($A28,$R$8:$R$12,1)))*($A28-INDEX($R$8:$R$12,MATCH($A28,$R$8:$R$12,1)))/(INDEX($R$8:$R$12,MATCH($A28,$R$8:$R$12,1)+1)-INDEX($R$8:$R$12,MATCH($A28,$R$8:$R$12,1)))) -> 56.6 | P28: =IF($B$5="Low",N28,IF($B$5="High",O28,B28)) -> 43.28
A29: 2047 | B29: =IF($A29>=$R$12,S$12,INDEX(S$8:S$12,MATCH($A29,$R$8:$R$12,1))+(INDEX(S$8:S$12,MATCH($A29,$R$8:$R$12,1)+1)-INDEX(S$8:S$12,MATCH($A29,$R$8:$R$12,1)))*($A29-INDEX($R$8:$R$12,MATCH($A29,$R$8:$R$12,1)))/(INDEX($R$8:$R$12,MATCH($A29,$R$8:$R$12,1)+1)-INDEX($R$8:$R$12,MATCH($A29,$R$8:$R$12,1)))) -> 43.86 | C29: =Inputs!$B$79 -> 0.5 | D29: =Inputs!$B$80 -> 0.6 | E29: =Inputs!$B$81 -> 0.7 | F29: =IF($B$3="Low",C29,IF($B$3="High",E29,D29)) -> 0.6 | G29: =P29*F29*L29 -> 39.886276 | H29: =Inputs!B40*M29 -> 50 | I29: =J29*H29+(1-J29)*G29 -> 39.886276 | J29: =IF(AND($B$4="Yes",K29=1),Inputs!$B$43,0) -> 0 | K29: =IF(AND(A29>=Inputs!$B$9,A29<Inputs!$B$9+Inputs!$B$44),1,0) -> 0 | L29: =(1+Inputs!$B$63)^(A29-$A$8) -> 1.5156663 | M29: =IF(Inputs!$B$64="Yes",L29,1) -> 1 | N29: =IF($A29>=$R$12,T$12,INDEX(T$8:T$12,MATCH($A29,$R$8:$R$12,1))+(INDEX(T$8:T$12,MATCH($A29,$R$8:$R$12,1)+1)-INDEX(T$8:T$12,MATCH($A29,$R$8:$R$12,1)))*($A29-INDEX($R$8:$R$12,MATCH($A29,$R$8:$R$12,1)))/(INDEX($R$8:$R$12,MATCH($A29,$R$8:$R$12,1)+1)-INDEX($R$8:$R$12,MATCH($A29,$R$8:$R$12,1)))) -> 35.96 | O29: =IF($A29>=$R$12,U$12,INDEX(U$8:U$12,MATCH($A29,$R$8:$R$12,1))+(INDEX(U$8:U$12,MATCH($A29,$R$8:$R$12,1)+1)-INDEX(U$8:U$12,MATCH($A29,$R$8:$R$12,1)))*($A29-INDEX($R$8:$R$12,MATCH($A29,$R$8:$R$12,1)))/(INDEX($R$8:$R$12,MATCH($A29,$R$8:$R$12,1)+1)-INDEX($R$8:$R$12,MATCH($A29,$R$8:$R$12,1)))) -> 56.6 | P29: =IF($B$5="Low",N29,IF($B$5="High",O29,B29)) -> 43.86
A30: 2048 | B30: =IF($A30>=$R$12,S$12,INDEX(S$8:S$12,MATCH($A30,$R$8:$R$12,1))+(INDEX(S$8:S$12,MATCH($A30,$R$8:$R$12,1)+1)-INDEX(S$8:S$12,MATCH($A30,$R$8:$R$12,1)))*($A30-INDEX($R$8:$R$12,MATCH($A30,$R$8:$R$12,1)))/(INDEX($R$8:$R$12,MATCH($A30,$R$8:$R$12,1)+1)-INDEX($R$8:$R$12,MATCH($A30,$R$8:$R$12,1)))) -> 44.44 | C30: =Inputs!$B$79 -> 0.5 | D30: =Inputs!$B$80 -> 0.6 | E30: =Inputs!$B$81 -> 0.7 | F30: =IF($B$3="Low",C30,IF($B$3="High",E30,D30)) -> 0.6 | G30: =P30*F30*L30 -> 41.222002 | H30: =Inputs!B40*M30 -> 50 | I30: =J30*H30+(1-J30)*G30 -> 41.222002 | J30: =IF(AND($B$4="Yes",K30=1),Inputs!$B$43,0) -> 0 | K30: =IF(AND(A30>=Inputs!$B$9,A30<Inputs!$B$9+Inputs!$B$44),1,0) -> 0 | L30: =(1+Inputs!$B$63)^(A30-$A$8) -> 1.5459797 | M30: =IF(Inputs!$B$64="Yes",L30,1) -> 1 | N30: =IF($A30>=$R$12,T$12,INDEX(T$8:T$12,MATCH($A30,$R$8:$R$12,1))+(INDEX(T$8:T$12,MATCH($A30,$R$8:$R$12,1)+1)-INDEX(T$8:T$12,MATCH($A30,$R$8:$R$12,1)))*($A30-INDEX($R$8:$R$12,MATCH($A30,$R$8:$R$12,1)))/(INDEX($R$8:$R$12,MATCH($A30,$R$8:$R$12,1)+1)-INDEX($R$8:$R$12,MATCH($A30,$R$8:$R$12,1)))) -> 36.44 | O30: =IF($A30>=$R$12,U$12,INDEX(U$8:U$12,MATCH($A30,$R$8:$R$12,1))+(INDEX(U$8:U$12,MATCH($A30,$R$8:$R$12,1)+1)-INDEX(U$8:U$12,MATCH($A30,$R$8:$R$12,1)))*($A30-INDEX($R$8:$R$12,MATCH($A30,$R$8:$R$12,1)))/(INDEX($R$8:$R$12,MATCH($A30,$R$8:$R$12,1)+1)-INDEX($R$8:$R$12,MATCH($A30,$R$8:$R$12,1)))) -> 56.6 | P30: =IF($B$5="Low",N30,IF($B$5="High",O30,B30)) -> 44.44
A31: 2049 | B31: =IF($A31>=$R$12,S$12,INDEX(S$8:S$12,MATCH($A31,$R$8:$R$12,1))+(INDEX(S$8:S$12,MATCH($A31,$R$8:$R$12,1)+1)-INDEX(S$8:S$12,MATCH($A31,$R$8:$R$12,1)))*($A31-INDEX($R$8:$R$12,MATCH($A31,$R$8:$R$12,1)))/(INDEX($R$8:$R$12,MATCH($A31,$R$8:$R$12,1)+1)-INDEX($R$8:$R$12,MATCH($A31,$R$8:$R$12,1)))) -> 45.02 | C31: =Inputs!$B$79 -> 0.5 | D31: =Inputs!$B$80 -> 0.6 | E31: =Inputs!$B$81 -> 0.7 | F31: =IF($B$3="Low",C31,IF($B$3="High",E31,D31)) -> 0.6 | G31: =P31*F31*L31 -> 42.595203 | H31: =Inputs!B40*M31 -> 50 | I31: =J31*H31+(1-J31)*G31 -> 42.595203 | J31: =IF(AND($B$4="Yes",K31=1),Inputs!$B$43,0) -> 0 | K31: =IF(AND(A31>=Inputs!$B$9,A31<Inputs!$B$9+Inputs!$B$44),1,0) -> 0 | L31: =(1+Inputs!$B$63)^(A31-$A$8) -> 1.5768993 | M31: =IF(Inputs!$B$64="Yes",L31,1) -> 1 | N31: =IF($A31>=$R$12,T$12,INDEX(T$8:T$12,MATCH($A31,$R$8:$R$12,1))+(INDEX(T$8:T$12,MATCH($A31,$R$8:$R$12,1)+1)-INDEX(T$8:T$12,MATCH($A31,$R$8:$R$12,1)))*($A31-INDEX($R$8:$R$12,MATCH($A31,$R$8:$R$12,1)))/(INDEX($R$8:$R$12,MATCH($A31,$R$8:$R$12,1)+1)-INDEX($R$8:$R$12,MATCH($A31,$R$8:$R$12,1)))) -> 36.92 | O31: =IF($A31>=$R$12,U$12,INDEX(U$8:U$12,MATCH($A31,$R$8:$R$12,1))+(INDEX(U$8:U$12,MATCH($A31,$R$8:$R$12,1)+1)-INDEX(U$8:U$12,MATCH($A31,$R$8:$R$12,1)))*($A31-INDEX($R$8:$R$12,MATCH($A31,$R$8:$R$12,1)))/(INDEX($R$8:$R$12,MATCH($A31,$R$8:$R$12,1)+1)-INDEX($R$8:$R$12,MATCH($A31,$R$8:$R$12,1)))) -> 56.6 | P31: =IF($B$5="Low",N31,IF($B$5="High",O31,B31)) -> 45.02
A32: 2050 | B32: =IF($A32>=$R$12,S$12,INDEX(S$8:S$12,MATCH($A32,$R$8:$R$12,1))+(INDEX(S$8:S$12,MATCH($A32,$R$8:$R$12,1)+1)-INDEX(S$8:S$12,MATCH($A32,$R$8:$R$12,1)))*($A32-INDEX($R$8:$R$12,MATCH($A32,$R$8:$R$12,1)))/(INDEX($R$8:$R$12,MATCH($A32,$R$8:$R$12,1)+1)-INDEX($R$8:$R$12,MATCH($A32,$R$8:$R$12,1)))) -> 45.6 | C32: =Inputs!$B$79 -> 0.5 | D32: =Inputs!$B$80 -> 0.6 | E32: =Inputs!$B$81 -> 0.7 | F32: =IF($B$3="Low",C32,IF($B$3="High",E32,D32)) -> 0.6 | G32: =P32*F32*L32 -> 44.006843 | H32: =Inputs!B40*M32 -> 50 | I32: =J32*H32+(1-J32)*G32 -> 44.006843 | J32: =IF(AND($B$4="Yes",K32=1),Inputs!$B$43,0) -> 0 | K32: =IF(AND(A32>=Inputs!$B$9,A32<Inputs!$B$9+Inputs!$B$44),1,0) -> 0 | L32: =(1+Inputs!$B$63)^(A32-$A$8) -> 1.6084372 | M32: =IF(Inputs!$B$64="Yes",L32,1) -> 1 | N32: =IF($A32>=$R$12,T$12,INDEX(T$8:T$12,MATCH($A32,$R$8:$R$12,1))+(INDEX(T$8:T$12,MATCH($A32,$R$8:$R$12,1)+1)-INDEX(T$8:T$12,MATCH($A32,$R$8:$R$12,1)))*($A32-INDEX($R$8:$R$12,MATCH($A32,$R$8:$R$12,1)))/(INDEX($R$8:$R$12,MATCH($A32,$R$8:$R$12,1)+1)-INDEX($R$8:$R$12,MATCH($A32,$R$8:$R$12,1)))) -> 37.4 | O32: =IF($A32>=$R$12,U$12,INDEX(U$8:U$12,MATCH($A32,$R$8:$R$12,1))+(INDEX(U$8:U$12,MATCH($A32,$R$8:$R$12,1)+1)-INDEX(U$8:U$12,MATCH($A32,$R$8:$R$12,1)))*($A32-INDEX($R$8:$R$12,MATCH($A32,$R$8:$R$12,1)))/(INDEX($R$8:$R$12,MATCH($A32,$R$8:$R$12,1)+1)-INDEX($R$8:$R$12,MATCH($A32,$R$8:$R$12,1)))) -> 56.6 | P32: =IF($B$5="Low",N32,IF($B$5="High",O32,B32)) -> 45.6
A33: 2051 | B33: =IF($A33>=$R$12,S$12,INDEX(S$8:S$12,MATCH($A33,$R$8:$R$12,1))+(INDEX(S$8:S$12,MATCH($A33,$R$8:$R$12,1)+1)-INDEX(S$8:S$12,MATCH($A33,$R$8:$R$12,1)))*($A33-INDEX($R$8:$R$12,MATCH($A33,$R$8:$R$12,1)))/(INDEX($R$8:$R$12,MATCH($A33,$R$8:$R$12,1)+1)-INDEX($R$8:$R$12,MATCH($A33,$R$8:$R$12,1)))) -> 45.6 | C33: =Inputs!$B$79 -> 0.5 | D33: =Inputs!$B$80 -> 0.6 | E33: =Inputs!$B$81 -> 0.7 | F33: =IF($B$3="Low",C33,IF($B$3="High",E33,D33)) -> 0.6 | G33: =P33*F33*L33 -> 44.88698 | H33: =Inputs!B40*M33 -> 50 | I33: =J33*H33+(1-J33)*G33 -> 44.88698 | J33: =IF(AND($B$4="Yes",K33=1),Inputs!$B$43,0) -> 0 | K33: =IF(AND(A33>=Inputs!$B$9,A33<Inputs!$B$9+Inputs!$B$44),1,0) -> 0 | L33: =(1+Inputs!$B$63)^(A33-$A$8) -> 1.640606 | M33: =IF(Inputs!$B$64="Yes",L33,1) -> 1 | N33: =IF($A33>=$R$12,T$12,INDEX(T$8:T$12,MATCH($A33,$R$8:$R$12,1))+(INDEX(T$8:T$12,MATCH($A33,$R$8:$R$12,1)+1)-INDEX(T$8:T$12,MATCH($A33,$R$8:$R$12,1)))*($A33-INDEX($R$8:$R$12,MATCH($A33,$R$8:$R$12,1)))/(INDEX($R$8:$R$12,MATCH($A33,$R$8:$R$12,1)+1)-INDEX($R$8:$R$12,MATCH($A33,$R$8:$R$12,1)))) -> 37.4 | O33: =IF($A33>=$R$12,U$12,INDEX(U$8:U$12,MATCH($A33,$R$8:$R$12,1))+(INDEX(U$8:U$12,MATCH($A33,$R$8:$R$12,1)+1)-INDEX(U$8:U$12,MATCH($A33,$R$8:$R$12,1)))*($A33-INDEX($R$8:$R$12,MATCH($A33,$R$8:$R$12,1)))/(INDEX($R$8:$R$12,MATCH($A33,$R$8:$R$12,1)+1)-INDEX($R$8:$R$12,MATCH($A33,$R$8:$R$12,1)))) -> 56.6 | P33: =IF($B$5="Low",N33,IF($B$5="High",O33,B33)) -> 45.6
A34: 2052 | B34: =IF($A34>=$R$12,S$12,INDEX(S$8:S$12,MATCH($A34,$R$8:$R$12,1))+(INDEX(S$8:S$12,MATCH($A34,$R$8:$R$12,1)+1)-INDEX(S$8:S$12,MATCH($A34,$R$8:$R$12,1)))*($A34-INDEX($R$8:$R$12,MATCH($A34,$R$8:$R$12,1)))/(INDEX($R$8:$R$12,MATCH($A34,$R$8:$R$12,1)+1)-INDEX($R$8:$R$12,MATCH($A34,$R$8:$R$12,1)))) -> 45.6 | C34: =Inputs!$B$79 -> 0.5 | D34: =Inputs!$B$80 -> 0.6 | E34: =Inputs!$B$81 -> 0.7 | F34: =IF($B$3="Low",C34,IF($B$3="High",E34,D34)) -> 0.6 | G34: =P34*F34*L34 -> 45.78472 | H34: =Inputs!B40*M34 -> 50 | I34: =J34*H34+(1-J34)*G34 -> 45.78472 | J34: =IF(AND($B$4="Yes",K34=1),Inputs!$B$43,0) -> 0 | K34: =IF(AND(A34>=Inputs!$B$9,A34<Inputs!$B$9+Inputs!$B$44),1,0) -> 0 | L34: =(1+Inputs!$B$63)^(A34-$A$8) -> 1.6734181 | M34: =IF(Inputs!$B$64="Yes",L34,1) -> 1 | N34: =IF($A34>=$R$12,T$12,INDEX(T$8:T$12,MATCH($A34,$R$8:$R$12,1))+(INDEX(T$8:T$12,MATCH($A34,$R$8:$R$12,1)+1)-INDEX(T$8:T$12,MATCH($A34,$R$8:$R$12,1)))*($A34-INDEX($R$8:$R$12,MATCH($A34,$R$8:$R$12,1)))/(INDEX($R$8:$R$12,MATCH($A34,$R$8:$R$12,1)+1)-INDEX($R$8:$R$12,MATCH($A34,$R$8:$R$12,1)))) -> 37.4 | O34: =IF($A34>=$R$12,U$12,INDEX(U$8:U$12,MATCH($A34,$R$8:$R$12,1))+(INDEX(U$8:U$12,MATCH($A34,$R$8:$R$12,1)+1)-INDEX(U$8:U$12,MATCH($A34,$R$8:$R$12,1)))*($A34-INDEX($R$8:$R$12,MATCH($A34,$R$8:$R$12,1)))/(INDEX($R$8:$R$12,MATCH($A34,$R$8:$R$12,1)+1)-INDEX($R$8:$R$12,MATCH($A34,$R$8:$R$12,1)))) -> 56.6 | P34: =IF($B$5="Low",N34,IF($B$5="High",O34,B34)) -> 45.6
A35: 2053 | B35: =IF($A35>=$R$12,S$12,INDEX(S$8:S$12,MATCH($A35,$R$8:$R$12,1))+(INDEX(S$8:S$12,MATCH($A35,$R$8:$R$12,1)+1)-INDEX(S$8:S$12,MATCH($A35,$R$8:$R$12,1)))*($A35-INDEX($R$8:$R$12,MATCH($A35,$R$8:$R$12,1)))/(INDEX($R$8:$R$12,MATCH($A35,$R$8:$R$12,1)+1)-INDEX($R$8:$R$12,MATCH($A35,$R$8:$R$12,1)))) -> 45.6 | C35: =Inputs!$B$79 -> 0.5 | D35: =Inputs!$B$80 -> 0.6 | E35: =Inputs!$B$81 -> 0.7 | F35: =IF($B$3="Low",C35,IF($B$3="High",E35,D35)) -> 0.6 | G35: =P35*F35*L35 -> 46.700414 | H35: =Inputs!B40*M35 -> 50 | I35: =J35*H35+(1-J35)*G35 -> 46.700414 | J35: =IF(AND($B$4="Yes",K35=1),Inputs!$B$43,0) -> 0 | K35: =IF(AND(A35>=Inputs!$B$9,A35<Inputs!$B$9+Inputs!$B$44),1,0) -> 0 | L35: =(1+Inputs!$B$63)^(A35-$A$8) -> 1.7068865 | M35: =IF(Inputs!$B$64="Yes",L35,1) -> 1 | N35: =IF($A35>=$R$12,T$12,INDEX(T$8:T$12,MATCH($A35,$R$8:$R$12,1))+(INDEX(T$8:T$12,MATCH($A35,$R$8:$R$12,1)+1)-INDEX(T$8:T$12,MATCH($A35,$R$8:$R$12,1)))*($A35-INDEX($R$8:$R$12,MATCH($A35,$R$8:$R$12,1)))/(INDEX($R$8:$R$12,MATCH($A35,$R$8:$R$12,1)+1)-INDEX($R$8:$R$12,MATCH($A35,$R$8:$R$12,1)))) -> 37.4 | O35: =IF($A35>=$R$12,U$12,INDEX(U$8:U$12,MATCH($A35,$R$8:$R$12,1))+(INDEX(U$8:U$12,MATCH($A35,$R$8:$R$12,1)+1)-INDEX(U$8:U$12,MATCH($A35,$R$8:$R$12,1)))*($A35-INDEX($R$8:$R$12,MATCH($A35,$R$8:$R$12,1)))/(INDEX($R$8:$R$12,MATCH($A35,$R$8:$R$12,1)+1)-INDEX($R$8:$R$12,MATCH($A35,$R$8:$R$12,1)))) -> 56.6 | P35: =IF($B$5="Low",N35,IF($B$5="High",O35,B35)) -> 45.6
A36: 2054 | B36: =IF($A36>=$R$12,S$12,INDEX(S$8:S$12,MATCH($A36,$R$8:$R$12,1))+(INDEX(S$8:S$12,MATCH($A36,$R$8:$R$12,1)+1)-INDEX(S$8:S$12,MATCH($A36,$R$8:$R$12,1)))*($A36-INDEX($R$8:$R$12,MATCH($A36,$R$8:$R$12,1)))/(INDEX($R$8:$R$12,MATCH($A36,$R$8:$R$12,1)+1)-INDEX($R$8:$R$12,MATCH($A36,$R$8:$R$12,1)))) -> 45.6 | C36: =Inputs!$B$79 -> 0.5 | D36: =Inputs!$B$80 -> 0.6 | E36: =Inputs!$B$81 -> 0.7 | F36: =IF($B$3="Low",C36,IF($B$3="High",E36,D36)) -> 0.6 | G36: =P36*F36*L36 -> 47.634422 | H36: =Inputs!B40*M36 -> 50 | I36: =J36*H36+(1-J36)*G36 -> 47.634422 | J36: =IF(AND($B$4="Yes",K36=1),Inputs!$B$43,0) -> 0 | K36: =IF(AND(A36>=Inputs!$B$9,A36<Inputs!$B$9+Inputs!$B$44),1,0) -> 0 | L36: =(1+Inputs!$B$63)^(A36-$A$8) -> 1.7410242 | M36: =IF(Inputs!$B$64="Yes",L36,1) -> 1 | N36: =IF($A36>=$R$12,T$12,INDEX(T$8:T$12,MATCH($A36,$R$8:$R$12,1))+(INDEX(T$8:T$12,MATCH($A36,$R$8:$R$12,1)+1)-INDEX(T$8:T$12,MATCH($A36,$R$8:$R$12,1)))*($A36-INDEX($R$8:$R$12,MATCH($A36,$R$8:$R$12,1)))/(INDEX($R$8:$R$12,MATCH($A36,$R$8:$R$12,1)+1)-INDEX($R$8:$R$12,MATCH($A36,$R$8:$R$12,1)))) -> 37.4 | O36: =IF($A36>=$R$12,U$12,INDEX(U$8:U$12,MATCH($A36,$R$8:$R$12,1))+(INDEX(U$8:U$12,MATCH($A36,$R$8:$R$12,1)+1)-INDEX(U$8:U$12,MATCH($A36,$R$8:$R$12,1)))*($A36-INDEX($R$8:$R$12,MATCH($A36,$R$8:$R$12,1)))/(INDEX($R$8:$R$12,MATCH($A36,$R$8:$R$12,1)+1)-INDEX($R$8:$R$12,MATCH($A36,$R$8:$R$12,1)))) -> 56.6 | P36: =IF($B$5="Low",N36,IF($B$5="High",O36,B36)) -> 45.6
A37: 2055 | B37: =IF($A37>=$R$12,S$12,INDEX(S$8:S$12,MATCH($A37,$R$8:$R$12,1))+(INDEX(S$8:S$12,MATCH($A37,$R$8:$R$12,1)+1)-INDEX(S$8:S$12,MATCH($A37,$R$8:$R$12,1)))*($A37-INDEX($R$8:$R$12,MATCH($A37,$R$8:$R$12,1)))/(INDEX($R$8:$R$12,MATCH($A37,$R$8:$R$12,1)+1)-INDEX($R$8:$R$12,MATCH($A37,$R$8:$R$12,1)))) -> 45.6 | C37: =Inputs!$B$79 -> 0.5 | D37: =Inputs!$B$80 -> 0.6 | E37: =Inputs!$B$81 -> 0.7 | F37: =IF($B$3="Low",C37,IF($B$3="High",E37,D37)) -> 0.6 | G37: =P37*F37*L37 -> 48.587111 | H37: =Inputs!B40*M37 -> 50 | I37: =J37*H37+(1-J37)*G37 -> 48.587111 | J37: =IF(AND($B$4="Yes",K37=1),Inputs!$B$43,0) -> 0 | K37: =IF(AND(A37>=Inputs!$B$9,A37<Inputs!$B$9+Inputs!$B$44),1,0) -> 0 | L37: =(1+Inputs!$B$63)^(A37-$A$8) -> 1.7758447 | M37: =IF(Inputs!$B$64="Yes",L37,1) -> 1 | N37: =IF($A37>=$R$12,T$12,INDEX(T$8:T$12,MATCH($A37,$R$8:$R$12,1))+(INDEX(T$8:T$12,MATCH($A37,$R$8:$R$12,1)+1)-INDEX(T$8:T$12,MATCH($A37,$R$8:$R$12,1)))*($A37-INDEX($R$8:$R$12,MATCH($A37,$R$8:$R$12,1)))/(INDEX($R$8:$R$12,MATCH($A37,$R$8:$R$12,1)+1)-INDEX($R$8:$R$12,MATCH($A37,$R$8:$R$12,1)))) -> 37.4 | O37: =IF($A37>=$R$12,U$12,INDEX(U$8:U$12,MATCH($A37,$R$8:$R$12,1))+(INDEX(U$8:U$12,MATCH($A37,$R$8:$R$12,1)+1)-INDEX(U$8:U$12,MATCH($A37,$R$8:$R$12,1)))*($A37-INDEX($R$8:$R$12,MATCH($A37,$R$8:$R$12,1)))/(INDEX($R$8:$R$12,MATCH($A37,$R$8:$R$12,1)+1)-INDEX($R$8:$R$12,MATCH($A37,$R$8:$R$12,1)))) -> 56.6 | P37: =IF($B$5="Low",N37,IF($B$5="High",O37,B37)) -> 45.6
A38: 2056 | B38: =IF($A38>=$R$12,S$12,INDEX(S$8:S$12,MATCH($A38,$R$8:$R$12,1))+(INDEX(S$8:S$12,MATCH($A38,$R$8:$R$12,1)+1)-INDEX(S$8:S$12,MATCH($A38,$R$8:$R$12,1)))*($A38-INDEX($R$8:$R$12,MATCH($A38,$R$8:$R$12,1)))/(INDEX($R$8:$R$12,MATCH($A38,$R$8:$R$12,1)+1)-INDEX($R$8:$R$12,MATCH($A38,$R$8:$R$12,1)))) -> 45.6 | C38: =Inputs!$B$79 -> 0.5 | D38: =Inputs!$B$80 -> 0.6 | E38: =Inputs!$B$81 -> 0.7 | F38: =IF($B$3="Low",C38,IF($B$3="High",E38,D38)) -> 0.6 | G38: =P38*F38*L38 -> 49.558853 | H38: =Inputs!B40*M38 -> 50 | I38: =J38*H38+(1-J38)*G38 -> 49.558853 | J38: =IF(AND($B$4="Yes",K38=1),Inputs!$B$43,0) -> 0 | K38: =IF(AND(A38>=Inputs!$B$9,A38<Inputs!$B$9+Inputs!$B$44),1,0) -> 0 | L38: =(1+Inputs!$B$63)^(A38-$A$8) -> 1.8113616 | M38: =IF(Inputs!$B$64="Yes",L38,1) -> 1 | N38: =IF($A38>=$R$12,T$12,INDEX(T$8:T$12,MATCH($A38,$R$8:$R$12,1))+(INDEX(T$8:T$12,MATCH($A38,$R$8:$R$12,1)+1)-INDEX(T$8:T$12,MATCH($A38,$R$8:$R$12,1)))*($A38-INDEX($R$8:$R$12,MATCH($A38,$R$8:$R$12,1)))/(INDEX($R$8:$R$12,MATCH($A38,$R$8:$R$12,1)+1)-INDEX($R$8:$R$12,MATCH($A38,$R$8:$R$12,1)))) -> 37.4 | O38: =IF($A38>=$R$12,U$12,INDEX(U$8:U$12,MATCH($A38,$R$8:$R$12,1))+(INDEX(U$8:U$12,MATCH($A38,$R$8:$R$12,1)+1)-INDEX(U$8:U$12,MATCH($A38,$R$8:$R$12,1)))*($A38-INDEX($R$8:$R$12,MATCH($A38,$R$8:$R$12,1)))/(INDEX($R$8:$R$12,MATCH($A38,$R$8:$R$12,1)+1)-INDEX($R$8:$R$12,MATCH($A38,$R$8:$R$12,1)))) -> 56.6 | P38: =IF($B$5="Low",N38,IF($B$5="High",O38,B38)) -> 45.6
A39: 2057 | B39: =IF($A39>=$R$12,S$12,INDEX(S$8:S$12,MATCH($A39,$R$8:$R$12,1))+(INDEX(S$8:S$12,MATCH($A39,$R$8:$R$12,1)+1)-INDEX(S$8:S$12,MATCH($A39,$R$8:$R$12,1)))*($A39-INDEX($R$8:$R$12,MATCH($A39,$R$8:$R$12,1)))/(INDEX($R$8:$R$12,MATCH($A39,$R$8:$R$12,1)+1)-INDEX($R$8:$R$12,MATCH($A39,$R$8:$R$12,1)))) -> 45.6 | C39: =Inputs!$B$79 -> 0.5 | D39: =Inputs!$B$80 -> 0.6 | E39: =Inputs!$B$81 -> 0.7 | F39: =IF($B$3="Low",C39,IF($B$3="High",E39,D39)) -> 0.6 | G39: =P39*F39*L39 -> 50.55003 | H39: =Inputs!$B$40*M39 -> 50 | I39: =J39*H39+(1-J39)*G39 -> 50.55003 | J39: =IF(AND($B$4="Yes",K39=1),Inputs!$B$43,0) -> 0 | K39: =IF(AND(A39>=Inputs!$B$9,A39<Inputs!$B$9+Inputs!$B$44),1,0) -> 0 | L39: =(1+Inputs!$B$63)^(A39-$A$8) -> 1.8475888 | M39: =IF(Inputs!$B$64="Yes",L39,1) -> 1 | N39: =IF($A39>=$R$12,T$12,INDEX(T$8:T$12,MATCH($A39,$R$8:$R$12,1))+(INDEX(T$8:T$12,MATCH($A39,$R$8:$R$12,1)+1)-INDEX(T$8:T$12,MATCH($A39,$R$8:$R$12,1)))*($A39-INDEX($R$8:$R$12,MATCH($A39,$R$8:$R$12,1)))/(INDEX($R$8:$R$12,MATCH($A39,$R$8:$R$12,1)+1)-INDEX($R$8:$R$12,MATCH($A39,$R$8:$R$12,1)))) -> 37.4 | O39: =IF($A39>=$R$12,U$12,INDEX(U$8:U$12,MATCH($A39,$R$8:$R$12,1))+(INDEX(U$8:U$12,MATCH($A39,$R$8:$R$12,1)+1)-INDEX(U$8:U$12,MATCH($A39,$R$8:$R$12,1)))*($A39-INDEX($R$8:$R$12,MATCH($A39,$R$8:$R$12,1)))/(INDEX($R$8:$R$12,MATCH($A39,$R$8:$R$12,1)+1)-INDEX($R$8:$R$12,MATCH($A39,$R$8:$R$12,1)))) -> 56.6 | P39: =IF($B$5="Low",N39,IF($B$5="High",O39,B39)) -> 45.6
A40: 2058 | B40: =IF($A40>=$R$12,S$12,INDEX(S$8:S$12,MATCH($A40,$R$8:$R$12,1))+(INDEX(S$8:S$12,MATCH($A40,$R$8:$R$12,1)+1)-INDEX(S$8:S$12,MATCH($A40,$R$8:$R$12,1)))*($A40-INDEX($R$8:$R$12,MATCH($A40,$R$8:$R$12,1)))/(INDEX($R$8:$R$12,MATCH($A40,$R$8:$R$12,1)+1)-INDEX($R$8:$R$12,MATCH($A40,$R$8:$R$12,1)))) -> 45.6 | C40: =Inputs!$B$79 -> 0.5 | D40: =Inputs!$B$80 -> 0.6 | E40: =Inputs!$B$81 -> 0.7 | F40: =IF($B$3="Low",C40,IF($B$3="High",E40,D40)) -> 0.6 | G40: =P40*F40*L40 -> 51.561031 | H40: =Inputs!$B$40*M40 -> 50 | I40: =J40*H40+(1-J40)*G40 -> 51.561031 | J40: =IF(AND($B$4="Yes",K40=1),Inputs!$B$43,0) -> 0 | K40: =IF(AND(A40>=Inputs!$B$9,A40<Inputs!$B$9+Inputs!$B$44),1,0) -> 0 | L40: =(1+Inputs!$B$63)^(A40-$A$8) -> 1.8845406 | M40: =IF(Inputs!$B$64="Yes",L40,1) -> 1 | N40: =IF($A40>=$R$12,T$12,INDEX(T$8:T$12,MATCH($A40,$R$8:$R$12,1))+(INDEX(T$8:T$12,MATCH($A40,$R$8:$R$12,1)+1)-INDEX(T$8:T$12,MATCH($A40,$R$8:$R$12,1)))*($A40-INDEX($R$8:$R$12,MATCH($A40,$R$8:$R$12,1)))/(INDEX($R$8:$R$12,MATCH($A40,$R$8:$R$12,1)+1)-INDEX($R$8:$R$12,MATCH($A40,$R$8:$R$12,1)))) -> 37.4 | O40: =IF($A40>=$R$12,U$12,INDEX(U$8:U$12,MATCH($A40,$R$8:$R$12,1))+(INDEX(U$8:U$12,MATCH($A40,$R$8:$R$12,1)+1)-INDEX(U$8:U$12,MATCH($A40,$R$8:$R$12,1)))*($A40-INDEX($R$8:$R$12,MATCH($A40,$R$8:$R$12,1)))/(INDEX($R$8:$R$12,MATCH($A40,$R$8:$R$12,1)+1)-INDEX($R$8:$R$12,MATCH($A40,$R$8:$R$12,1)))) -> 56.6 | P40: =IF($B$5="Low",N40,IF($B$5="High",O40,B40)) -> 45.6
A42: Notes: Market prices are time-average day-ahead prices in real 2026 EUR/MWh, indexed to nominal with the inflation index. All price and capture inputs sit in Inputs rows 68-81 with source and status. Base (B), Low (N) and High (O) paths interpolate linearly between the anchor years in R8:R12 (2026 observed, 2028 and 2030 optional futures anchor, 2040, 2050) and stay flat in real terms after 2050. Capture rates (C:E) are flat per scenario. The market price scenario (Cover!B17) selects the path and the capture-rate scenario (Cover!B16) selects the capture rate, independently of each other. Selected revenue price = PPA share x PPA price + (1 - share) x merchant realised price (nominal). 2027 is the construction year with COD 2028.

Sheet Production
A1: PRODUCTION
A3: WIND GENERATION
A4: Year | B4: Capacity MW | C4: Capacity factor | D4: Hours | E4: Gross MWh | F4: Curtailment | G4: Net MWh | H4: BESS charge MWh (grid, memo) | I4: BESS discharge MWh (memo) | J4: Net exported MWh (wind) | K4: Source | L4: Status | M4: Wind operating flag | N4: BESS operating flag
A5: 2026 | B5: =Inputs!B7 -> 100 | C5: =Inputs!B10 -> 0.35 | D5: =IF(OR(MOD(A5,400)=0,AND(MOD(A5,4)=0,MOD(A5,100)<>0)),8784,8760) -> 8760 | E5: =B5*C5*D5*M5 -> 0 | F5: =E5*Inputs!B11 -> 0 | G5: =E5-F5 -> 0 | H5: =Inputs!$B$26*Inputs!$B$24*N5 -> 0 | I5: =H5*Inputs!$B$25 -> 0 | J5: =G5 -> 0 | L5: formula | M5: =IF(AND(A5>=Inputs!$B$9,A5<Inputs!$B$9+Inputs!$B$8),1,0) -> 0 | N5: =IF(AND(M5=1,Inputs!$B$24>0),1,0) -> 0
A6: 2027 | B6: =Inputs!B7 -> 100 | C6: =Inputs!B10 -> 0.35 | D6: =IF(OR(MOD(A6,400)=0,AND(MOD(A6,4)=0,MOD(A6,100)<>0)),8784,8760) -> 8760 | E6: =B6*C6*D6*M6 -> 0 | F6: =E6*Inputs!B11 -> 0 | G6: =E6-F6 -> 0 | H6: =Inputs!$B$26*Inputs!$B$24*N6 -> 0 | I6: =H6*Inputs!$B$25 -> 0 | J6: =G6 -> 0 | L6: formula | M6: =IF(AND(A6>=Inputs!$B$9,A6<Inputs!$B$9+Inputs!$B$8),1,0) -> 0 | N6: =IF(AND(M6=1,Inputs!$B$24>0),1,0) -> 0
A7: 2028 | B7: =Inputs!B7 -> 100 | C7: =Inputs!B10 -> 0.35 | D7: =IF(OR(MOD(A7,400)=0,AND(MOD(A7,4)=0,MOD(A7,100)<>0)),8784,8760) -> 8784 | E7: =B7*C7*D7*M7 -> 307440 | F7: =E7*Inputs!B11 -> 15372 | G7: =E7-F7 -> 292068 | H7: =Inputs!$B$26*Inputs!$B$24*N7 -> 0 | I7: =H7*Inputs!$B$25 -> 0 | J7: =G7 -> 292068 | L7: formula | M7: =IF(AND(A7>=Inputs!$B$9,A7<Inputs!$B$9+Inputs!$B$8),1,0) -> 1 | N7: =IF(AND(M7=1,Inputs!$B$24>0),1,0) -> 0
A8: 2029 | B8: =Inputs!B7 -> 100 | C8: =Inputs!B10 -> 0.35 | D8: =IF(OR(MOD(A8,400)=0,AND(MOD(A8,4)=0,MOD(A8,100)<>0)),8784,8760) -> 8760 | E8: =B8*C8*D8*M8 -> 306600 | F8: =E8*Inputs!B11 -> 15330 | G8: =E8-F8 -> 291270 | H8: =Inputs!$B$26*Inputs!$B$24*N8 -> 0 | I8: =H8*Inputs!$B$25 -> 0 | J8: =G8 -> 291270 | L8: formula | M8: =IF(AND(A8>=Inputs!$B$9,A8<Inputs!$B$9+Inputs!$B$8),1,0) -> 1 | N8: =IF(AND(M8=1,Inputs!$B$24>0),1,0) -> 0
A9: 2030 | B9: =Inputs!B7 -> 100 | C9: =Inputs!B10 -> 0.35 | D9: =IF(OR(MOD(A9,400)=0,AND(MOD(A9,4)=0,MOD(A9,100)<>0)),8784,8760) -> 8760 | E9: =B9*C9*D9*M9 -> 306600 | F9: =E9*Inputs!B11 -> 15330 | G9: =E9-F9 -> 291270 | H9: =Inputs!$B$26*Inputs!$B$24*N9 -> 0 | I9: =H9*Inputs!$B$25 -> 0 | J9: =G9 -> 291270 | L9: formula | M9: =IF(AND(A9>=Inputs!$B$9,A9<Inputs!$B$9+Inputs!$B$8),1,0) -> 1 | N9: =IF(AND(M9=1,Inputs!$B$24>0),1,0) -> 0
A10: 2031 | B10: =Inputs!B7 -> 100 | C10: =Inputs!B10 -> 0.35 | D10: =IF(OR(MOD(A10,400)=0,AND(MOD(A10,4)=0,MOD(A10,100)<>0)),8784,8760) -> 8760 | E10: =B10*C10*D10*M10 -> 306600 | F10: =E10*Inputs!B11 -> 15330 | G10: =E10-F10 -> 291270 | H10: =Inputs!$B$26*Inputs!$B$24*N10 -> 0 | I10: =H10*Inputs!$B$25 -> 0 | J10: =G10 -> 291270 | L10: formula | M10: =IF(AND(A10>=Inputs!$B$9,A10<Inputs!$B$9+Inputs!$B$8),1,0) -> 1 | N10: =IF(AND(M10=1,Inputs!$B$24>0),1,0) -> 0
A11: 2032 | B11: =Inputs!B7 -> 100 | C11: =Inputs!B10 -> 0.35 | D11: =IF(OR(MOD(A11,400)=0,AND(MOD(A11,4)=0,MOD(A11,100)<>0)),8784,8760) -> 8784 | E11: =B11*C11*D11*M11 -> 307440 | F11: =E11*Inputs!B11 -> 15372 | G11: =E11-F11 -> 292068 | H11: =Inputs!$B$26*Inputs!$B$24*N11 -> 0 | I11: =H11*Inputs!$B$25 -> 0 | J11: =G11 -> 292068 | L11: formula | M11: =IF(AND(A11>=Inputs!$B$9,A11<Inputs!$B$9+Inputs!$B$8),1,0) -> 1 | N11: =IF(AND(M11=1,Inputs!$B$24>0),1,0) -> 0
A12: 2033 | B12: =Inputs!B7 -> 100 | C12: =Inputs!B10 -> 0.35 | D12: =IF(OR(MOD(A12,400)=0,AND(MOD(A12,4)=0,MOD(A12,100)<>0)),8784,8760) -> 8760 | E12: =B12*C12*D12*M12 -> 306600 | F12: =E12*Inputs!B11 -> 15330 | G12: =E12-F12 -> 291270 | H12: =Inputs!$B$26*Inputs!$B$24*N12 -> 0 | I12: =H12*Inputs!$B$25 -> 0 | J12: =G12 -> 291270 | L12: formula | M12: =IF(AND(A12>=Inputs!$B$9,A12<Inputs!$B$9+Inputs!$B$8),1,0) -> 1 | N12: =IF(AND(M12=1,Inputs!$B$24>0),1,0) -> 0
A13: 2034 | B13: =Inputs!B7 -> 100 | C13: =Inputs!B10 -> 0.35 | D13: =IF(OR(MOD(A13,400)=0,AND(MOD(A13,4)=0,MOD(A13,100)<>0)),8784,8760) -> 8760 | E13: =B13*C13*D13*M13 -> 306600 | F13: =E13*Inputs!B11 -> 15330 | G13: =E13-F13 -> 291270 | H13: =Inputs!$B$26*Inputs!$B$24*N13 -> 0 | I13: =H13*Inputs!$B$25 -> 0 | J13: =G13 -> 291270 | L13: formula | M13: =IF(AND(A13>=Inputs!$B$9,A13<Inputs!$B$9+Inputs!$B$8),1,0) -> 1 | N13: =IF(AND(M13=1,Inputs!$B$24>0),1,0) -> 0
A14: 2035 | B14: =Inputs!B7 -> 100 | C14: =Inputs!B10 -> 0.35 | D14: =IF(OR(MOD(A14,400)=0,AND(MOD(A14,4)=0,MOD(A14,100)<>0)),8784,8760) -> 8760 | E14: =B14*C14*D14*M14 -> 306600 | F14: =E14*Inputs!B11 -> 15330 | G14: =E14-F14 -> 291270 | H14: =Inputs!$B$26*Inputs!$B$24*N14 -> 0 | I14: =H14*Inputs!$B$25 -> 0 | J14: =G14 -> 291270 | L14: formula | M14: =IF(AND(A14>=Inputs!$B$9,A14<Inputs!$B$9+Inputs!$B$8),1,0) -> 1 | N14: =IF(AND(M14=1,Inputs!$B$24>0),1,0) -> 0
A15: 2036 | B15: =Inputs!B7 -> 100 | C15: =Inputs!B10 -> 0.35 | D15: =IF(OR(MOD(A15,400)=0,AND(MOD(A15,4)=0,MOD(A15,100)<>0)),8784,8760) -> 8784 | E15: =B15*C15*D15*M15 -> 307440 | F15: =E15*Inputs!B11 -> 15372 | G15: =E15-F15 -> 292068 | H15: =Inputs!$B$26*Inputs!$B$24*N15 -> 0 | I15: =H15*Inputs!$B$25 -> 0 | J15: =G15 -> 292068 | L15: formula | M15: =IF(AND(A15>=Inputs!$B$9,A15<Inputs!$B$9+Inputs!$B$8),1,0) -> 1 | N15: =IF(AND(M15=1,Inputs!$B$24>0),1,0) -> 0
A16: 2037 | B16: =Inputs!B7 -> 100 | C16: =Inputs!B10 -> 0.35 | D16: =IF(OR(MOD(A16,400)=0,AND(MOD(A16,4)=0,MOD(A16,100)<>0)),8784,8760) -> 8760 | E16: =B16*C16*D16*M16 -> 306600 | F16: =E16*Inputs!B11 -> 15330 | G16: =E16-F16 -> 291270 | H16: =Inputs!$B$26*Inputs!$B$24*N16 -> 0 | I16: =H16*Inputs!$B$25 -> 0 | J16: =G16 -> 291270 | L16: formula | M16: =IF(AND(A16>=Inputs!$B$9,A16<Inputs!$B$9+Inputs!$B$8),1,0) -> 1 | N16: =IF(AND(M16=1,Inputs!$B$24>0),1,0) -> 0
A17: 2038 | B17: =Inputs!B7 -> 100 | C17: =Inputs!B10 -> 0.35 | D17: =IF(OR(MOD(A17,400)=0,AND(MOD(A17,4)=0,MOD(A17,100)<>0)),8784,8760) -> 8760 | E17: =B17*C17*D17*M17 -> 306600 | F17: =E17*Inputs!B11 -> 15330 | G17: =E17-F17 -> 291270 | H17: =Inputs!$B$26*Inputs!$B$24*N17 -> 0 | I17: =H17*Inputs!$B$25 -> 0 | J17: =G17 -> 291270 | L17: formula | M17: =IF(AND(A17>=Inputs!$B$9,A17<Inputs!$B$9+Inputs!$B$8),1,0) -> 1 | N17: =IF(AND(M17=1,Inputs!$B$24>0),1,0) -> 0
A18: 2039 | B18: =Inputs!B7 -> 100 | C18: =Inputs!B10 -> 0.35 | D18: =IF(OR(MOD(A18,400)=0,AND(MOD(A18,4)=0,MOD(A18,100)<>0)),8784,8760) -> 8760 | E18: =B18*C18*D18*M18 -> 306600 | F18: =E18*Inputs!B11 -> 15330 | G18: =E18-F18 -> 291270 | H18: =Inputs!$B$26*Inputs!$B$24*N18 -> 0 | I18: =H18*Inputs!$B$25 -> 0 | J18: =G18 -> 291270 | L18: formula | M18: =IF(AND(A18>=Inputs!$B$9,A18<Inputs!$B$9+Inputs!$B$8),1,0) -> 1 | N18: =IF(AND(M18=1,Inputs!$B$24>0),1,0) -> 0
A19: 2040 | B19: =Inputs!B7 -> 100 | C19: =Inputs!B10 -> 0.35 | D19: =IF(OR(MOD(A19,400)=0,AND(MOD(A19,4)=0,MOD(A19,100)<>0)),8784,8760) -> 8784 | E19: =B19*C19*D19*M19 -> 307440 | F19: =E19*Inputs!B11 -> 15372 | G19: =E19-F19 -> 292068 | H19: =Inputs!$B$26*Inputs!$B$24*N19 -> 0 | I19: =H19*Inputs!$B$25 -> 0 | J19: =G19 -> 292068 | L19: formula | M19: =IF(AND(A19>=Inputs!$B$9,A19<Inputs!$B$9+Inputs!$B$8),1,0) -> 1 | N19: =IF(AND(M19=1,Inputs!$B$24>0),1,0) -> 0
A20: 2041 | B20: =Inputs!B7 -> 100 | C20: =Inputs!B10 -> 0.35 | D20: =IF(OR(MOD(A20,400)=0,AND(MOD(A20,4)=0,MOD(A20,100)<>0)),8784,8760) -> 8760 | E20: =B20*C20*D20*M20 -> 306600 | F20: =E20*Inputs!B11 -> 15330 | G20: =E20-F20 -> 291270 | H20: =Inputs!$B$26*Inputs!$B$24*N20 -> 0 | I20: =H20*Inputs!$B$25 -> 0 | J20: =G20 -> 291270 | L20: formula | M20: =IF(AND(A20>=Inputs!$B$9,A20<Inputs!$B$9+Inputs!$B$8),1,0) -> 1 | N20: =IF(AND(M20=1,Inputs!$B$24>0),1,0) -> 0
A21: 2042 | B21: =Inputs!B7 -> 100 | C21: =Inputs!B10 -> 0.35 | D21: =IF(OR(MOD(A21,400)=0,AND(MOD(A21,4)=0,MOD(A21,100)<>0)),8784,8760) -> 8760 | E21: =B21*C21*D21*M21 -> 306600 | F21: =E21*Inputs!B11 -> 15330 | G21: =E21-F21 -> 291270 | H21: =Inputs!$B$26*Inputs!$B$24*N21 -> 0 | I21: =H21*Inputs!$B$25 -> 0 | J21: =G21 -> 291270 | L21: formula | M21: =IF(AND(A21>=Inputs!$B$9,A21<Inputs!$B$9+Inputs!$B$8),1,0) -> 1 | N21: =IF(AND(M21=1,Inputs!$B$24>0),1,0) -> 0
A22: 2043 | B22: =Inputs!B7 -> 100 | C22: =Inputs!B10 -> 0.35 | D22: =IF(OR(MOD(A22,400)=0,AND(MOD(A22,4)=0,MOD(A22,100)<>0)),8784,8760) -> 8760 | E22: =B22*C22*D22*M22 -> 306600 | F22: =E22*Inputs!B11 -> 15330 | G22: =E22-F22 -> 291270 | H22: =Inputs!$B$26*Inputs!$B$24*N22 -> 0 | I22: =H22*Inputs!$B$25 -> 0 | J22: =G22 -> 291270 | L22: formula | M22: =IF(AND(A22>=Inputs!$B$9,A22<Inputs!$B$9+Inputs!$B$8),1,0) -> 1 | N22: =IF(AND(M22=1,Inputs!$B$24>0),1,0) -> 0
A23: 2044 | B23: =Inputs!B7 -> 100 | C23: =Inputs!B10 -> 0.35 | D23: =IF(OR(MOD(A23,400)=0,AND(MOD(A23,4)=0,MOD(A23,100)<>0)),8784,8760) -> 8784 | E23: =B23*C23*D23*M23 -> 307440 | F23: =E23*Inputs!B11 -> 15372 | G23: =E23-F23 -> 292068 | H23: =Inputs!$B$26*Inputs!$B$24*N23 -> 0 | I23: =H23*Inputs!$B$25 -> 0 | J23: =G23 -> 292068 | L23: formula | M23: =IF(AND(A23>=Inputs!$B$9,A23<Inputs!$B$9+Inputs!$B$8),1,0) -> 1 | N23: =IF(AND(M23=1,Inputs!$B$24>0),1,0) -> 0
A24: 2045 | B24: =Inputs!B7 -> 100 | C24: =Inputs!B10 -> 0.35 | D24: =IF(OR(MOD(A24,400)=0,AND(MOD(A24,4)=0,MOD(A24,100)<>0)),8784,8760) -> 8760 | E24: =B24*C24*D24*M24 -> 306600 | F24: =E24*Inputs!B11 -> 15330 | G24: =E24-F24 -> 291270 | H24: =Inputs!$B$26*Inputs!$B$24*N24 -> 0 | I24: =H24*Inputs!$B$25 -> 0 | J24: =G24 -> 291270 | L24: formula | M24: =IF(AND(A24>=Inputs!$B$9,A24<Inputs!$B$9+Inputs!$B$8),1,0) -> 1 | N24: =IF(AND(M24=1,Inputs!$B$24>0),1,0) -> 0
A25: 2046 | B25: =Inputs!B7 -> 100 | C25: =Inputs!B10 -> 0.35 | D25: =IF(OR(MOD(A25,400)=0,AND(MOD(A25,4)=0,MOD(A25,100)<>0)),8784,8760) -> 8760 | E25: =B25*C25*D25*M25 -> 306600 | F25: =E25*Inputs!B11 -> 15330 | G25: =E25-F25 -> 291270 | H25: =Inputs!$B$26*Inputs!$B$24*N25 -> 0 | I25: =H25*Inputs!$B$25 -> 0 | J25: =G25 -> 291270 | L25: formula | M25: =IF(AND(A25>=Inputs!$B$9,A25<Inputs!$B$9+Inputs!$B$8),1,0) -> 1 | N25: =IF(AND(M25=1,Inputs!$B$24>0),1,0) -> 0
A26: 2047 | B26: =Inputs!B7 -> 100 | C26: =Inputs!B10 -> 0.35 | D26: =IF(OR(MOD(A26,400)=0,AND(MOD(A26,4)=0,MOD(A26,100)<>0)),8784,8760) -> 8760 | E26: =B26*C26*D26*M26 -> 306600 | F26: =E26*Inputs!B11 -> 15330 | G26: =E26-F26 -> 291270 | H26: =Inputs!$B$26*Inputs!$B$24*N26 -> 0 | I26: =H26*Inputs!$B$25 -> 0 | J26: =G26 -> 291270 | L26: formula | M26: =IF(AND(A26>=Inputs!$B$9,A26<Inputs!$B$9+Inputs!$B$8),1,0) -> 1 | N26: =IF(AND(M26=1,Inputs!$B$24>0),1,0) -> 0
A27: 2048 | B27: =Inputs!B7 -> 100 | C27: =Inputs!B10 -> 0.35 | D27: =IF(OR(MOD(A27,400)=0,AND(MOD(A27,4)=0,MOD(A27,100)<>0)),8784,8760) -> 8784 | E27: =B27*C27*D27*M27 -> 307440 | F27: =E27*Inputs!B11 -> 15372 | G27: =E27-F27 -> 292068 | H27: =Inputs!$B$26*Inputs!$B$24*N27 -> 0 | I27: =H27*Inputs!$B$25 -> 0 | J27: =G27 -> 292068 | L27: formula | M27: =IF(AND(A27>=Inputs!$B$9,A27<Inputs!$B$9+Inputs!$B$8),1,0) -> 1 | N27: =IF(AND(M27=1,Inputs!$B$24>0),1,0) -> 0
A28: 2049 | B28: =Inputs!B7 -> 100 | C28: =Inputs!B10 -> 0.35 | D28: =IF(OR(MOD(A28,400)=0,AND(MOD(A28,4)=0,MOD(A28,100)<>0)),8784,8760) -> 8760 | E28: =B28*C28*D28*M28 -> 306600 | F28: =E28*Inputs!B11 -> 15330 | G28: =E28-F28 -> 291270 | H28: =Inputs!$B$26*Inputs!$B$24*N28 -> 0 | I28: =H28*Inputs!$B$25 -> 0 | J28: =G28 -> 291270 | L28: formula | M28: =IF(AND(A28>=Inputs!$B$9,A28<Inputs!$B$9+Inputs!$B$8),1,0) -> 1 | N28: =IF(AND(M28=1,Inputs!$B$24>0),1,0) -> 0
A29: 2050 | B29: =Inputs!B7 -> 100 | C29: =Inputs!B10 -> 0.35 | D29: =IF(OR(MOD(A29,400)=0,AND(MOD(A29,4)=0,MOD(A29,100)<>0)),8784,8760) -> 8760 | E29: =B29*C29*D29*M29 -> 306600 | F29: =E29*Inputs!B11 -> 15330 | G29: =E29-F29 -> 291270 | H29: =Inputs!$B$26*Inputs!$B$24*N29 -> 0 | I29: =H29*Inputs!$B$25 -> 0 | J29: =G29 -> 291270 | L29: formula | M29: =IF(AND(A29>=Inputs!$B$9,A29<Inputs!$B$9+Inputs!$B$8),1,0) -> 1 | N29: =IF(AND(M29=1,Inputs!$B$24>0),1,0) -> 0
A30: 2051 | B30: =Inputs!B7 -> 100 | C30: =Inputs!B10 -> 0.35 | D30: =IF(OR(MOD(A30,400)=0,AND(MOD(A30,4)=0,MOD(A30,100)<>0)),8784,8760) -> 8760 | E30: =B30*C30*D30*M30 -> 306600 | F30: =E30*Inputs!B11 -> 15330 | G30: =E30-F30 -> 291270 | H30: =Inputs!$B$26*Inputs!$B$24*N30 -> 0 | I30: =H30*Inputs!$B$25 -> 0 | J30: =G30 -> 291270 | L30: formula | M30: =IF(AND(A30>=Inputs!$B$9,A30<Inputs!$B$9+Inputs!$B$8),1,0) -> 1 | N30: =IF(AND(M30=1,Inputs!$B$24>0),1,0) -> 0
A31: 2052 | B31: =Inputs!B7 -> 100 | C31: =Inputs!B10 -> 0.35 | D31: =IF(OR(MOD(A31,400)=0,AND(MOD(A31,4)=0,MOD(A31,100)<>0)),8784,8760) -> 8784 | E31: =B31*C31*D31*M31 -> 307440 | F31: =E31*Inputs!B11 -> 15372 | G31: =E31-F31 -> 292068 | H31: =Inputs!$B$26*Inputs!$B$24*N31 -> 0 | I31: =H31*Inputs!$B$25 -> 0 | J31: =G31 -> 292068 | L31: formula | M31: =IF(AND(A31>=Inputs!$B$9,A31<Inputs!$B$9+Inputs!$B$8),1,0) -> 1 | N31: =IF(AND(M31=1,Inputs!$B$24>0),1,0) -> 0
A32: 2053 | B32: =Inputs!B7 -> 100 | C32: =Inputs!B10 -> 0.35 | D32: =IF(OR(MOD(A32,400)=0,AND(MOD(A32,4)=0,MOD(A32,100)<>0)),8784,8760) -> 8760 | E32: =B32*C32*D32*M32 -> 0 | F32: =E32*Inputs!B11 -> 0 | G32: =E32-F32 -> 0 | H32: =Inputs!$B$26*Inputs!$B$24*N32 -> 0 | I32: =H32*Inputs!$B$25 -> 0 | J32: =G32 -> 0 | L32: formula | M32: =IF(AND(A32>=Inputs!$B$9,A32<Inputs!$B$9+Inputs!$B$8),1,0) -> 0 | N32: =IF(AND(M32=1,Inputs!$B$24>0),1,0) -> 0
A33: 2054 | B33: =Inputs!B7 -> 100 | C33: =Inputs!B10 -> 0.35 | D33: =IF(OR(MOD(A33,400)=0,AND(MOD(A33,4)=0,MOD(A33,100)<>0)),8784,8760) -> 8760 | E33: =B33*C33*D33*M33 -> 0 | F33: =E33*Inputs!B11 -> 0 | G33: =E33-F33 -> 0 | H33: =Inputs!$B$26*Inputs!$B$24*N33 -> 0 | I33: =H33*Inputs!$B$25 -> 0 | J33: =G33 -> 0 | L33: formula | M33: =IF(AND(A33>=Inputs!$B$9,A33<Inputs!$B$9+Inputs!$B$8),1,0) -> 0 | N33: =IF(AND(M33=1,Inputs!$B$24>0),1,0) -> 0
A34: 2055 | B34: =Inputs!B7 -> 100 | C34: =Inputs!B10 -> 0.35 | D34: =IF(OR(MOD(A34,400)=0,AND(MOD(A34,4)=0,MOD(A34,100)<>0)),8784,8760) -> 8760 | E34: =B34*C34*D34*M34 -> 0 | F34: =E34*Inputs!B11 -> 0 | G34: =E34-F34 -> 0 | H34: =Inputs!$B$26*Inputs!$B$24*N34 -> 0 | I34: =H34*Inputs!$B$25 -> 0 | J34: =G34 -> 0 | L34: formula | M34: =IF(AND(A34>=Inputs!$B$9,A34<Inputs!$B$9+Inputs!$B$8),1,0) -> 0 | N34: =IF(AND(M34=1,Inputs!$B$24>0),1,0) -> 0
A35: 2056 | B35: =Inputs!B7 -> 100 | C35: =Inputs!B10 -> 0.35 | D35: =IF(OR(MOD(A35,400)=0,AND(MOD(A35,4)=0,MOD(A35,100)<>0)),8784,8760) -> 8784 | E35: =B35*C35*D35*M35 -> 0 | F35: =E35*Inputs!B11 -> 0 | G35: =E35-F35 -> 0 | H35: =Inputs!$B$26*Inputs!$B$24*N35 -> 0 | I35: =H35*Inputs!$B$25 -> 0 | J35: =G35 -> 0 | L35: formula | M35: =IF(AND(A35>=Inputs!$B$9,A35<Inputs!$B$9+Inputs!$B$8),1,0) -> 0 | N35: =IF(AND(M35=1,Inputs!$B$24>0),1,0) -> 0
A36: 2057 | B36: =Inputs!$B$7 -> 100 | C36: =Inputs!$B$10 -> 0.35 | D36: =IF(OR(MOD(A36,400)=0,AND(MOD(A36,4)=0,MOD(A36,100)<>0)),8784,8760) -> 8760 | E36: =B36*C36*D36*M36 -> 0 | F36: =E36*Inputs!$B$11 -> 0 | G36: =E36-F36 -> 0 | H36: =Inputs!$B$26*Inputs!$B$24*N36 -> 0 | I36: =H36*Inputs!$B$25 -> 0 | J36: =G36 -> 0 | L36: formula | M36: =IF(AND(A36>=Inputs!$B$9,A36<Inputs!$B$9+Inputs!$B$8),1,0) -> 0 | N36: =IF(AND(M36=1,Inputs!$B$24>0),1,0) -> 0
A37: 2058 | B37: =Inputs!$B$7 -> 100 | C37: =Inputs!$B$10 -> 0.35 | D37: =IF(OR(MOD(A37,400)=0,AND(MOD(A37,4)=0,MOD(A37,100)<>0)),8784,8760) -> 8760 | E37: =B37*C37*D37*M37 -> 0 | F37: =E37*Inputs!$B$11 -> 0 | G37: =E37-F37 -> 0 | H37: =Inputs!$B$26*Inputs!$B$24*N37 -> 0 | I37: =H37*Inputs!$B$25 -> 0 | J37: =G37 -> 0 | L37: formula | M37: =IF(AND(A37>=Inputs!$B$9,A37<Inputs!$B$9+Inputs!$B$8),1,0) -> 0 | N37: =IF(AND(M37=1,Inputs!$B$24>0),1,0) -> 0
A39: Notes: Year 2026 is the construction year (flag = 0). Operating flag is driven by COD (Inputs!B9) and lifetime (Inputs!B8). BESS volumes are grid-side memo items (V1: BESS grid-charged), so wind export is not reduced by BESS charging; BESS revenue is built in Revenue from the net margin and reserve inputs.

Sheet Revenue
A1: REVENUE
A3: REVENUE BUILD-UP
A4: Year | B4: Net generation MWh | C4: Selected revenue price | D4: Wind revenue | E4: BESS revenue | F4: Other revenue | G4: Total revenue | H4: Fixed OPEX (wind + BESS) | I4: Variable OPEX | J4: Lease | K4: EBITDA | L4: Status
A5: 2026 | B5: =Production!J5 -> 0 | C5: =Prices!I8 -> 33.468 | D5: =B5*C5 -> 0 | E5: =(Production!I5*Inputs!$B$48+Inputs!$B$47*Inputs!$B$49*Production!N5)*Prices!L8 -> 0 | F5: 0 | G5: =SUM(D5:F5) -> 0 | H5: =(Inputs!$B$19*Inputs!$B$7*Production!M5+Inputs!$B$50*Inputs!$B$47*Production!N5)*Prices!L8 -> 0 | I5: =Inputs!$B$20*B5*Prices!L8 -> 0 | J5: =Inputs!$B$21*Inputs!$B$7*Production!M5*Prices!L8 -> 0 | K5: =G5-SUM(H5:J5) -> 0 | L5: formula
A6: 2027 | B6: =Production!J6 -> 0 | C6: =Prices!I9 -> 33.54372 | D6: =B6*C6 -> 0 | E6: =(Production!I6*Inputs!$B$48+Inputs!$B$47*Inputs!$B$49*Production!N6)*Prices!L9 -> 0 | F6: 0 | G6: =SUM(D6:F6) -> 0 | H6: =(Inputs!$B$19*Inputs!$B$7*Production!M6+Inputs!$B$50*Inputs!$B$47*Production!N6)*Prices!L9 -> 0 | I6: =Inputs!$B$20*B6*Prices!L9 -> 0 | J6: =Inputs!$B$21*Inputs!$B$7*Production!M6*Prices!L9 -> 0 | K6: =G6-SUM(H6:J6) -> 0 | L6: formula
A7: 2028 | B7: =Production!J7 -> 292068 | C7: =Prices!I10 -> 50 | D7: =B7*C7 -> 14603400 | E7: =(Production!I7*Inputs!$B$48+Inputs!$B$47*Inputs!$B$49*Production!N7)*Prices!L10 -> 0 | F7: 0 | G7: =SUM(D7:F7) -> 14603400 | H7: =(Inputs!$B$19*Inputs!$B$7*Production!M7+Inputs!$B$50*Inputs!$B$47*Production!N7)*Prices!L10 -> 4057560 | I7: =Inputs!$B$20*B7*Prices!L10 -> 0 | J7: =Inputs!$B$21*Inputs!$B$7*Production!M7*Prices!L10 -> 520200 | K7: =G7-SUM(H7:J7) -> 10025640 | L7: formula
A8: 2029 | B8: =Production!J8 -> 291270 | C8: =Prices!I11 -> 50 | D8: =B8*C8 -> 14563500 | E8: =(Production!I8*Inputs!$B$48+Inputs!$B$47*Inputs!$B$49*Production!N8)*Prices!L11 -> 0 | F8: 0 | G8: =SUM(D8:F8) -> 14563500 | H8: =(Inputs!$B$19*Inputs!$B$7*Production!M8+Inputs!$B$50*Inputs!$B$47*Production!N8)*Prices!L11 -> 4138711.2 | I8: =Inputs!$B$20*B8*Prices!L11 -> 0 | J8: =Inputs!$B$21*Inputs!$B$7*Production!M8*Prices!L11 -> 530604 | K8: =G8-SUM(H8:J8) -> 9894184.8 | L8: formula
A9: 2030 | B9: =Production!J9 -> 291270 | C9: =Prices!I12 -> 50 | D9: =B9*C9 -> 14563500 | E9: =(Production!I9*Inputs!$B$48+Inputs!$B$47*Inputs!$B$49*Production!N9)*Prices!L12 -> 0 | F9: 0 | G9: =SUM(D9:F9) -> 14563500 | H9: =(Inputs!$B$19*Inputs!$B$7*Production!M9+Inputs!$B$50*Inputs!$B$47*Production!N9)*Prices!L12 -> 4221485.4 | I9: =Inputs!$B$20*B9*Prices!L12 -> 0 | J9: =Inputs!$B$21*Inputs!$B$7*Production!M9*Prices!L12 -> 541216.08 | K9: =G9-SUM(H9:J9) -> 9800798.5 | L9: formula
A10: 2031 | B10: =Production!J10 -> 291270 | C10: =Prices!I13 -> 50 | D10: =B10*C10 -> 14563500 | E10: =(Production!I10*Inputs!$B$48+Inputs!$B$47*Inputs!$B$49*Production!N10)*Prices!L13 -> 0 | F10: 0 | G10: =SUM(D10:F10) -> 14563500 | H10: =(Inputs!$B$19*Inputs!$B$7*Production!M10+Inputs!$B$50*Inputs!$B$47*Production!N10)*Prices!L13 -> 4305915.1 | I10: =Inputs!$B$20*B10*Prices!L13 -> 0 | J10: =Inputs!$B$21*Inputs!$B$7*Production!M10*Prices!L13 -> 552040.4 | K10: =G10-SUM(H10:J10) -> 9705544.5 | L10: formula
A11: 2032 | B11: =Production!J11 -> 292068 | C11: =Prices!I14 -> 50 | D11: =B11*C11 -> 14603400 | E11: =(Production!I11*Inputs!$B$48+Inputs!$B$47*Inputs!$B$49*Production!N11)*Prices!L14 -> 0 | F11: 0 | G11: =SUM(D11:F11) -> 14603400 | H11: =(Inputs!$B$19*Inputs!$B$7*Production!M11+Inputs!$B$50*Inputs!$B$47*Production!N11)*Prices!L14 -> 4392033.4 | I11: =Inputs!$B$20*B11*Prices!L14 -> 0 | J11: =Inputs!$B$21*Inputs!$B$7*Production!M11*Prices!L14 -> 563081.21 | K11: =G11-SUM(H11:J11) -> 9648285.4 | L11: formula
A12: 2033 | B12: =Production!J12 -> 291270 | C12: =Prices!I15 -> 50 | D12: =B12*C12 -> 14563500 | E12: =(Production!I12*Inputs!$B$48+Inputs!$B$47*Inputs!$B$49*Production!N12)*Prices!L15 -> 0 | F12: 0 | G12: =SUM(D12:F12) -> 14563500 | H12: =(Inputs!$B$19*Inputs!$B$7*Production!M12+Inputs!$B$50*Inputs!$B$47*Production!N12)*Prices!L15 -> 4479874.1 | I12: =Inputs!$B$20*B12*Prices!L15 -> 0 | J12: =Inputs!$B$21*Inputs!$B$7*Production!M12*Prices!L15 -> 574342.83 | K12: =G12-SUM(H12:J12) -> 9509283.1 | L12: formula
A13: 2034 | B13: =Production!J13 -> 291270 | C13: =Prices!I16 -> 50 | D13: =B13*C13 -> 14563500 | E13: =(Production!I13*Inputs!$B$48+Inputs!$B$47*Inputs!$B$49*Production!N13)*Prices!L16 -> 0 | F13: 0 | G13: =SUM(D13:F13) -> 14563500 | H13: =(Inputs!$B$19*Inputs!$B$7*Production!M13+Inputs!$B$50*Inputs!$B$47*Production!N13)*Prices!L16 -> 4569471.6 | I13: =Inputs!$B$20*B13*Prices!L16 -> 0 | J13: =Inputs!$B$21*Inputs!$B$7*Production!M13*Prices!L16 -> 585829.69 | K13: =G13-SUM(H13:J13) -> 9408198.7 | L13: formula
A14: 2035 | B14: =Production!J14 -> 291270 | C14: =Prices!I17 -> 50 | D14: =B14*C14 -> 14563500 | E14: =(Production!I14*Inputs!$B$48+Inputs!$B$47*Inputs!$B$49*Production!N14)*Prices!L17 -> 0 | F14: 0 | G14: =SUM(D14:F14) -> 14563500 | H14: =(Inputs!$B$19*Inputs!$B$7*Production!M14+Inputs!$B$50*Inputs!$B$47*Production!N14)*Prices!L17 -> 4660861 | I14: =Inputs!$B$20*B14*Prices!L17 -> 0 | J14: =Inputs!$B$21*Inputs!$B$7*Production!M14*Prices!L17 -> 597546.28 | K14: =G14-SUM(H14:J14) -> 9305092.7 | L14: formula
A15: 2036 | B15: =Production!J15 -> 292068 | C15: =Prices!I18 -> 50 | D15: =B15*C15 -> 14603400 | E15: =(Production!I15*Inputs!$B$48+Inputs!$B$47*Inputs!$B$49*Production!N15)*Prices!L18 -> 0 | F15: 0 | G15: =SUM(D15:F15) -> 14603400 | H15: =(Inputs!$B$19*Inputs!$B$7*Production!M15+Inputs!$B$50*Inputs!$B$47*Production!N15)*Prices!L18 -> 4754078.2 | I15: =Inputs!$B$20*B15*Prices!L18 -> 0 | J15: =Inputs!$B$21*Inputs!$B$7*Production!M15*Prices!L18 -> 609497.21 | K15: =G15-SUM(H15:J15) -> 9239824.6 | L15: formula
A16: 2037 | B16: =Production!J16 -> 291270 | C16: =Prices!I19 -> 50 | D16: =B16*C16 -> 14563500 | E16: =(Production!I16*Inputs!$B$48+Inputs!$B$47*Inputs!$B$49*Production!N16)*Prices!L19 -> 0 | F16: 0 | G16: =SUM(D16:F16) -> 14563500 | H16: =(Inputs!$B$19*Inputs!$B$7*Production!M16+Inputs!$B$50*Inputs!$B$47*Production!N16)*Prices!L19 -> 4849159.8 | I16: =Inputs!$B$20*B16*Prices!L19 -> 0 | J16: =Inputs!$B$21*Inputs!$B$7*Production!M16*Prices!L19 -> 621687.15 | K16: =G16-SUM(H16:J16) -> 9092653 | L16: formula
... A37: 2058 | B37: =Production!J37 -> 0 | C37: =Prices!I40 -> 51.561031 | D37: =B37*C37 -> 0 | E37: =(Production!I37*Inputs!$B$48+Inputs!$B$47*Inputs!$B$49*Production!N37)*Prices!L40 -> 0 | F37: 0 | G37: =SUM(D37:F37) -> 0 | H37: =(Inputs!$B$19*Inputs!$B$7*Production!M37+Inputs!$B$50*Inputs!$B$47*Production!N37)*Prices!L40 -> 0 | I37: =Inputs!$B$20*B37*Prices!L40 -> 0 | J37: =Inputs!$B$21*Inputs!$B$7*Production!M37*Prices!L40 -> 0 | K37: =G37-SUM(H37:J37) -> 0 | L37: formula

Sheet Financing
A1: FINANCING
A3: DEBT SIZING
A4: Metric | B4: Value | C4: Unit | D4: Comment | F4: Sizing detail | G4: Value
A5: Target minimum DSCR | B5: =Inputs!B32 -> 1.3 | C5: x | D5: Sizing constraint | F5: Total initial CAPEX, nominal (€) | G5: =((Inputs!B14+Inputs!B16)*Inputs!B7*1000+Inputs!B15*Inputs!B24*1000)*(1+Inputs!$B$63)^(Inputs!B9-1-Cashflow!A5) -> 153000000
A6: Interest rate | B6: =Inputs!B33 -> 0.0575 | C6: % | D6: Debt pricing | F6: DSCR-sized debt, uncapped (€) | G6: =SUMPRODUCT(N14:N46,O14:O46) -> 71421308
A7: Debt tenor | B7: =Inputs!B34 -> 15 | C7: years | D7: Debt tenor | F7: Gearing-cap scale factor | G7: =IF(G6=0,1,MIN(1,Inputs!$B$59*G5/G6)) -> 1
A8: Indicative debt amount | B8: =G6*G7 -> 71421308 | C8: € | D8: DSCR-sculpted debt, capped by maximum gearing (see sizing detail) | F8: Resulting gearing (debt / CAPEX) | G8: =IF(G5=0,"",B8/G5) -> 0.46680593
A9: Indicative equity amount | B9: =G5-B8 -> 81578692 | C9: € | D9: Initial CAPEX less debt | F9: Maximum gearing (input) | G9: =Inputs!$B$59 -> 0.75
A12: DEBT SCHEDULE
A13: Year | B13: CFADS | C13: Opening debt | D13: Drawdown | E13: Interest | F13: Principal | G13: Debt service | H13: Closing debt | I13: DSCR | J13: Minimum DSCR | K13: Check | L13: Status | M13: Sizing window (1/0) | N13: Target debt service (unscaled) | O13: Discount factor
A14: 2026 | B14: =Cashflow!F5 -> 0 | C14: 0 | D14: =IF(A14=Inputs!$B$9-1,$B$8,0) -> 0 | E14: =C14*$B$6 -> 0 | F14: =IF(M14=1,N14*$G$7-E14,0) -> 0 | G14: =E14+F14 -> 0 | H14: =C14+D14-F14 -> 0 | I14: =IF(ABS(G14)<0.5,"",B14/G14) | J14: =$B$5 -> 1.3 | K14: =IF(I14="","",I14-J14) | L14: formula | M14: =IF(AND(A14>=Inputs!$B$9,A14<Inputs!$B$9+MIN($B$7,Inputs!$B$35)),1,0) -> 0 | N14: =M14*Cashflow!N5/$B$5 -> 0 | O14: =1/(1+$B$6)^(A14-(Inputs!$B$9-1)) -> 1.0575
A15: 2027 | B15: =Cashflow!F6 -> 0 | C15: =H14 -> 0 | D15: =IF(A15=Inputs!$B$9-1,$B$8,0) -> 71421308 | E15: =C15*$B$6 -> 0 | F15: =IF(M15=1,N15*$G$7-E15,0) -> 0 | G15: =E15+F15 -> 0 | H15: =C15+D15-F15 -> 71421308 | I15: =IF(ABS(G15)<0.5,"",B15/G15) | J15: =$B$5 -> 1.3 | K15: =IF(I15="","",I15-J15) | L15: formula | M15: =IF(AND(A15>=Inputs!$B$9,A15<Inputs!$B$9+MIN($B$7,Inputs!$B$35)),1,0) -> 0 | N15: =M15*Cashflow!N6/$B$5 -> 0 | O15: =1/(1+$B$6)^(A15-(Inputs!$B$9-1)) -> 1
A16: 2028 | B16: =Cashflow!F7 -> 10025640 | C16: =H15 -> 71421308 | D16: =IF(A16=Inputs!$B$9-1,$B$8,0) -> 0 | E16: =C16*$B$6 -> 4106725.2 | F16: =IF(M16=1,N16*$G$7-E16,0) -> 3605305.6 | G16: =E16+F16 -> 7712030.8 | H16: =C16+D16-F16 -> 67816002 | I16: =IF(ABS(G16)<0.5,"",B16/G16) -> 1.3 | J16: =$B$5 -> 1.3 | K16: =IF(I16="","",I16-J16) -> 0 | L16: formula | M16: =IF(AND(A16>=Inputs!$B$9,A16<Inputs!$B$9+MIN($B$7,Inputs!$B$35)),1,0) -> 1 | N16: =M16*Cashflow!N7/$B$5 -> 7712030.8 | O16: =1/(1+$B$6)^(A16-(Inputs!$B$9-1)) -> 0.94562648
A17: 2029 | B17: =Cashflow!F8 -> 9894184.8 | C17: =H16 -> 67816002 | D17: =IF(A17=Inputs!$B$9-1,$B$8,0) -> 0 | E17: =C17*$B$6 -> 3899420.1 | F17: =IF(M17=1,N17*$G$7-E17,0) -> 3711491.3 | G17: =E17+F17 -> 7610911.4 | H17: =C17+D17-F17 -> 64104511 | I17: =IF(ABS(G17)<0.5,"",B17/G17) -> 1.3 | J17: =$B$5 -> 1.3 | K17: =IF(I17="","",I17-J17) -> 0 | L17: formula | M17: =IF(AND(A17>=Inputs!$B$9,A17<Inputs!$B$9+MIN($B$7,Inputs!$B$35)),1,0) -> 1 | N17: =M17*Cashflow!N8/$B$5 -> 7610911.4 | O17: =1/(1+$B$6)^(A17-(Inputs!$B$9-1)) -> 0.89420944
A18: 2030 | B18: =Cashflow!F9 -> 9800798.5 | C18: =H17 -> 64104511 | D18: =IF(A18=Inputs!$B$9-1,$B$8,0) -> 0 | E18: =C18*$B$6 -> 3686009.4 | F18: =IF(M18=1,N18*$G$7-E18,0) -> 3853066.4 | G18: =E18+F18 -> 7539075.8 | H18: =C18+D18-F18 -> 60251445 | I18: =IF(ABS(G18)<0.5,"",B18/G18) -> 1.3 | J18: =$B$5 -> 1.3 | K18: =IF(I18="","",I18-J18) -> 0 | L18: formula | M18: =IF(AND(A18>=Inputs!$B$9,A18<Inputs!$B$9+MIN($B$7,Inputs!$B$35)),1,0) -> 1 | N18: =M18*Cashflow!N9/$B$5 -> 7539075.8 | O18: =1/(1+$B$6)^(A18-(Inputs!$B$9-1)) -> 0.84558812
A19: 2031 | B19: =Cashflow!F10 -> 9705544.5 | C19: =H18 -> 60251445 | D19: =IF(A19=Inputs!$B$9-1,$B$8,0) -> 0 | E19: =C19*$B$6 -> 3464458.1 | F19: =IF(M19=1,N19*$G$7-E19,0) -> 4001345.4 | G19: =E19+F19 -> 7465803.4 | H19: =C19+D19-F19 -> 56250099 | I19: =IF(ABS(G19)<0.5,"",B19/G19) -> 1.3 | J19: =$B$5 -> 1.3 | K19: =IF(I19="","",I19-J19) -> 0 | L19: formula | M19: =IF(AND(A19>=Inputs!$B$9,A19<Inputs!$B$9+MIN($B$7,Inputs!$B$35)),1,0) -> 1 | N19: =M19*Cashflow!N10/$B$5 -> 7465803.4 | O19: =1/(1+$B$6)^(A19-(Inputs!$B$9-1)) -> 0.79961051
A20: 2032 | B20: =Cashflow!F11 -> 9648285.4 | C20: =H19 -> 56250099 | D20: =IF(A20=Inputs!$B$9-1,$B$8,0) -> 0 | E20: =C20*$B$6 -> 3234380.7 | F20: =IF(M20=1,N20*$G$7-E20,0) -> 4187377.3 | G20: =E20+F20 -> 7421758 | H20: =C20+D20-F20 -> 52062722 | I20: =IF(ABS(G20)<0.5,"",B20/G20) -> 1.3 | J20: =$B$5 -> 1.3 | K20: =IF(I20="","",I20-J20) -> 0 | L20: formula | M20: =IF(AND(A20>=Inputs!$B$9,A20<Inputs!$B$9+MIN($B$7,Inputs!$B$35)),1,0) -> 1 | N20: =M20*Cashflow!N11/$B$5 -> 7421758 | O20: =1/(1+$B$6)^(A20-(Inputs!$B$9-1)) -> 0.75613287
A21: 2033 | B21: =Cashflow!F12 -> 9509283.1 | C21: =H20 -> 52062722 | D21: =IF(A21=Inputs!$B$9-1,$B$8,0) -> 0 | E21: =C21*$B$6 -> 2993606.5 | F21: =IF(M21=1,N21*$G$7-E21,0) -> 4321226.6 | G21: =E21+F21 -> 7314833.1 | H21: =C21+D21-F21 -> 47741495 | I21: =IF(ABS(G21)<0.5,"",B21/G21) -> 1.3 | J21: =$B$5 -> 1.3 | K21: =IF(I21="","",I21-J21) -> 0 | L21: formula | M21: =IF(AND(A21>=Inputs!$B$9,A21<Inputs!$B$9+MIN($B$7,Inputs!$B$35)),1,0) -> 1 | N21: =M21*Cashflow!N12/$B$5 -> 7314833.1 | O21: =1/(1+$B$6)^(A21-(Inputs!$B$9-1)) -> 0.71501927
A22: 2034 | B22: =Cashflow!F13 -> 9408198.7 | C22: =H21 -> 47741495 | D22: =IF(A22=Inputs!$B$9-1,$B$8,0) -> 0 | E22: =C22*$B$6 -> 2745136 | F22: =IF(M22=1,N22*$G$7-E22,0) -> 4491940 | G22: =E22+F22 -> 7237075.9 | H22: =C22+D22-F22 -> 43249555 | I22: =IF(ABS(G22)<0.5,"",B22/G22) -> 1.3 | J22: =$B$5 -> 1.3 | K22: =IF(I22="","",I22-J22) -> 2.220446e-16 | L22: formula | M22: =IF(AND(A22>=Inputs!$B$9,A22<Inputs!$B$9+MIN($B$7,Inputs!$B$35)),1,0) -> 1 | N22: =M22*Cashflow!N13/$B$5 -> 7237075.9 | O22: =1/(1+$B$6)^(A22-(Inputs!$B$9-1)) -> 0.67614115
A23: 2035 | B23: =Cashflow!F14 -> 9305092.7 | C23: =H22 -> 43249555 | D23: =IF(A23=Inputs!$B$9-1,$B$8,0) -> 0 | E23: =C23*$B$6 -> 2486849.4 | F23: =IF(M23=1,N23*$G$7-E23,0) -> 4670914.2 | G23: =E23+F23 -> 7157763.6 | H23: =C23+D23-F23 -> 38578641 | I23: =IF(ABS(G23)<0.5,"",B23/G23) -> 1.3 | J23: =$B$5 -> 1.3 | K23: =IF(I23="","",I23-J23) -> 0 | L23: formula | M23: =IF(AND(A23>=Inputs!$B$9,A23<Inputs!$B$9+MIN($B$7,Inputs!$B$35)),1,0) -> 1 | N23: =M23*Cashflow!N14/$B$5 -> 7157763.6 | O23: =1/(1+$B$6)^(A23-(Inputs!$B$9-1)) -> 0.63937697
A24: 2036 | B24: =Cashflow!F15 -> 9239824.6 | C24: =H23 -> 38578641 | D24: =IF(A24=Inputs!$B$9-1,$B$8,0) -> 0 | E24: =C24*$B$6 -> 2218271.9 | F24: =IF(M24=1,N24*$G$7-E24,0) -> 4889285.5 | G24: =E24+F24 -> 7107557.3 | H24: =C24+D24-F24 -> 33689356 | I24: =IF(ABS(G24)<0.5,"",B24/G24) -> 1.3 | J24: =$B$5 -> 1.3 | K24: =IF(I24="","",I24-J24) -> 0 | L24: formula | M24: =IF(AND(A24>=Inputs!$B$9,A24<Inputs!$B$9+MIN($B$7,Inputs!$B$35)),1,0) -> 1 | N24: =M24*Cashflow!N15/$B$5 -> 7107557.3 | O24: =1/(1+$B$6)^(A24-(Inputs!$B$9-1)) -> 0.6046118
A25: 2037 | B25: =Cashflow!F16 -> 9092653 | C25: =H24 -> 33689356 | D25: =IF(A25=Inputs!$B$9-1,$B$8,0) -> 0 | E25: =C25*$B$6 -> 1937138 | F25: =IF(M25=1,N25*$G$7-E25,0) -> 5057210.5 | G25: =E25+F25 -> 6994348.5 | H25: =C25+D25-F25 -> 28632145 | I25: =IF(ABS(G25)<0.5,"",B25/G25) -> 1.3 | J25: =$B$5 -> 1.3 | K25: =IF(I25="","",I25-J25) -> 0 | L25: formula | M25: =IF(AND(A25>=Inputs!$B$9,A25<Inputs!$B$9+MIN($B$7,Inputs!$B$35)),1,0) -> 1 | N25: =M25*Cashflow!N16/$B$5 -> 6994348.5 | O25: =1/(1+$B$6)^(A25-(Inputs!$B$9-1)) -> 0.57173692
A26: 2038 | B26: =Cashflow!F17 -> 8983236.1 | C26: =H25 -> 28632145 | D26: =IF(A26=Inputs!$B$9-1,$B$8,0) -> 0 | E26: =C26*$B$6 -> 1646348.3 | F26: =IF(M26=1,N26*$G$7-E26,0) -> 5263833.3 | G26: =E26+F26 -> 6910181.6 | H26: =C26+D26-F26 -> 23368312 | I26: =IF(ABS(G26)<0.5,"",B26/G26) -> 1.3 | J26: =$B$5 -> 1.3 | K26: =IF(I26="","",I26-J26) -> 0 | L26: formula | M26: =IF(AND(A26>=Inputs!$B$9,A26<Inputs!$B$9+MIN($B$7,Inputs!$B$35)),1,0) -> 1 | N26: =M26*Cashflow!N17/$B$5 -> 6910181.6 | O26: =1/(1+$B$6)^(A26-(Inputs!$B$9-1)) -> 0.54064957
... A46: 2058 | B46: =Cashflow!F37 -> -1.5101396e-09 | C46: =H45 -> -1.3131648e-07 | D46: =IF(A46=Inputs!$B$9-1,$B$8,0) -> 0 | E46: =C46*$B$6 -> -7.5506978e-09 | F46: =IF(M46=1,N46*$G$7-E46,0) -> 0 | G46: =E46+F46 -> -7.5506978e-09 | H46: =C46+D46-F46 -> -1.3131648e-07 | I46: =IF(ABS(G46)<0.5,"",B46/G46) | J46: =$B$5 -> 1.3 | K46: =IF(I46="","",I46-J46) | L46: formula | M46: =IF(AND(A46>=Inputs!$B$9,A46<Inputs!$B$9+MIN($B$7,Inputs!$B$35)),1,0) -> 0 | N46: =M46*Cashflow!N37/$B$5 -> 0 | O46: =1/(1+$B$6)^(A46-(Inputs!$B$9-1)) -> 0.17672921
A48: Notes: Debt is drawn at the end of the construction year (no interest during construction modelled). Target debt service = CFADS (unlevered tax) / minimum DSCR over min(tenor, sizing horizon); debt = PV of target debt service at the debt interest rate, capped at maximum gearing x CAPEX. Principal = debt service - interest.

Sheet Taxes
A1: TAXES
A3: TAX CALCULATION
A4: Year | B4: EBITDA | C4: Depreciation | D4: EBIT | E4: Interest | F4: EBT | G4: Opening tax losses | H4: Taxable income | I4: Tax losses carried | J4: Tax rate | K4: Tax | L4: Disallowed interest | M4: Taxable result before losses | N4: Opening tax losses (unlev.) | O4: Taxable income (unlev.) | P4: Tax losses carried (unlev.) | Q4: Tax (unlevered)
A5: 2026 | B5: =Cashflow!D5 -> 0 | C5: 0 | D5: =B5-C5 -> 0 | E5: =Financing!E14 -> 0 | F5: =D5-E5 -> 0 | G5: 0 | H5: =MAX(0,M5-G5) -> 0 | I5: =MAX(0,G5-M5) -> 0 | J5: =Inputs!B29 -> 0.2 | K5: =H5*J5 -> 0 | L5: =E5-MIN(E5,MAX(Inputs!$B$58,Inputs!$B$57*MAX(B5,0))) -> 0 | M5: =F5+L5 -> 0 | N5: 0 | O5: =MAX(0,D5-N5) -> 0 | P5: =MAX(0,N5-D5) -> 0 | Q5: =O5*J5 -> 0
A6: 2027 | B6: =Cashflow!D6 -> 0 | C6: =Inputs!$B$56*(SUM(Cashflow!$E$5:E5)-SUM($C$5:C5))*Production!M6 -> 0 | D6: =B6-C6 -> 0 | E6: =Financing!E15 -> 0 | F6: =D6-E6 -> 0 | G6: =I5 -> 0 | H6: =MAX(0,M6-G6) -> 0 | I6: =MAX(0,G6-M6) -> 0 | J6: =Inputs!B29 -> 0.2 | K6: =H6*J6 -> 0 | L6: =E6-MIN(E6,MAX(Inputs!$B$58,Inputs!$B$57*MAX(B6,0))) -> 0 | M6: =F6+L6 -> 0 | N6: =P5 -> 0 | O6: =MAX(0,D6-N6) -> 0 | P6: =MAX(0,N6-D6) -> 0 | Q6: =O6*J6 -> 0
A7: 2028 | B7: =Cashflow!D7 -> 10025640 | C7: =Inputs!$B$56*(SUM(Cashflow!$E$5:E6)-SUM($C$5:C6))*Production!M7 -> 35955000 | D7: =B7-C7 -> -25929360 | E7: =Financing!E16 -> 4106725.2 | F7: =D7-E7 -> -30036085 | G7: =I6 -> 0 | H7: =MAX(0,M7-G7) -> 0 | I7: =MAX(0,G7-M7) -> 28435770 | J7: =Inputs!B29 -> 0.2 | K7: =H7*J7 -> 0 | L7: =E7-MIN(E7,MAX(Inputs!$B$58,Inputs!$B$57*MAX(B7,0))) -> 1600315.2 | M7: =F7+L7 -> -28435770 | N7: =P6 -> 0 | O7: =MAX(0,D7-N7) -> 0 | P7: =MAX(0,N7-D7) -> 25929360 | Q7: =O7*J7 -> 0
A8: 2029 | B8: =Cashflow!D8 -> 9894184.8 | C8: =Inputs!$B$56*(SUM(Cashflow!$E$5:E7)-SUM($C$5:C7))*Production!M8 -> 27505575 | D8: =B8-C8 -> -17611390 | E8: =Financing!E17 -> 3899420.1 | F8: =D8-E8 -> -21510810 | G8: =I7 -> 28435770 | H8: =MAX(0,M8-G8) -> 0 | I8: =MAX(0,G8-M8) -> 48520706 | J8: =Inputs!B29 -> 0.2 | K8: =H8*J8 -> 0 | L8: =E8-MIN(E8,MAX(Inputs!$B$58,Inputs!$B$57*MAX(B8,0))) -> 1425873.9 | M8: =F8+L8 -> -20084936 | N8: =P7 -> 25929360 | O8: =MAX(0,D8-N8) -> 0 | P8: =MAX(0,N8-D8) -> 43540750 | Q8: =O8*J8 -> 0
A9: 2030 | B9: =Cashflow!D9 -> 9800798.5 | C9: =Inputs!$B$56*(SUM(Cashflow!$E$5:E8)-SUM($C$5:C8))*Production!M9 -> 21041765 | D9: =B9-C9 -> -11240966 | E9: =Financing!E18 -> 3686009.4 | F9: =D9-E9 -> -14926976 | G9: =I8 -> 48520706 | H9: =MAX(0,M9-G9) -> 0 | I9: =MAX(0,G9-M9) -> 62211872 | J9: =Inputs!B29 -> 0.2 | K9: =H9*J9 -> 0 | L9: =E9-MIN(E9,MAX(Inputs!$B$58,Inputs!$B$57*MAX(B9,0))) -> 1235809.8 | M9: =F9+L9 -> -13691166 | N9: =P8 -> 43540750 | O9: =MAX(0,D9-N9) -> 0 | P9: =MAX(0,N9-D9) -> 54781717 | Q9: =O9*J9 -> 0
A10: 2031 | B10: =Cashflow!D10 -> 9705544.5 | C10: =Inputs!$B$56*(SUM(Cashflow!$E$5:E9)-SUM($C$5:C9))*Production!M10 -> 16096950 | D10: =B10-C10 -> -6391405.7 | E10: =Financing!E19 -> 3464458.1 | F10: =D10-E10 -> -9855863.7 | G10: =I9 -> 62211872 | H10: =MAX(0,M10-G10) -> 0 | I10: =MAX(0,G10-M10) -> 71029664 | J10: =Inputs!B29 -> 0.2 | K10: =H10*J10 -> 0 | L10: =E10-MIN(E10,MAX(Inputs!$B$58,Inputs!$B$57*MAX(B10,0))) -> 1038071.9 | M10: =F10+L10 -> -8817791.8 | N10: =P9 -> 54781717 | O10: =MAX(0,D10-N10) -> 0 | P10: =MAX(0,N10-D10) -> 61173122 | Q10: =O10*J10 -> 0
A11: 2032 | B11: =Cashflow!D11 -> 9648285.4 | C11: =Inputs!$B$56*(SUM(Cashflow!$E$5:E10)-SUM($C$5:C10))*Production!M11 -> 12314167 | D11: =B11-C11 -> -2665881.5 | E11: =Financing!E20 -> 3234380.7 | F11: =D11-E11 -> -5900262.2 | G11: =I10 -> 71029664 | H11: =MAX(0,M11-G11) -> 0 | I11: =MAX(0,G11-M11) -> 76107617 | J11: =Inputs!B29 -> 0.2 | K11: =H11*J11 -> 0 | L11: =E11-MIN(E11,MAX(Inputs!$B$58,Inputs!$B$57*MAX(B11,0))) -> 822309.37 | M11: =F11+L11 -> -5077952.8 | N11: =P10 -> 61173122 | O11: =MAX(0,D11-N11) -> 0 | P11: =MAX(0,N11-D11) -> 63839004 | Q11: =O11*J11 -> 0
A12: 2033 | B12: =Cashflow!D12 -> 9509283.1 | C12: =Inputs!$B$56*(SUM(Cashflow!$E$5:E11)-SUM($C$5:C11))*Production!M12 -> 9420337.6 | D12: =B12-C12 -> 88945.423 | E12: =Financing!E21 -> 2993606.5 | F12: =D12-E12 -> -2904661.1 | G12: =I11 -> 76107617 | H12: =MAX(0,M12-G12) -> 0 | I12: =MAX(0,G12-M12) -> 78395992 | J12: =Inputs!B29 -> 0.2 | K12: =H12*J12 -> 0 | L12: =E12-MIN(E12,MAX(Inputs!$B$58,Inputs!$B$57*MAX(B12,0))) -> 616285.75 | M12: =F12+L12 -> -2288375.3 | N12: =P11 -> 63839004 | O12: =MAX(0,D12-N12) -> 0 | P12: =MAX(0,N12-D12) -> 63750058 | Q12: =O12*J12 -> 0
A13: 2034 | B13: =Cashflow!D13 -> 9408198.7 | C13: =Inputs!$B$56*(SUM(Cashflow!$E$5:E12)-SUM($C$5:C12))*Production!M13 -> 7206558.3 | D13: =B13-C13 -> 2201640.4 | E13: =Financing!E22 -> 2745136 | F13: =D13-E13 -> -543495.55 | G13: =I12 -> 78395992 | H13: =MAX(0,M13-G13) -> 0 | I13: =MAX(0,G13-M13) -> 78546402 | J13: =Inputs!B29 -> 0.2 | K13: =H13*J13 -> 0 | L13: =E13-MIN(E13,MAX(Inputs!$B$58,Inputs!$B$57*MAX(B13,0))) -> 393086.3 | M13: =F13+L13 -> -150409.25 | N13: =P12 -> 63750058 | O13: =MAX(0,D13-N13) -> 0 | P13: =MAX(0,N13-D13) -> 61548418 | Q13: =O13*J13 -> 0
A14: 2035 | B14: =Cashflow!D14 -> 9305092.7 | C14: =Inputs!$B$56*(SUM(Cashflow!$E$5:E13)-SUM($C$5:C13))*Production!M14 -> 5513017.1 | D14: =B14-C14 -> 3792075.6 | E14: =Financing!E23 -> 2486849.4 | F14: =D14-E14 -> 1305226.2 | G14: =I13 -> 78546402 | H14: =MAX(0,M14-G14) -> 0 | I14: =MAX(0,G14-M14) -> 77080599 | J14: =Inputs!B29 -> 0.2 | K14: =H14*J14 -> 0 | L14: =E14-MIN(E14,MAX(Inputs!$B$58,Inputs!$B$57*MAX(B14,0))) -> 160576.26 | M14: =F14+L14 -> 1465802.4 | N14: =P13 -> 61548418 | O14: =MAX(0,D14-N14) -> 0 | P14: =MAX(0,N14-D14) -> 57756342 | Q14: =O14*J14 -> 0
A15: 2036 | B15: =Cashflow!D15 -> 9239824.6 | C15: =Inputs!$B$56*(SUM(Cashflow!$E$5:E14)-SUM($C$5:C14))*Production!M15 -> 4217458.1 | D15: =B15-C15 -> 5022366.5 | E15: =Financing!E24 -> 2218271.9 | F15: =D15-E15 -> 2804094.6 | G15: =I14 -> 77080599 | H15: =MAX(0,M15-G15) -> 0 | I15: =MAX(0,G15-M15) -> 74276505 | J15: =Inputs!B29 -> 0.2 | K15: =H15*J15 -> 0 | L15: =E15-MIN(E15,MAX(Inputs!$B$58,Inputs!$B$57*MAX(B15,0))) -> 0 | M15: =F15+L15 -> 2804094.6 | N15: =P14 -> 57756342 | O15: =MAX(0,D15-N15) -> 0 | P15: =MAX(0,N15-D15) -> 52733976 | Q15: =O15*J15 -> 0
A16: 2037 | B16: =Cashflow!D16 -> 9092653 | C16: =Inputs!$B$56*(SUM(Cashflow!$E$5:E15)-SUM($C$5:C15))*Production!M16 -> 3226355.4 | D16: =B16-C16 -> 5866297.6 | E16: =Financing!E25 -> 1937138 | F16: =D16-E16 -> 3929159.7 | G16: =I15 -> 74276505 | H16: =MAX(0,M16-G16) -> 0 | I16: =MAX(0,G16-M16) -> 70347345 | J16: =Inputs!B29 -> 0.2 | K16: =H16*J16 -> 0 | L16: =E16-MIN(E16,MAX(Inputs!$B$58,Inputs!$B$57*MAX(B16,0))) -> 0 | M16: =F16+L16 -> 3929159.7 | N16: =P15 -> 52733976 | O16: =MAX(0,D16-N16) -> 0 | P16: =MAX(0,N16-D16) -> 46867678 | Q16: =O16*J16 -> 0
A17: 2038 | B17: =Cashflow!D17 -> 8983236.1 | C17: =Inputs!$B$56*(SUM(Cashflow!$E$5:E16)-SUM($C$5:C16))*Production!M17 -> 2468161.9 | D17: =B17-C17 -> 6515074.2 | E17: =Financing!E26 -> 1646348.3 | F17: =D17-E17 -> 4868725.9 | G17: =I16 -> 70347345 | H17: =MAX(0,M17-G17) -> 0 | I17: =MAX(0,G17-M17) -> 65478619 | J17: =Inputs!B29 -> 0.2 | K17: =H17*J17 -> 0 | L17: =E17-MIN(E17,MAX(Inputs!$B$58,Inputs!$B$57*MAX(B17,0))) -> 0 | M17: =F17+L17 -> 4868725.9 | N17: =P16 -> 46867678 | O17: =MAX(0,D17-N17) -> 0 | P17: =MAX(0,N17-D17) -> 40352604 | Q17: =O17*J17 -> 0
A18: 2039 | B18: =Cashflow!D18 -> 8871630.8 | C18: =Inputs!$B$56*(SUM(Cashflow!$E$5:E17)-SUM($C$5:C17))*Production!M18 -> 1888143.9 | D18: =B18-C18 -> 6983487 | E18: =Financing!E27 -> 1343677.9 | F18: =D18-E18 -> 5639809 | G18: =I17 -> 65478619 | H18: =MAX(0,M18-G18) -> 0 | I18: =MAX(0,G18-M18) -> 59838810 | J18: =Inputs!B29 -> 0.2 | K18: =H18*J18 -> 0 | L18: =E18-MIN(E18,MAX(Inputs!$B$58,Inputs!$B$57*MAX(B18,0))) -> 0 | M18: =F18+L18 -> 5639809 | N18: =P17 -> 40352604 | O18: =MAX(0,D18-N18) -> 0 | P18: =MAX(0,N18-D18) -> 33369117 | Q18: =O18*J18 -> 0
A19: 2040 | B19: =Cashflow!D19 -> 8797693.4 | C19: =Inputs!$B$56*(SUM(Cashflow!$E$5:E18)-SUM($C$5:C18))*Production!M19 -> 1444430 | D19: =B19-C19 -> 7353263.4 | E19: =Financing!E28 -> 1028540.4 | F19: =D19-E19 -> 6324723 | G19: =I18 -> 59838810 | H19: =MAX(0,M19-G19) -> 0 | I19: =MAX(0,G19-M19) -> 53514087 | J19: =Inputs!B29 -> 0.2 | K19: =H19*J19 -> 0 | L19: =E19-MIN(E19,MAX(Inputs!$B$58,Inputs!$B$57*MAX(B19,0))) -> 0 | M19: =F19+L19 -> 6324723 | N19: =P18 -> 33369117 | O19: =MAX(0,D19-N19) -> 0 | P19: =MAX(0,N19-D19) -> 26015854 | Q19: =O19*J19 -> 0
A20: 2041 | B20: =Cashflow!D20 -> 8641679.3 | C20: =Inputs!$B$56*(SUM(Cashflow!$E$5:E19)-SUM($C$5:C19))*Production!M20 -> 1104989 | D20: =B20-C20 -> 7536690.3 | E20: =Financing!E29 -> 698552.68 | F20: =D20-E20 -> 6838137.6 | G20: =I19 -> 53514087 | H20: =MAX(0,M20-G20) -> 0 | I20: =MAX(0,G20-M20) -> 46675949 | J20: =Inputs!B29 -> 0.2 | K20: =H20*J20 -> 0 | L20: =E20-MIN(E20,MAX(Inputs!$B$58,Inputs!$B$57*MAX(B20,0))) -> 0 | M20: =F20+L20 -> 6838137.6 | N20: =P19 -> 26015854 | O20: =MAX(0,D20-N20) -> 0 | P20: =MAX(0,N20-D20) -> 18479163 | Q20: =O20*J20 -> 0
A21: 2042 | B21: =Cashflow!D21 -> 8523242.9 | C21: =Inputs!$B$56*(SUM(Cashflow!$E$5:E20)-SUM($C$5:C20))*Production!M21 -> 845316.58 | D21: =B21-C21 -> 7677926.3 | E21: =Financing!E30 -> 356491.34 | F21: =D21-E21 -> 7321435 | G21: =I20 -> 46675949 | H21: =MAX(0,M21-G21) -> 0 | I21: =MAX(0,G21-M21) -> 39354514 | J21: =Inputs!B29 -> 0.2 | K21: =H21*J21 -> 0 | L21: =E21-MIN(E21,MAX(Inputs!$B$58,Inputs!$B$57*MAX(B21,0))) -> 0 | M21: =F21+L21 -> 7321435 | N21: =P20 -> 18479163 | O21: =MAX(0,D21-N21) -> 0 | P21: =MAX(0,N21-D21) -> 10801237 | Q21: =O21*J21 -> 0
A22: 2043 | B22: =Cashflow!D22 -> 4004149.2 | C22: =Inputs!$B$56*(SUM(Cashflow!$E$5:E21)-SUM($C$5:C21))*Production!M22 -> 646667.18 | D22: =B22-C22 -> 3357482.1 | E22: =Financing!E31 -> -7.5506978e-09 | F22: =D22-E22 -> 3357482.1 | G22: =I21 -> 39354514 | H22: =MAX(0,M22-G22) -> 0 | I22: =MAX(0,G22-M22) -> 35997032 | J22: =Inputs!B29 -> 0.2 | K22: =H22*J22 -> 0 | L22: =E22-MIN(E22,MAX(Inputs!$B$58,Inputs!$B$57*MAX(B22,0))) -> 0 | M22: =F22+L22 -> 3357482.1 | N22: =P21 -> 10801237 | O22: =MAX(0,D22-N22) -> 0 | P22: =MAX(0,N22-D22) -> 7443754.9 | Q22: =O22*J22 -> 0
A23: 2044 | B23: =Cashflow!D23 -> 4257805.6 | C23: =Inputs!$B$56*(SUM(Cashflow!$E$5:E22)-SUM($C$5:C22))*Production!M23 -> 494700.39 | D23: =B23-C23 -> 3763105.2 | E23: =Financing!E32 -> -7.5506978e-09 | F23: =D23-E23 -> 3763105.2 | G23: =I22 -> 35997032 | H23: =MAX(0,M23-G23) -> 0 | I23: =MAX(0,G23-M23) -> 32233927 | J23: =Inputs!B29 -> 0.2 | K23: =H23*J23 -> 0 | L23: =E23-MIN(E23,MAX(Inputs!$B$58,Inputs!$B$57*MAX(B23,0))) -> 0 | M23: =F23+L23 -> 3763105.2 | N23: =P22 -> 7443754.9 | O23: =MAX(0,D23-N23) -> 0 | P23: =MAX(0,N23-D23) -> 3680649.7 | Q23: =O23*J23 -> 0
A24: 2045 | B24: =Cashflow!D24 -> 4461247.3 | C24: =Inputs!$B$56*(SUM(Cashflow!$E$5:E23)-SUM($C$5:C23))*Production!M24 -> 378445.8 | D24: =B24-C24 -> 4082801.5 | E24: =Financing!E33 -> -7.5506978e-09 | F24: =D24-E24 -> 4082801.5 | G24: =I23 -> 32233927 | H24: =MAX(0,M24-G24) -> 0 | I24: =MAX(0,G24-M24) -> 28151126 | J24: =Inputs!B29 -> 0.2 | K24: =H24*J24 -> 0 | L24: =E24-MIN(E24,MAX(Inputs!$B$58,Inputs!$B$57*MAX(B24,0))) -> 0 | M24: =F24+L24 -> 4082801.5 | N24: =P23 -> 3680649.7 | O24: =MAX(0,D24-N24) -> 402151.8 | P24: =MAX(0,N24-D24) -> 0 | Q24: =O24*J24 -> 80430.36
A25: 2046 | B25: =Cashflow!D25 -> 4701090.8 | C25: =Inputs!$B$56*(SUM(Cashflow!$E$5:E24)-SUM($C$5:C24))*Production!M25 -> 289511.04 | D25: =B25-C25 -> 4411579.8 | E25: =Financing!E34 -> -7.5506978e-09 | F25: =D25-E25 -> 4411579.8 | G25: =I24 -> 28151126 | H25: =MAX(0,M25-G25) -> 0 | I25: =MAX(0,G25-M25) -> 23739546 | J25: =Inputs!B29 -> 0.2 | K25: =H25*J25 -> 0 | L25: =E25-MIN(E25,MAX(Inputs!$B$58,Inputs!$B$57*MAX(B25,0))) -> 0 | M25: =F25+L25 -> 4411579.8 | N25: =P24 -> 0 | O25: =MAX(0,D25-N25) -> 4411579.8 | P25: =MAX(0,N25-D25) -> 0 | Q25: =O25*J25 -> 882315.96
A26: 2047 | B26: =Cashflow!D26 -> 4948743.6 | C26: =Inputs!$B$56*(SUM(Cashflow!$E$5:E25)-SUM($C$5:C25))*Production!M26 -> 221475.94 | D26: =B26-C26 -> 4727267.6 | E26: =Financing!E35 -> -7.5506978e-09 | F26: =D26-E26 -> 4727267.6 | G26: =I25 -> 23739546 | H26: =MAX(0,M26-G26) -> 0 | I26: =MAX(0,G26-M26) -> 19012278 | J26: =Inputs!B29 -> 0.2 | K26: =H26*J26 -> 0 | L26: =E26-MIN(E26,MAX(Inputs!$B$58,Inputs!$B$57*MAX(B26,0))) -> 0 | M26: =F26+L26 -> 4727267.6 | N26: =P25 -> 0 | O26: =MAX(0,D26-N26) -> 4727267.6 | P26: =MAX(0,N26-D26) -> 0 | Q26: =O26*J26 -> 945453.52
A27: 2048 | B27: =Cashflow!D27 -> 5237317.1 | C27: =Inputs!$B$56*(SUM(Cashflow!$E$5:E26)-SUM($C$5:C26))*Production!M27 -> 169429.1 | D27: =B27-C27 -> 5067888 | E27: =Financing!E36 -> -7.5506978e-09 | F27: =D27-E27 -> 5067888 | G27: =I26 -> 19012278 | H27: =MAX(0,M27-G27) -> 0 | I27: =MAX(0,G27-M27) -> 13944390 | J27: =Inputs!B29 -> 0.2 | K27: =H27*J27 -> 0 | L27: =E27-MIN(E27,MAX(Inputs!$B$58,Inputs!$B$57*MAX(B27,0))) -> 0 | M27: =F27+L27 -> 5067888 | N27: =P26 -> 0 | O27: =MAX(0,D27-N27) -> 5067888 | P27: =MAX(0,N27-D27) -> 0 | Q27: =O27*J27 -> 1013577.6
A28: 2049 | B28: =Cashflow!D28 -> 5468348 | C28: =Inputs!$B$56*(SUM(Cashflow!$E$5:E27)-SUM($C$5:C27))*Production!M28 -> 129613.26 | D28: =B28-C28 -> 5338734.7 | E28: =Financing!E37 -> -7.5506978e-09 | F28: =D28-E28 -> 5338734.7 | G28: =I27 -> 13944390 | H28: =MAX(0,M28-G28) -> 0 | I28: =MAX(0,G28-M28) -> 8605655.4 | J28: =Inputs!B29 -> 0.2 | K28: =H28*J28 -> 0 | L28: =E28-MIN(E28,MAX(Inputs!$B$58,Inputs!$B$57*MAX(B28,0))) -> 0 | M28: =F28+L28 -> 5338734.7 | N28: =P27 -> 0 | O28: =MAX(0,D28-N28) -> 5338734.7 | P28: =MAX(0,N28-D28) -> 0 | Q28: =O28*J28 -> 1067746.9
A29: 2050 | B29: =Cashflow!D29 -> 5740749.3 | C29: =Inputs!$B$56*(SUM(Cashflow!$E$5:E28)-SUM($C$5:C28))*Production!M29 -> 99154.143 | D29: =B29-C29 -> 5641595.2 | E29: =Financing!E38 -> -7.5506978e-09 | F29: =D29-E29 -> 5641595.2 | G29: =I28 -> 8605655.4 | H29: =MAX(0,M29-G29) -> 0 | I29: =MAX(0,G29-M29) -> 2964060.3 | J29: =Inputs!B29 -> 0.2 | K29: =H29*J29 -> 0 | L29: =E29-MIN(E29,MAX(Inputs!$B$58,Inputs!$B$57*MAX(B29,0))) -> 0 | M29: =F29+L29 -> 5641595.2 | N29: =P28 -> 0 | O29: =MAX(0,D29-N29) -> 5641595.2 | P29: =MAX(0,N29-D29) -> 0 | Q29: =O29*J29 -> 1128319
A30: 2051 | B30: =Cashflow!D30 -> 5855564.3 | C30: =Inputs!$B$56*(SUM(Cashflow!$E$5:E29)-SUM($C$5:C29))*Production!M30 -> 75852.92 | D30: =B30-C30 -> 5779711.4 | E30: =Financing!E39 -> -7.5506978e-09 | F30: =D30-E30 -> 5779711.4 | G30: =I29 -> 2964060.3 | H30: =MAX(0,M30-G30) -> 2815651.1 | I30: =MAX(0,G30-M30) -> 0 | J30: =Inputs!B29 -> 0.2 | K30: =H30*J30 -> 563130.22 | L30: =E30-MIN(E30,MAX(Inputs!$B$58,Inputs!$B$57*MAX(B30,0))) -> 0 | M30: =F30+L30 -> 5779711.4 | N30: =P29 -> 0 | O30: =MAX(0,D30-N30) -> 5779711.4 | P30: =MAX(0,N30-D30) -> 0 | Q30: =O30*J30 -> 1155942.3
A31: 2052 | B31: =Cashflow!D31 -> 6009211.8 | C31: =Inputs!$B$56*(SUM(Cashflow!$E$5:E30)-SUM($C$5:C30))*Production!M31 -> 58027.484 | D31: =B31-C31 -> 5951184.3 | E31: =Financing!E40 -> -7.5506978e-09 | F31: =D31-E31 -> 5951184.3 | G31: =I30 -> 0 | H31: =MAX(0,M31-G31) -> 5951184.3 | I31: =MAX(0,G31-M31) -> 0 | J31: =Inputs!B29 -> 0.2 | K31: =H31*J31 -> 1190236.9 | L31: =E31-MIN(E31,MAX(Inputs!$B$58,Inputs!$B$57*MAX(B31,0))) -> 0 | M31: =F31+L31 -> 5951184.3 | N31: =P30 -> 0 | O31: =MAX(0,D31-N31) -> 5951184.3 | P31: =MAX(0,N31-D31) -> 0 | Q31: =O31*J31 -> 1190236.9
A32: 2053 | B32: =Cashflow!D32 -> 0 | C32: =Inputs!$B$56*(SUM(Cashflow!$E$5:E31)-SUM($C$5:C31))*Production!M32 -> 0 | D32: =B32-C32 -> 0 | E32: =Financing!E41 -> -7.5506978e-09 | F32: =D32-E32 -> 7.5506978e-09 | G32: =I31 -> 0 | H32: =MAX(0,M32-G32) -> 7.5506978e-09 | I32: =MAX(0,G32-M32) -> 0 | J32: =Inputs!B29 -> 0.2 | K32: =H32*J32 -> 1.5101396e-09 | L32: =E32-MIN(E32,MAX(Inputs!$B$58,Inputs!$B$57*MAX(B32,0))) -> 0 | M32: =F32+L32 -> 7.5506978e-09 | N32: =P31 -> 0 | O32: =MAX(0,D32-N32) -> 0 | P32: =MAX(0,N32-D32) -> 0 | Q32: =O32*J32 -> 0
A33: 2054 | B33: =Cashflow!D33 -> 0 | C33: =Inputs!$B$56*(SUM(Cashflow!$E$5:E32)-SUM($C$5:C32))*Production!M33 -> 0 | D33: =B33-C33 -> 0 | E33: =Financing!E42 -> -7.5506978e-09 | F33: =D33-E33 -> 7.5506978e-09 | G33: =I32 -> 0 | H33: =MAX(0,M33-G33) -> 7.5506978e-09 | I33: =MAX(0,G33-M33) -> 0 | J33: =Inputs!B29 -> 0.2 | K33: =H33*J33 -> 1.5101396e-09 | L33: =E33-MIN(E33,MAX(Inputs!$B$58,Inputs!$B$57*MAX(B33,0))) -> 0 | M33: =F33+L33 -> 7.5506978e-09 | N33: =P32 -> 0 | O33: =MAX(0,D33-N33) -> 0 | P33: =MAX(0,N33-D33) -> 0 | Q33: =O33*J33 -> 0
A34: 2055 | B34: =Cashflow!D34 -> 0 | C34: =Inputs!$B$56*(SUM(Cashflow!$E$5:E33)-SUM($C$5:C33))*Production!M34 -> 0 | D34: =B34-C34 -> 0 | E34: =Financing!E43 -> -7.5506978e-09 | F34: =D34-E34 -> 7.5506978e-09 | G34: =I33 -> 0 | H34: =MAX(0,M34-G34) -> 7.5506978e-09 | I34: =MAX(0,G34-M34) -> 0 | J34: =Inputs!B29 -> 0.2 | K34: =H34*J34 -> 1.5101396e-09 | L34: =E34-MIN(E34,MAX(Inputs!$B$58,Inputs!$B$57*MAX(B34,0))) -> 0 | M34: =F34+L34 -> 7.5506978e-09 | N34: =P33 -> 0 | O34: =MAX(0,D34-N34) -> 0 | P34: =MAX(0,N34-D34) -> 0 | Q34: =O34*J34 -> 0
A35: 2056 | B35: =Cashflow!D35 -> 0 | C35: =Inputs!$B$56*(SUM(Cashflow!$E$5:E34)-SUM($C$5:C34))*Production!M35 -> 0 | D35: =B35-C35 -> 0 | E35: =Financing!E44 -> -7.5506978e-09 | F35: =D35-E35 -> 7.5506978e-09 | G35: =I34 -> 0 | H35: =MAX(0,M35-G35) -> 7.5506978e-09 | I35: =MAX(0,G35-M35) -> 0 | J35: =Inputs!B29 -> 0.2 | K35: =H35*J35 -> 1.5101396e-09 | L35: =E35-MIN(E35,MAX(Inputs!$B$58,Inputs!$B$57*MAX(B35,0))) -> 0 | M35: =F35+L35 -> 7.5506978e-09 | N35: =P34 -> 0 | O35: =MAX(0,D35-N35) -> 0 | P35: =MAX(0,N35-D35) -> 0 | Q35: =O35*J35 -> 0
A36: 2057 | B36: =Cashflow!D36 -> 0 | C36: =Inputs!$B$56*(SUM(Cashflow!$E$5:E35)-SUM($C$5:C35))*Production!M36 -> 0 | D36: =B36-C36 -> 0 | E36: =Financing!E45 -> -7.5506978e-09 | F36: =D36-E36 -> 7.5506978e-09 | G36: =I35 -> 0 | H36: =MAX(0,M36-G36) -> 7.5506978e-09 | I36: =MAX(0,G36-M36) -> 0 | J36: =Inputs!$B$29 -> 0.2 | K36: =H36*J36 -> 1.5101396e-09 | L36: =E36-MIN(E36,MAX(Inputs!$B$58,Inputs!$B$57*MAX(B36,0))) -> 0 | M36: =F36+L36 -> 7.5506978e-09 | N36: =P35 -> 0 | O36: =MAX(0,D36-N36) -> 0 | P36: =MAX(0,N36-D36) -> 0 | Q36: =O36*J36 -> 0
A37: 2058 | B37: =Cashflow!D37 -> 0 | C37: =Inputs!$B$56*(SUM(Cashflow!$E$5:E36)-SUM($C$5:C36))*Production!M37 -> 0 | D37: =B37-C37 -> 0 | E37: =Financing!E46 -> -7.5506978e-09 | F37: =D37-E37 -> 7.5506978e-09 | G37: =I36 -> 0 | H37: =MAX(0,M37-G37) -> 7.5506978e-09 | I37: =MAX(0,G37-M37) -> 0 | J37: =Inputs!$B$29 -> 0.2 | K37: =H37*J37 -> 1.5101396e-09 | L37: =E37-MIN(E37,MAX(Inputs!$B$58,Inputs!$B$57*MAX(B37,0))) -> 0 | M37: =F37+L37 -> 7.5506978e-09 | N37: =P36 -> 0 | O37: =MAX(0,D37-N37) -> 0 | P37: =MAX(0,N37-D37) -> 0 | Q37: =O37*J37 -> 0
A39: Notes: Tax depreciation = declining balance on CAPEX placed in service (spend in year t depreciates from t+1). Interest above the threshold is deductible only up to the EBITDA cap; disallowed interest is not carried forward. Loss carry-forward has no expiry in this version (10 years under current law; 25 years proposed from 2026 losses - to verify).

Sheet Cashflow
A1: CASHFLOW
A3: PROJECT CASH FLOW
A4: Year | B4: Revenue | C4: OPEX | D4: EBITDA | E4: CAPEX / decom. | F4: CFADS (after tax) | G4: Debt service | H4: Tax | I4: Project FCF (unlevered) | J4: Equity FCF | K4: Cumulative equity CF | L4: Status | M4: Tax (unlevered) | N4: CFADS for sizing | O4: Discount factor
A5: 2026 | B5: =Revenue!G5 -> 0 | C5: =SUM(Revenue!H5:J5) -> 0 | D5: =B5-C5 -> 0 | E5: =IF(A5=Inputs!$B$9-1,Financing!$G$5,0)+IF(AND(A5=Inputs!$B$9+Inputs!$B$51,Inputs!$B$51<Inputs!$B$8),Inputs!$B$52*Inputs!$B$15*Inputs!$B$24*1000*Prices!L8,0)+IF(A5=Inputs!$B$9+Inputs!$B$8-1,Inputs!$B$55*Inputs!$B$7*1000*Prices!L8,0) -> 0 | F5: =D5-H5 -> 0 | G5: =Financing!G14 -> 0 | H5: =Taxes!K5 -> 0 | I5: =D5-M5-E5 -> 0 | J5: =D5-H5-E5-G5+Financing!D14 -> 0 | K5: =J5 -> 0 | L5: formula | M5: =Taxes!Q5 -> 0 | N5: =D5-M5 -> 0 | O5: =1/(1+Inputs!$B$38)^(A5-$A$5) -> 1
A6: 2027 | B6: =Revenue!G6 -> 0 | C6: =SUM(Revenue!H6:J6) -> 0 | D6: =B6-C6 -> 0 | E6: =IF(A6=Inputs!$B$9-1,Financing!$G$5,0)+IF(AND(A6=Inputs!$B$9+Inputs!$B$51,Inputs!$B$51<Inputs!$B$8),Inputs!$B$52*Inputs!$B$15*Inputs!$B$24*1000*Prices!L9,0)+IF(A6=Inputs!$B$9+Inputs!$B$8-1,Inputs!$B$55*Inputs!$B$7*1000*Prices!L9,0) -> 153000000 | F6: =D6-H6 -> 0 | G6: =Financing!G15 -> 0 | H6: =Taxes!K6 -> 0 | I6: =D6-M6-E6 -> -153000000 | J6: =D6-H6-E6-G6+Financing!D15 -> -81578692 | K6: =K5+J6 -> -81578692 | L6: formula | M6: =Taxes!Q6 -> 0 | N6: =D6-M6 -> 0 | O6: =1/(1+Inputs!$B$38)^(A6-$A$5) -> 0.94339623
A7: 2028 | B7: =Revenue!G7 -> 14603400 | C7: =SUM(Revenue!H7:J7) -> 4577760 | D7: =B7-C7 -> 10025640 | E7: =IF(A7=Inputs!$B$9-1,Financing!$G$5,0)+IF(AND(A7=Inputs!$B$9+Inputs!$B$51,Inputs!$B$51<Inputs!$B$8),Inputs!$B$52*Inputs!$B$15*Inputs!$B$24*1000*Prices!L10,0)+IF(A7=Inputs!$B$9+Inputs!$B$8-1,Inputs!$B$55*Inputs!$B$7*1000*Prices!L10,0) -> 0 | F7: =D7-H7 -> 10025640 | G7: =Financing!G16 -> 7712030.8 | H7: =Taxes!K7 -> 0 | I7: =D7-M7-E7 -> 10025640 | J7: =D7-H7-E7-G7+Financing!D16 -> 2313609.2 | K7: =K6+J7 -> -79265083 | L7: formula | M7: =Taxes!Q7 -> 0 | N7: =D7-M7 -> 10025640 | O7: =1/(1+Inputs!$B$38)^(A7-$A$5) -> 0.88999644
A8: 2029 | B8: =Revenue!G8 -> 14563500 | C8: =SUM(Revenue!H8:J8) -> 4669315.2 | D8: =B8-C8 -> 9894184.8 | E8: =IF(A8=Inputs!$B$9-1,Financing!$G$5,0)+IF(AND(A8=Inputs!$B$9+Inputs!$B$51,Inputs!$B$51<Inputs!$B$8),Inputs!$B$52*Inputs!$B$15*Inputs!$B$24*1000*Prices!L11,0)+IF(A8=Inputs!$B$9+Inputs!$B$8-1,Inputs!$B$55*Inputs!$B$7*1000*Prices!L11,0) -> 0 | F8: =D8-H8 -> 9894184.8 | G8: =Financing!G17 -> 7610911.4 | H8: =Taxes!K8 -> 0 | I8: =D8-M8-E8 -> 9894184.8 | J8: =D8-H8-E8-G8+Financing!D17 -> 2283273.4 | K8: =K7+J8 -> -76981810 | L8: formula | M8: =Taxes!Q8 -> 0 | N8: =D8-M8 -> 9894184.8 | O8: =1/(1+Inputs!$B$38)^(A8-$A$5) -> 0.83961928
A9: 2030 | B9: =Revenue!G9 -> 14563500 | C9: =SUM(Revenue!H9:J9) -> 4762701.5 | D9: =B9-C9 -> 9800798.5 | E9: =IF(A9=Inputs!$B$9-1,Financing!$G$5,0)+IF(AND(A9=Inputs!$B$9+Inputs!$B$51,Inputs!$B$51<Inputs!$B$8),Inputs!$B$52*Inputs!$B$15*Inputs!$B$24*1000*Prices!L12,0)+IF(A9=Inputs!$B$9+Inputs!$B$8-1,Inputs!$B$55*Inputs!$B$7*1000*Prices!L12,0) -> 0 | F9: =D9-H9 -> 9800798.5 | G9: =Financing!G18 -> 7539075.8 | H9: =Taxes!K9 -> 0 | I9: =D9-M9-E9 -> 9800798.5 | J9: =D9-H9-E9-G9+Financing!D18 -> 2261722.7 | K9: =K8+J9 -> -74720087 | L9: formula | M9: =Taxes!Q9 -> 0 | N9: =D9-M9 -> 9800798.5 | O9: =1/(1+Inputs!$B$38)^(A9-$A$5) -> 0.79209366
A10: 2031 | B10: =Revenue!G10 -> 14563500 | C10: =SUM(Revenue!H10:J10) -> 4857955.5 | D10: =B10-C10 -> 9705544.5 | E10: =IF(A10=Inputs!$B$9-1,Financing!$G$5,0)+IF(AND(A10=Inputs!$B$9+Inputs!$B$51,Inputs!$B$51<Inputs!$B$8),Inputs!$B$52*Inputs!$B$15*Inputs!$B$24*1000*Prices!L13,0)+IF(A10=Inputs!$B$9+Inputs!$B$8-1,Inputs!$B$55*Inputs!$B$7*1000*Prices!L13,0) -> 0 | F10: =D10-H10 -> 9705544.5 | G10: =Financing!G19 -> 7465803.4 | H10: =Taxes!K10 -> 0 | I10: =D10-M10-E10 -> 9705544.5 | J10: =D10-H10-E10-G10+Financing!D19 -> 2239741 | K10: =K9+J10 -> -72480346 | L10: formula | M10: =Taxes!Q10 -> 0 | N10: =D10-M10 -> 9705544.5 | O10: =1/(1+Inputs!$B$38)^(A10-$A$5) -> 0.74725817
A11: 2032 | B11: =Revenue!G11 -> 14603400 | C11: =SUM(Revenue!H11:J11) -> 4955114.6 | D11: =B11-C11 -> 9648285.4 | E11: =IF(A11=Inputs!$B$9-1,Financing!$G$5,0)+IF(AND(A11=Inputs!$B$9+Inputs!$B$51,Inputs!$B$51<Inputs!$B$8),Inputs!$B$52*Inputs!$B$15*Inputs!$B$24*1000*Prices!L14,0)+IF(A11=Inputs!$B$9+Inputs!$B$8-1,Inputs!$B$55*Inputs!$B$7*1000*Prices!L14,0) -> 0 | F11: =D11-H11 -> 9648285.4 | G11: =Financing!G20 -> 7421758 | H11: =Taxes!K11 -> 0 | I11: =D11-M11-E11 -> 9648285.4 | J11: =D11-H11-E11-G11+Financing!D20 -> 2226527.4 | K11: =K10+J11 -> -70253818 | L11: formula | M11: =Taxes!Q11 -> 0 | N11: =D11-M11 -> 9648285.4 | O11: =1/(1+Inputs!$B$38)^(A11-$A$5) -> 0.70496054
A12: 2033 | B12: =Revenue!G12 -> 14563500 | C12: =SUM(Revenue!H12:J12) -> 5054216.9 | D12: =B12-C12 -> 9509283.1 | E12: =IF(A12=Inputs!$B$9-1,Financing!$G$5,0)+IF(AND(A12=Inputs!$B$9+Inputs!$B$51,Inputs!$B$51<Inputs!$B$8),Inputs!$B$52*Inputs!$B$15*Inputs!$B$24*1000*Prices!L15,0)+IF(A12=Inputs!$B$9+Inputs!$B$8-1,Inputs!$B$55*Inputs!$B$7*1000*Prices!L15,0) -> 0 | F12: =D12-H12 -> 9509283.1 | G12: =Financing!G21 -> 7314833.1 | H12: =Taxes!K12 -> 0 | I12: =D12-M12-E12 -> 9509283.1 | J12: =D12-H12-E12-G12+Financing!D21 -> 2194449.9 | K12: =K11+J12 -> -68059368 | L12: formula | M12: =Taxes!Q12 -> 0 | N12: =D12-M12 -> 9509283.1 | O12: =1/(1+Inputs!$B$38)^(A12-$A$5) -> 0.66505711
A13: 2034 | B13: =Revenue!G13 -> 14563500 | C13: =SUM(Revenue!H13:J13) -> 5155301.3 | D13: =B13-C13 -> 9408198.7 | E13: =IF(A13=Inputs!$B$9-1,Financing!$G$5,0)+IF(AND(A13=Inputs!$B$9+Inputs!$B$51,Inputs!$B$51<Inputs!$B$8),Inputs!$B$52*Inputs!$B$15*Inputs!$B$24*1000*Prices!L16,0)+IF(A13=Inputs!$B$9+Inputs!$B$8-1,Inputs!$B$55*Inputs!$B$7*1000*Prices!L16,0) -> 0 | F13: =D13-H13 -> 9408198.7 | G13: =Financing!G22 -> 7237075.9 | H13: =Taxes!K13 -> 0 | I13: =D13-M13-E13 -> 9408198.7 | J13: =D13-H13-E13-G13+Financing!D22 -> 2171122.8 | K13: =K12+J13 -> -65888246 | L13: formula | M13: =Taxes!Q13 -> 0 | N13: =D13-M13 -> 9408198.7 | O13: =1/(1+Inputs!$B$38)^(A13-$A$5) -> 0.62741237
A14: 2035 | B14: =Revenue!G14 -> 14563500 | C14: =SUM(Revenue!H14:J14) -> 5258407.3 | D14: =B14-C14 -> 9305092.7 | E14: =IF(A14=Inputs!$B$9-1,Financing!$G$5,0)+IF(AND(A14=Inputs!$B$9+Inputs!$B$51,Inputs!$B$51<Inputs!$B$8),Inputs!$B$52*Inputs!$B$15*Inputs!$B$24*1000*Prices!L17,0)+IF(A14=Inputs!$B$9+Inputs!$B$8-1,Inputs!$B$55*Inputs!$B$7*1000*Prices!L17,0) -> 0 | F14: =D14-H14 -> 9305092.7 | G14: =Financing!G23 -> 7157763.6 | H14: =Taxes!K14 -> 0 | I14: =D14-M14-E14 -> 9305092.7 | J14: =D14-H14-E14-G14+Financing!D23 -> 2147329.1 | K14: =K13+J14 -> -63740917 | L14: formula | M14: =Taxes!Q14 -> 0 | N14: =D14-M14 -> 9305092.7 | O14: =1/(1+Inputs!$B$38)^(A14-$A$5) -> 0.59189846
A15: 2036 | B15: =Revenue!G15 -> 14603400 | C15: =SUM(Revenue!H15:J15) -> 5363575.4 | D15: =B15-C15 -> 9239824.6 | E15: =IF(A15=Inputs!$B$9-1,Financing!$G$5,0)+IF(AND(A15=Inputs!$B$9+Inputs!$B$51,Inputs!$B$51<Inputs!$B$8),Inputs!$B$52*Inputs!$B$15*Inputs!$B$24*1000*Prices!L18,0)+IF(A15=Inputs!$B$9+Inputs!$B$8-1,Inputs!$B$55*Inputs!$B$7*1000*Prices!L18,0) -> 0 | F15: =D15-H15 -> 9239824.6 | G15: =Financing!G24 -> 7107557.3 | H15: =Taxes!K15 -> 0 | I15: =D15-M15-E15 -> 9239824.6 | J15: =D15-H15-E15-G15+Financing!D24 -> 2132267.2 | K15: =K14+J15 -> -61608649 | L15: formula | M15: =Taxes!Q15 -> 0 | N15: =D15-M15 -> 9239824.6 | O15: =1/(1+Inputs!$B$38)^(A15-$A$5) -> 0.55839478
A16: 2037 | B16: =Revenue!G16 -> 14563500 | C16: =SUM(Revenue!H16:J16) -> 5470847 | D16: =B16-C16 -> 9092653 | E16: =IF(A16=Inputs!$B$9-1,Financing!$G$5,0)+IF(AND(A16=Inputs!$B$9+Inputs!$B$51,Inputs!$B$51<Inputs!$B$8),Inputs!$B$52*Inputs!$B$15*Inputs!$B$24*1000*Prices!L19,0)+IF(A16=Inputs!$B$9+Inputs!$B$8-1,Inputs!$B$55*Inputs!$B$7*1000*Prices!L19,0) -> 0 | F16: =D16-H16 -> 9092653 | G16: =Financing!G25 -> 6994348.5 | H16: =Taxes!K16 -> 0 | I16: =D16-M16-E16 -> 9092653 | J16: =D16-H16-E16-G16+Financing!D25 -> 2098304.5 | K16: =K15+J16 -> -59510345 | L16: formula | M16: =Taxes!Q16 -> 0 | N16: =D16-M16 -> 9092653 | O16: =1/(1+Inputs!$B$38)^(A16-$A$5) -> 0.52678753
A17: 2038 | B17: =Revenue!G17 -> 14563500 | C17: =SUM(Revenue!H17:J17) -> 5580263.9 | D17: =B17-C17 -> 8983236.1 | E17: =IF(A17=Inputs!$B$9-1,Financing!$G$5,0)+IF(AND(A17=Inputs!$B$9+Inputs!$B$51,Inputs!$B$51<Inputs!$B$8),Inputs!$B$52*Inputs!$B$15*Inputs!$B$24*1000*Prices!L20,0)+IF(A17=Inputs!$B$9+Inputs!$B$8-1,Inputs!$B$55*Inputs!$B$7*1000*Prices!L20,0) -> 0 | F17: =D17-H17 -> 8983236.1 | G17: =Financing!G26 -> 6910181.6 | H17: =Taxes!K17 -> 0 | I17: =D17-M17-E17 -> 8983236.1 | J17: =D17-H17-E17-G17+Financing!D26 -> 2073054.5 | K17: =K16+J17 -> -57437290 | L17: formula | M17: =Taxes!Q17 -> 0 | N17: =D17-M17 -> 8983236.1 | O17: =1/(1+Inputs!$B$38)^(A17-$A$5) -> 0.49696936
... A37: 2058 | B37: =Revenue!G37 -> 0 | C37: =SUM(Revenue!H37:J37) -> 0 | D37: =B37-C37 -> 0 | E37: =IF(A37=Inputs!$B$9-1,Financing!$G$5,0)+IF(AND(A37=Inputs!$B$9+Inputs!$B$51,Inputs!$B$51<Inputs!$B$8),Inputs!$B$52*Inputs!$B$15*Inputs!$B$24*1000*Prices!L40,0)+IF(A37=Inputs!$B$9+Inputs!$B$8-1,Inputs!$B$55*Inputs!$B$7*1000*Prices!L40,0) -> 0 | F37: =D37-H37 -> -1.5101396e-09 | G37: =Financing!G46 -> -7.5506978e-09 | H37: =Taxes!K37 -> 1.5101396e-09 | I37: =D37-M37-E37 -> 0 | J37: =D37-H37-E37-G37+Financing!D46 -> 6.0405582e-09 | K37: =K36+J37 -> -3814594.4 | L37: formula | M37: =Taxes!Q37 -> 0 | N37: =D37-M37 -> 0 | O37: =1/(1+Inputs!$B$38)^(A37-$A$5) -> 0.1549574
A39: Notes: All cash flows are nominal (real 2026 inputs indexed with inflation). CFADS = EBITDA - tax paid (levered tax incl. interest shield). Project FCF uses unlevered tax (no interest shield) and excludes debt service. Equity FCF = EBITDA - tax - CAPEX - debt service + debt drawdown. Debt is sized on CFADS with unlevered tax (column N), which avoids a circular reference.

Sheet Outputs
A1: OUTPUTS
A3: KEY PROJECT METRICS
A5: Project IRR (nominal) | E5: Equity IRR (nominal) | I5: Project NPV (nominal, at WACC)
A6: =IFERROR(IRR(Cashflow!I5:I37,-0.05),"") -> 0.015622265 | E6: =IFERROR(IRR(Cashflow!J5:J37,-0.05),"") -> -0.0031297951 | I6: =IF(Inputs!B14="","n/a",NPV(Inputs!B38,Cashflow!I6:I37)+Cashflow!I5) -> -46455203
A8: % | E8: % | I8: €
A9: Minimum DSCR | E9: LCOE (real 2026 EUR, wind only) | I9: PPA indifference price (PV)
A10: =IF(COUNT(Financing!I14:I46)=0,"n/a",MIN(Financing!I14:I46)) -> 1.3 | E10: =IF(Inputs!B14="","n/a",IFERROR(((Inputs!B14+Inputs!B16)*Inputs!B7*1000*((1+Inputs!$B$63)/(1+Inputs!B38))^(Inputs!B9-1-Cashflow!A5)+(Inputs!B19+Inputs!B21)*Inputs!B7*SUMPRODUCT(Production!M5:M37,Prices!L8:L40,Cashflow!O5:O37)+Inputs!B20*SUMPRODUCT(Production!J5:J37,Prices!L8:L40,Cashflow!O5:O37)+Inputs!B55*Inputs!B7*1000*((1+Inputs!$B$63)/(1+Inputs!B38))^(Inputs!B9+Inputs!B8-1-Cashflow!A5))/SUMPRODUCT(Production!J5:J37,Prices!L8:L40,Cashflow!O5:O37),"n/a")) -> 47.928352 | I10: =IF(SUMPRODUCT(--(Prices!P8:P40>0))=0,"n/a",IFERROR(SUMPRODUCT(Production!J5:J37,Prices!K8:K40,Prices!G8:G40,Cashflow!O5:O37)/SUMPRODUCT(Production!J5:J37,Prices!K8:K40,Prices!M8:M40,Cashflow!O5:O37),"n/a")) -> 32.071083
A12: x | E12: €/MWh | I12: €/MWh
E13: Levelised cost in real 2026 EUR/MWh: nominal wind and development CAPEX, OPEX, lease and decommissioning discounted at the nominal WACC, divided by discounted generation weighted with the inflation index. Pre-tax, BESS excluded. | I13: Discounted merchant realised price over the PPA tenor on PPA volume. Fixed nominal EUR/MWh (or real 2026 EUR/MWh if the PPA is indexed). Excludes the effect on debt sizing; the break-even PPA price including debt sizing is in rows 28-32 (snapshot).
A14: SCENARIO OUTPUT: 100 % PPA AT 50 EUR/MWh, DSCR 1.30x, WACC 6 % (SNAPSHOT: MARKET PRICE LEVEL x CAPTURE RATE)
A15: Equity IRR (nominal) | B15: Capture Low | C15: Capture Base | D15: Capture High | F15: Project NPV (EUR, nominal) | G15: Capture Low | H15: Capture Base | I15: Capture High
A16: Price Low | B16: -0.0543 | C16: -0.0236 | D16: -0.0067 | F16: Price Low | G16: -55187688 | H16: -51368358 | I16: -47637412
A17: Price Base | B17: -0.0216 | C17: -0.0031 | D17: 0.0087 | F17: Price Base | G17: -50998901 | H17: -46455203 | I17: -41937891
A18: Price High | B18: 0.0022 | C18: 0.0157 | D18: 0.0262 | F18: Price High | G18: -44377868 | H18: -38556019 | I18: -32738297
A19: Snapshot values: each cell is a full model run with the two Cover switches set to that combination (PPA mode Yes, PPA price 50 EUR/MWh, DSCR 1.30x, WACC 6 %). The PPA covers 2028-2042, so the scenarios only affect the merchant tail from 2043; debt sizing is identical in all nine runs. Live result of the active scenario: Key project metrics above.
A21: SCENARIO OUTPUT: FULL MERCHANT, DSCR 1.60x, WACC 7 % (SNAPSHOT: MARKET PRICE LEVEL x CAPTURE RATE)
A22: Equity IRR (nominal) | B22: Capture Low | C22: Capture Base | D22: Capture High | F22: Project NPV (EUR, nominal, at 7 % WACC) | G22: Capture Low | H22: Capture Base | I22: Capture High
A23: Price Low | B23: -0.1211 | C23: -0.0703 | D23: -0.0428 | F23: Price Low | G23: -131464696 | H23: -117104081 | I23: -102743465
A24: Price Base | B24: -0.0657 | C24: -0.0341 | D24: -0.0105 | F24: Price Base | G24: -113919747 | H24: -96050142 | I24: -78245979
A25: Price High | B25: -0.0249 | C25: 0.001 | D25: 0.0214 | F25: Price High | G25: -91877948 | H25: -70709432 | I25: -50984131
A26: Snapshot values: Cover!B15 = No, Inputs!B32 = 1.60, Inputs!B38 = 7 %, other inputs as Base case. NPV is discounted at 7 % and is therefore not directly comparable with the PPA grid (6 %); equity IRR is. Debt is small because merchant CFADS supports little leverage (Base/Base: EUR 25.8m, gearing 17 % vs 47 % with PPA). Low/Low: equity recovers only about 10 % of its investment (nominal); -12.1 % is the economically relevant IRR root (a second root below -50 % results from the decommissioning outflow).
A28: BREAK-EVEN PPA PRICE (SNAPSHOT: BASE/BASE, 100 % PPA, 15 YEARS, FIXED NOMINAL, DSCR 1.30x, WACC 6 %)
A29: Target | B29: PPA price (EUR/MWh) | C29: Project IRR | D29: Equity IRR | E29: Gearing | F29: Minimum DSCR | G29: Binding debt constraint
A30: Project NPV = 0 | B30: 70.35 | C30: 0.06 | D30: 0.0748 | E30: 0.722 | F30: 1.3 | G30: DSCR 1.30x
A31: Equity IRR = target (10 %) | B31: 73.94 | C31: 0.0678 | D31: 0.1 | E31: 0.75 | F31: 1.33 | G31: Gearing cap 75 %
A32: Snapshot values: solved by iteration on Inputs!B40 (Goal Seek equivalent) with full model recalculation incl. DSCR debt re-sizing; tolerance 0.01 EUR/MWh. A live formula would only be approximate because NPV is not linear in the PPA price (tax losses, gearing cap). Base case PPA price 50 EUR/MWh: gap about 20-24 EUR/MWh. Reconciliation with the OX2 back-calculation (about 62-67 EUR/MWh): see Sources & Checks #9; method and iterations: #14. Reproducible in Excel desktop via Goal Seek (Outputs!I6 -> 0 or E6 -> 10 %, by changing Inputs!B40).
A34: Real project IRR (selected scenario) | B34: =IF(ISNUMBER(A6),(1+A6)/(1+Inputs!$B$63)-1,"n/a") -> -0.0042918973
A35: Real equity IRR (selected scenario) | B35: =IF(ISNUMBER(E6),(1+E6)/(1+Inputs!$B$63)-1,"n/a") -> -0.02267627
A36: Active scenario | B36: ="Price: "&Cover!B17&" / Capture: "&Cover!B16 -> Price: Base / Capture: Base
A37: ANNUAL CASH FLOW
A38: Year | B38: Project FCF | C38: Equity FCF | D38: Revenue | E38: EBITDA | F38: Debt service | G38: DSCR
A39: 2026 | B39: =Cashflow!I5 -> 0 | C39: =Cashflow!J5 -> 0 | D39: =Cashflow!B5 -> 0 | E39: =Cashflow!D5 -> 0 | F39: =Cashflow!G5 -> 0 | G39: =Financing!I14
A40: 2027 | B40: =Cashflow!I6 -> -153000000 | C40: =Cashflow!J6 -> -81578692 | D40: =Cashflow!B6 -> 0 | E40: =Cashflow!D6 -> 0 | F40: =Cashflow!G6 -> 0 | G40: =Financing!I15
A41: 2028 | B41: =Cashflow!I7 -> 10025640 | C41: =Cashflow!J7 -> 2313609.2 | D41: =Cashflow!B7 -> 14603400 | E41: =Cashflow!D7 -> 10025640 | F41: =Cashflow!G7 -> 7712030.8 | G41: =Financing!I16 -> 1.3
A42: 2029 | B42: =Cashflow!I8 -> 9894184.8 | C42: =Cashflow!J8 -> 2283273.4 | D42: =Cashflow!B8 -> 14563500 | E42: =Cashflow!D8 -> 9894184.8 | F42: =Cashflow!G8 -> 7610911.4 | G42: =Financing!I17 -> 1.3
A43: 2030 | B43: =Cashflow!I9 -> 9800798.5 | C43: =Cashflow!J9 -> 2261722.7 | D43: =Cashflow!B9 -> 14563500 | E43: =Cashflow!D9 -> 9800798.5 | F43: =Cashflow!G9 -> 7539075.8 | G43: =Financing!I18 -> 1.3
A44: 2031 | B44: =Cashflow!I10 -> 9705544.5 | C44: =Cashflow!J10 -> 2239741 | D44: =Cashflow!B10 -> 14563500 | E44: =Cashflow!D10 -> 9705544.5 | F44: =Cashflow!G10 -> 7465803.4 | G44: =Financing!I19 -> 1.3
A45: 2032 | B45: =Cashflow!I11 -> 9648285.4 | C45: =Cashflow!J11 -> 2226527.4 | D45: =Cashflow!B11 -> 14603400 | E45: =Cashflow!D11 -> 9648285.4 | F45: =Cashflow!G11 -> 7421758 | G45: =Financing!I20 -> 1.3
A46: 2033 | B46: =Cashflow!I12 -> 9509283.1 | C46: =Cashflow!J12 -> 2194449.9 | D46: =Cashflow!B12 -> 14563500 | E46: =Cashflow!D12 -> 9509283.1 | F46: =Cashflow!G12 -> 7314833.1 | G46: =Financing!I21 -> 1.3
A47: 2034 | B47: =Cashflow!I13 -> 9408198.7 | C47: =Cashflow!J13 -> 2171122.8 | D47: =Cashflow!B13 -> 14563500 | E47: =Cashflow!D13 -> 9408198.7 | F47: =Cashflow!G13 -> 7237075.9 | G47: =Financing!I22 -> 1.3
A48: 2035 | B48: =Cashflow!I14 -> 9305092.7 | C48: =Cashflow!J14 -> 2147329.1 | D48: =Cashflow!B14 -> 14563500 | E48: =Cashflow!D14 -> 9305092.7 | F48: =Cashflow!G14 -> 7157763.6 | G48: =Financing!I23 -> 1.3
A49: 2036 | B49: =Cashflow!I15 -> 9239824.6 | C49: =Cashflow!J15 -> 2132267.2 | D49: =Cashflow!B15 -> 14603400 | E49: =Cashflow!D15 -> 9239824.6 | F49: =Cashflow!G15 -> 7107557.3 | G49: =Financing!I24 -> 1.3
A50: 2037 | B50: =Cashflow!I16 -> 9092653 | C50: =Cashflow!J16 -> 2098304.5 | D50: =Cashflow!B16 -> 14563500 | E50: =Cashflow!D16 -> 9092653 | F50: =Cashflow!G16 -> 6994348.5 | G50: =Financing!I25 -> 1.3
... A71: 2058 | B71: =Cashflow!I37 -> 0 | C71: =Cashflow!J37 -> 6.0405582e-09 | D71: =Cashflow!B37 -> 0 | E71: =Cashflow!D37 -> 0 | F71: =Cashflow!G37 -> -7.5506978e-09 | G71: =Financing!I46

Sheet BESS
A1: BESS (STANDALONE, CO-LOCATED, EQUITY-FUNDED)
A2: Battery at the wind farm site evaluated as a separate investment: grid-charged, merchant, 100 % equity, own cash flows and returns. Not part of the wind SPV cash flows, debt sizing or Outputs (Inputs B24/B47 stay 0). Inputs in real 2026 EUR, cash flows nominal (inflation Inputs!B63). Physical synergies with the wind farm (shared connection, charging curtailed wind, PPA shaping) are not modelled.
A4: INPUTS
A5: Parameter | B5: Value | C5: Unit | D5: Source / reference | E5: Status
A6: Power capacity | B6: 25 | C6: MW | D6: Own assumption | E6: own assumption
A7: Energy capacity | B7: 50 | C7: MWh | D7: Project brief; 2-hour duration in line with Nordic practice (RaboResearch, "Backup power for Europe - part 8", Jul 2026: 1-2 h systems expected to dominate). | E7: own assumption
A8: Revenue scenario | B8: Base | C8: - | D8: Switch Low / Base / High for the gross revenue rows below.
A9: Gross revenue Low | B9: 45000 | C9: €/MW/year | D9: Strong further saturation: Fingrid storage connection agreements could raise capacity to about 4 GW (Fingrid half-year report Jan-Jun 2026); installed about 1.5 GW (Solarplaza, Jul 2026). Real 2026 EUR, gross. | E9: own assumption
A10: Gross revenue Base | B10: 65000 | C10: €/MW/year | D10: Clean Horizon Storage Index Finland, 2-hour BESS, June 2026: 89 kEUR/MW/yr gross (average-MW methodology since Jan 2026; 85 % RTE, 1.5 cycles/day; excl. grid fees, taxes and SOC costs). Base about 25 % below as lifetime average under further saturation (own assumption). cleanhorizon.com, accessed 2 Oct 2026. | E10: own assumption
A11: Gross revenue High | B11: 89000 | C11: €/MW/year | D11: Clean Horizon Storage Index Finland, June 2026 level held flat in real terms. | E11: source-based
A12: Selected gross revenue | B12: =INDEX(B9:B11,MATCH(B8,{"Low";"Base";"High"},0)) -> 65000 | C12: €/MW/year | D12: Formula: row selected in B8.
A13: Energy trading share of revenue | B13: 0.8 | C13: % of gross revenue | D13: Clean Horizon Storage Index, Feb 2026: energy trading about 80 % of total revenues of a 2-hour BESS in Finland. Used for the revenue split only. | E13: source-based
A14: Cycles | B14: 547.5 | C14: cycles/year | D14: Clean Horizon index reference: 1.5 cycles/day. Degradation not modelled (own simplification). | E14: source-based
A15: Round-trip efficiency | B15: 0.85 | C15: % | D15: Clean Horizon index methodology (85 % at grid connection point). Drives grid energy fees only. | E15: source-based
A16: CAPEX before co-location saving | B16: 287 | C16: €/kWh | D16: Modo Energy, 2026 Capex Survey (9 Sep 2026): global median total capex of 2-hour projects USD 325k/MWh; converted at EUR/USD 1.1308 (2025 average) = about 287 EUR/kWh (own calculation). Share of grid connection not disclosed. | E16: source-based
A17: Co-location CAPEX saving | B17: 0 | C17: % of CAPEX | D17: Base 0 (conservative). A shared substation and connection with the wind farm could lower CAPEX; Modo notes grid connection costs explain much of the capex difference between markets. Sensitivity 10 % (own assumption). | E17: own assumption
A18: O&M and insurance | B18: 0.015 | C18: % of CAPEX per year | D18: Own assumption; no Nordic benchmark found. | E18: to verify
A19: Optimiser / route-to-market fee | B19: 0.08 | C19: % of gross revenue | D19: Own assumption; revenue-share terms not checked. | E19: to verify
A20: Fingrid capacity fee (input + output) | B20: 2274 | C20: €/MW/year | D20: Fingrid main grid service fees 2026: energy storages 94.75 EUR/MW per month each for grid input and grid output = 2 x 1,137 EUR/MW/yr (fingrid.fi, accessed 2 Oct 2026). | E20: verified
A21: Fingrid energy fee, charging | B21: 1.07 | C21: €/MWh charged | D21: Fingrid 2026: main grid output fee 1.07 EUR/MWh. | E21: verified
A22: Fingrid energy fee, discharging | B22: 0.71 | C22: €/MWh discharged | D22: Fingrid 2026: main grid input fee 0.71 EUR/MWh. | E22: verified
A23: Operating life | B23: =Inputs!B51 -> 15 | C23: years | D23: Link to Inputs B51 (project brief, about 15 years). One battery life evaluated, no replacement.
A24: Tax depreciation rate (declining balance) | B24: 0.25 | C24: % | D24: Finnish machinery and equipment, max. 25 % declining balance (to verify for BESS); remaining book value written off in the last operating year (own simplification). | E24: to verify
A25: Discount rate (nominal) | B25: 0.07 | C25: % | D25: Merchant WACC of the wind model (Inputs G38). Pure equity funding would justify a higher rate; 7 % kept for comparability (own assumption). | E25: own assumption
A26: COD | B26: =Inputs!B9 -> 2028 | C26: year | D26: Link: same COD as the wind farm; CAPEX in the year before COD.
A27: Inflation rate | B27: =Inputs!B63 -> 0.02 | C27: % p.a. | D27: Link to Inputs B63.
A28: Corporate income tax rate | B28: =Inputs!B29 -> 0.2 | C28: % | D28: Link to Inputs B29.
A29: Initial CAPEX (real 2026 EUR) | B29: =B16*1000*B7*(1-B17) -> 14350000 | C29: € | D29: Formula: CAPEX x energy capacity x (1 - co-location saving).
A31: RESULTS (SELECTED SCENARIO, NOMINAL)
A32: Initial CAPEX (nominal) | B32: =-SUM(K62:K94) -> 14637000
A33: NPV at discount rate (B25) | B33: =SUMPRODUCT(R62:R94,S62:S94) -> -2458845.9
A34: IRR after tax (nominal) | B34: =IFERROR(IRR(R62:R94,-0.05),"n/a") -> 0.040520003
A35: IRR after tax (real) | B35: =IF(ISNUMBER(B34),(1+B34)/(1+B27)-1,"n/a") -> 0.02011765
A36: Payback year (undiscounted, nominal incl. inflation; ignores cost of capital) | B36: =IFERROR(INDEX(A62:A94,MATCH(1,INDEX((T62:T94>=0)*(A62:A94>=B26),0),0)),"not within life") -> 2038
A37: Average annual EBITDA (operating years) | B37: =SUMIF(B62:B94,1,J62:J94)/B23 -> 1411883.3
A38: Discounted payback year (at discount rate B25) | B38: =IFERROR(INDEX(A62:A94,MATCH(1,INDEX((U62:U94>=0)*(A62:A94>=B26),0),0)),"not within life") -> not within life
A39: SCENARIO SNAPSHOT (EACH ROW A FULL RUN)
A40: Case | B40: Gross revenue (€/MW/yr) | C40: NPV at 7 % (€) | D40: IRR nominal | E40: Payback year
A41: Low | B41: 45000 | C41: -6536867 | D41: -0.0147 | E41: not within life
A42: Base | B42: 65000 | C42: -2458846 | D42: 0.0405 | E42: 2038
A43: High | B43: 89000 | C43: 2113161 | D43: 0.0937 | E43: 2035
A44: Base + co-location saving 10 % | B44: 65000 | C44: -1045990 | D44: 0.0563 | E44: 2037
A45: Break-even (NPV = 0 at 7 %) | B45: 77815 | C45: 0 | D45: 0.07 | E45: 2036
A46: Snapshot values: each row is a full recalculation with B8 (and B17 or B10) set as stated; other inputs as above. Break-even: gross revenue at which NPV = 0 at 7 %, solved by iteration on B10 (tolerance 50 EUR/MW/yr). Today's level (89 kEUR/MW/yr, Clean Horizon June 2026) clears the hurdle; a saturation-driven decline of more than about 13 % does not.
A48: CAPEX SAVING x GROSS REVENUE (SNAPSHOT, EACH CELL A FULL RUN)
A49: NPV at 7 % (€) | B49: Revenue Low 45 kEUR/MW/yr | C49: Revenue Base 65 kEUR/MW/yr | D49: Revenue High 89 kEUR/MW/yr | E49: Break-even revenue (€/MW/yr, NPV = 0)
A50: CAPEX saving 0 % | B50: -6536867 | C50: -2458846 | D50: 2113161 | E50: 77815
A51: CAPEX saving 10 % | B51: -4962373 | C51: -1045990 | D51: 3486002 | E51: 70480
A52: CAPEX saving 20 % | B52: -3511701 | C52: 351484 | D52: 4847482 | E52: 63145
A53: IRR nominal | B53: Revenue Low 45 kEUR/MW/yr | C53: Revenue Base 65 kEUR/MW/yr | D53: Revenue High 89 kEUR/MW/yr
A54: CAPEX saving 0 % | B54: -0.0147 | C54: 0.0405 | D54: 0.0937
A55: CAPEX saving 10 % | B55: 0.0008 | C55: 0.0563 | D55: 0.1125
A56: CAPEX saving 20 % | B56: 0.0158 | C56: 0.075 | D56: 0.1347
A57: Snapshot values from runs with B8/B10 (revenue) and B17 (CAPEX saving) set as stated, other inputs as above. CAPEX savings of 10 % and 20 % are own assumptions (share of grid connection in BESS CAPEX not verified). Rule of thumb: each 10 % CAPEX saving lowers the break-even revenue by about 7.3 kEUR/MW/yr.
A60: ANNUAL CASH FLOW (NOMINAL EUR)
A61: Year | B61: Operating flag | C61: Inflation index | D61: Gross revenue | E61: of which energy trading | F61: of which ancillary | G61: Optimiser fee | H61: Grid fees (Fingrid) | I61: O&M and insurance | J61: EBITDA | K61: CAPEX | L61: Tax depreciation | M61: Tax book value (closing) | N61: Taxable result before losses | O61: Tax losses carried (closing) | P61: Taxable income | Q61: Tax | R61: Free cash flow | S61: Discount factor | T61: Cumulative FCF | U61: Cumulative discounted FCF
A62: 2026 | B62: =IF(AND(A62>=$B$26,A62<$B$26+$B$23),1,0) -> 0 | C62: =(1+$B$27)^(A62-2026) -> 1 | D62: =B62*$B$6*$B$12*C62 -> 0 | E62: =D62*$B$13 -> 0 | F62: =D62-E62 -> 0 | G62: =-D62*$B$19 -> 0 | H62: =-B62*($B$20*$B$6+$B$14*$B$7*$B$21+$B$14*$B$7*$B$15*$B$22)*C62 -> 0 | I62: =-B62*$B$18*$B$29*C62 -> 0 | J62: =D62+G62+H62+I62 -> 0 | K62: =-IF(A62=$B$26-1,$B$29*C62,0) -> 0 | L62: =IF(B62=1,IF(A62=$B$26+$B$23-1,0-K62,(0-K62)*$B$24),0) -> 0 | M62: =0-K62-L62 -> 0 | N62: =J62-L62 -> 0 | O62: =MAX(0,0-N62) -> 0 | P62: =MAX(0,N62-0) -> 0 | Q62: =-P62*$B$28 -> 0 | R62: =J62+K62+Q62 -> 0 | S62: =1/(1+$B$25)^(A62-2026) -> 1 | T62: =R62 -> 0 | U62: =R62*S62 -> 0
A63: 2027 | B63: =IF(AND(A63>=$B$26,A63<$B$26+$B$23),1,0) -> 0 | C63: =(1+$B$27)^(A63-2026) -> 1.02 | D63: =B63*$B$6*$B$12*C63 -> 0 | E63: =D63*$B$13 -> 0 | F63: =D63-E63 -> 0 | G63: =-D63*$B$19 -> 0 | H63: =-B63*($B$20*$B$6+$B$14*$B$7*$B$21+$B$14*$B$7*$B$15*$B$22)*C63 -> 0 | I63: =-B63*$B$18*$B$29*C63 -> 0 | J63: =D63+G63+H63+I63 -> 0 | K63: =-IF(A63=$B$26-1,$B$29*C63,0) -> -14637000 | L63: =IF(B63=1,IF(A63=$B$26+$B$23-1,M62-K63,(M62-K63)*$B$24),0) -> 0 | M63: =M62-K63-L63 -> 14637000 | N63: =J63-L63 -> 0 | O63: =MAX(0,O62-N63) -> 0 | P63: =MAX(0,N63-O62) -> 0 | Q63: =-P63*$B$28 -> 0 | R63: =J63+K63+Q63 -> -14637000 | S63: =1/(1+$B$25)^(A63-2026) -> 0.93457944 | T63: =T62+R63 -> -14637000 | U63: =U62+R63*S63 -> -13679439
A64: 2028 | B64: =IF(AND(A64>=$B$26,A64<$B$26+$B$23),1,0) -> 1 | C64: =(1+$B$27)^(A64-2026) -> 1.0404 | D64: =B64*$B$6*$B$12*C64 -> 1690650 | E64: =D64*$B$13 -> 1352520 | F64: =D64-E64 -> 338130 | G64: =-D64*$B$19 -> -135252 | H64: =-B64*($B$20*$B$6+$B$14*$B$7*$B$21+$B$14*$B$7*$B$15*$B$22)*C64 -> -106809.61 | I64: =-B64*$B$18*$B$29*C64 -> -223946.1 | J64: =D64+G64+H64+I64 -> 1224642.3 | K64: =-IF(A64=$B$26-1,$B$29*C64,0) -> 0 | L64: =IF(B64=1,IF(A64=$B$26+$B$23-1,M63-K64,(M63-K64)*$B$24),0) -> 3659250 | M64: =M63-K64-L64 -> 10977750 | N64: =J64-L64 -> -2434607.7 | O64: =MAX(0,O63-N64) -> 2434607.7 | P64: =MAX(0,N64-O63) -> 0 | Q64: =-P64*$B$28 -> 0 | R64: =J64+K64+Q64 -> 1224642.3 | S64: =1/(1+$B$25)^(A64-2026) -> 0.87343873 | T64: =T63+R64 -> -13412358 | U64: =U63+R64*S64 -> -12609789
A65: 2029 | B65: =IF(AND(A65>=$B$26,A65<$B$26+$B$23),1,0) -> 1 | C65: =(1+$B$27)^(A65-2026) -> 1.061208 | D65: =B65*$B$6*$B$12*C65 -> 1724463 | E65: =D65*$B$13 -> 1379570.4 | F65: =D65-E65 -> 344892.6 | G65: =-D65*$B$19 -> -137957.04 | H65: =-B65*($B$20*$B$6+$B$14*$B$7*$B$21+$B$14*$B$7*$B$15*$B$22)*C65 -> -108945.8 | I65: =-B65*$B$18*$B$29*C65 -> -228425.02 | J65: =D65+G65+H65+I65 -> 1249135.1 | K65: =-IF(A65=$B$26-1,$B$29*C65,0) -> 0 | L65: =IF(B65=1,IF(A65=$B$26+$B$23-1,M64-K65,(M64-K65)*$B$24),0) -> 2744437.5 | M65: =M64-K65-L65 -> 8233312.5 | N65: =J65-L65 -> -1495302.4 | O65: =MAX(0,O64-N65) -> 3929910.1 | P65: =MAX(0,N65-O64) -> 0 | Q65: =-P65*$B$28 -> 0 | R65: =J65+K65+Q65 -> 1249135.1 | S65: =1/(1+$B$25)^(A65-2026) -> 0.81629788 | T65: =T64+R65 -> -12163223 | U65: =U64+R65*S65 -> -11590123
A66: 2030 | B66: =IF(AND(A66>=$B$26,A66<$B$26+$B$23),1,0) -> 1 | C66: =(1+$B$27)^(A66-2026) -> 1.0824322 | D66: =B66*$B$6*$B$12*C66 -> 1758952.3 | E66: =D66*$B$13 -> 1407161.8 | F66: =D66-E66 -> 351790.45 | G66: =-D66*$B$19 -> -140716.18 | H66: =-B66*($B$20*$B$6+$B$14*$B$7*$B$21+$B$14*$B$7*$B$15*$B$22)*C66 -> -111124.72 | I66: =-B66*$B$18*$B$29*C66 -> -232993.52 | J66: =D66+G66+H66+I66 -> 1274117.8 | K66: =-IF(A66=$B$26-1,$B$29*C66,0) -> 0 | L66: =IF(B66=1,IF(A66=$B$26+$B$23-1,M65-K66,(M65-K66)*$B$24),0) -> 2058328.1 | M66: =M65-K66-L66 -> 6174984.4 | N66: =J66-L66 -> -784210.29 | O66: =MAX(0,O65-N66) -> 4714120.4 | P66: =MAX(0,N66-O65) -> 0 | Q66: =-P66*$B$28 -> 0 | R66: =J66+K66+Q66 -> 1274117.8 | S66: =1/(1+$B$25)^(A66-2026) -> 0.76289521 | T66: =T65+R66 -> -10889105 | U66: =U65+R66*S66 -> -10618104
A67: 2031 | B67: =IF(AND(A67>=$B$26,A67<$B$26+$B$23),1,0) -> 1 | C67: =(1+$B$27)^(A67-2026) -> 1.1040808 | D67: =B67*$B$6*$B$12*C67 -> 1794131.3 | E67: =D67*$B$13 -> 1435305 | F67: =D67-E67 -> 358826.26 | G67: =-D67*$B$19 -> -143530.5 | H67: =-B67*($B$20*$B$6+$B$14*$B$7*$B$21+$B$14*$B$7*$B$15*$B$22)*C67 -> -113347.21 | I67: =-B67*$B$18*$B$29*C67 -> -237653.39 | J67: =D67+G67+H67+I67 -> 1299600.2 | K67: =-IF(A67=$B$26-1,$B$29*C67,0) -> 0 | L67: =IF(B67=1,IF(A67=$B$26+$B$23-1,M66-K67,(M66-K67)*$B$24),0) -> 1543746.1 | M67: =M66-K67-L67 -> 4631238.3 | N67: =J67-L67 -> -244145.9 | O67: =MAX(0,O66-N67) -> 4958266.3 | P67: =MAX(0,N67-O66) -> 0 | Q67: =-P67*$B$28 -> 0 | R67: =J67+K67+Q67 -> 1299600.2 | S67: =1/(1+$B$25)^(A67-2026) -> 0.71298618 | T67: =T66+R67 -> -9589504.5 | U67: =U66+R67*S67 -> -9691507.5
A68: 2032 | B68: =IF(AND(A68>=$B$26,A68<$B$26+$B$23),1,0) -> 1 | C68: =(1+$B$27)^(A68-2026) -> 1.1261624 | D68: =B68*$B$6*$B$12*C68 -> 1830013.9 | E68: =D68*$B$13 -> 1464011.1 | F68: =D68-E68 -> 366002.79 | G68: =-D68*$B$19 -> -146401.11 | H68: =-B68*($B$20*$B$6+$B$14*$B$7*$B$21+$B$14*$B$7*$B$15*$B$22)*C68 -> -115614.16 | I68: =-B68*$B$18*$B$29*C68 -> -242406.46 | J68: =D68+G68+H68+I68 -> 1325592.2 | K68: =-IF(A68=$B$26-1,$B$29*C68,0) -> 0 | L68: =IF(B68=1,IF(A68=$B$26+$B$23-1,M67-K68,(M67-K68)*$B$24),0) -> 1157809.6 | M68: =M67-K68-L68 -> 3473428.7 | N68: =J68-L68 -> 167782.63 | O68: =MAX(0,O67-N68) -> 4790483.6 | P68: =MAX(0,N68-O67) -> 0 | Q68: =-P68*$B$28 -> 0 | R68: =J68+K68+Q68 -> 1325592.2 | S68: =1/(1+$B$25)^(A68-2026) -> 0.66634222 | T68: =T67+R68 -> -8263912.3 | U68: =U67+R68*S68 -> -8808209.5
A69: 2033 | B69: =IF(AND(A69>=$B$26,A69<$B$26+$B$23),1,0) -> 1 | C69: =(1+$B$27)^(A69-2026) -> 1.1486857 | D69: =B69*$B$6*$B$12*C69 -> 1866614.2 | E69: =D69*$B$13 -> 1493291.4 | F69: =D69-E69 -> 373322.84 | G69: =-D69*$B$19 -> -149329.14 | H69: =-B69*($B$20*$B$6+$B$14*$B$7*$B$21+$B$14*$B$7*$B$15*$B$22)*C69 -> -117926.44 | I69: =-B69*$B$18*$B$29*C69 -> -247254.59 | J69: =D69+G69+H69+I69 -> 1352104 | K69: =-IF(A69=$B$26-1,$B$29*C69,0) -> 0 | L69: =IF(B69=1,IF(A69=$B$26+$B$23-1,M68-K69,(M68-K69)*$B$24),0) -> 868357.18 | M69: =M68-K69-L69 -> 2605071.5 | N69: =J69-L69 -> 483746.87 | O69: =MAX(0,O68-N69) -> 4306736.8 | P69: =MAX(0,N69-O68) -> 0 | Q69: =-P69*$B$28 -> 0 | R69: =J69+K69+Q69 -> 1352104 | S69: =1/(1+$B$25)^(A69-2026) -> 0.62274974 | T69: =T68+R69 -> -6911808.3 | U69: =U68+R69*S69 -> -7966187
A70: 2034 | B70: =IF(AND(A70>=$B$26,A70<$B$26+$B$23),1,0) -> 1 | C70: =(1+$B$27)^(A70-2026) -> 1.1716594 | D70: =B70*$B$6*$B$12*C70 -> 1903946.5 | E70: =D70*$B$13 -> 1523157.2 | F70: =D70-E70 -> 380789.3 | G70: =-D70*$B$19 -> -152315.72 | H70: =-B70*($B$20*$B$6+$B$14*$B$7*$B$21+$B$14*$B$7*$B$15*$B$22)*C70 -> -120284.97 | I70: =-B70*$B$18*$B$29*C70 -> -252199.68 | J70: =D70+G70+H70+I70 -> 1379146.1 | K70: =-IF(A70=$B$26-1,$B$29*C70,0) -> 0 | L70: =IF(B70=1,IF(A70=$B$26+$B$23-1,M69-K70,(M69-K70)*$B$24),0) -> 651267.88 | M70: =M69-K70-L70 -> 1953803.6 | N70: =J70-L70 -> 727878.24 | O70: =MAX(0,O69-N70) -> 3578858.5 | P70: =MAX(0,N70-O69) -> 0 | Q70: =-P70*$B$28 -> 0 | R70: =J70+K70+Q70 -> 1379146.1 | S70: =1/(1+$B$25)^(A70-2026) -> 0.5820091 | T70: =T69+R70 -> -5532662.2 | U70: =U69+R70*S70 -> -7163511.4
A71: 2035 | B71: =IF(AND(A71>=$B$26,A71<$B$26+$B$23),1,0) -> 1 | C71: =(1+$B$27)^(A71-2026) -> 1.1950926 | D71: =B71*$B$6*$B$12*C71 -> 1942025.4 | E71: =D71*$B$13 -> 1553620.3 | F71: =D71-E71 -> 388405.08 | G71: =-D71*$B$19 -> -155362.03 | H71: =-B71*($B$20*$B$6+$B$14*$B$7*$B$21+$B$14*$B$7*$B$15*$B$22)*C71 -> -122690.67 | I71: =-B71*$B$18*$B$29*C71 -> -257243.68 | J71: =D71+G71+H71+I71 -> 1406729 | K71: =-IF(A71=$B$26-1,$B$29*C71,0) -> 0 | L71: =IF(B71=1,IF(A71=$B$26+$B$23-1,M70-K71,(M70-K71)*$B$24),0) -> 488450.91 | M71: =M70-K71-L71 -> 1465352.7 | N71: =J71-L71 -> 918278.13 | O71: =MAX(0,O70-N71) -> 2660580.4 | P71: =MAX(0,N71-O70) -> 0 | Q71: =-P71*$B$28 -> 0 | R71: =J71+K71+Q71 -> 1406729 | S71: =1/(1+$B$25)^(A71-2026) -> 0.54393374 | T71: =T70+R71 -> -4125933.1 | U71: =U70+R71*S71 -> -6398344
A72: 2036 | B72: =IF(AND(A72>=$B$26,A72<$B$26+$B$23),1,0) -> 1 | C72: =(1+$B$27)^(A72-2026) -> 1.2189944 | D72: =B72*$B$6*$B$12*C72 -> 1980865.9 | E72: =D72*$B$13 -> 1584692.7 | F72: =D72-E72 -> 396173.19 | G72: =-D72*$B$19 -> -158469.27 | H72: =-B72*($B$20*$B$6+$B$14*$B$7*$B$21+$B$14*$B$7*$B$15*$B$22)*C72 -> -125144.48 | I72: =-B72*$B$18*$B$29*C72 -> -262388.55 | J72: =D72+G72+H72+I72 -> 1434863.6 | K72: =-IF(A72=$B$26-1,$B$29*C72,0) -> 0 | L72: =IF(B72=1,IF(A72=$B$26+$B$23-1,M71-K72,(M71-K72)*$B$24),0) -> 366338.18 | M72: =M71-K72-L72 -> 1099014.6 | N72: =J72-L72 -> 1068525.4 | O72: =MAX(0,O71-N72) -> 1592054.9 | P72: =MAX(0,N72-O71) -> 0 | Q72: =-P72*$B$28 -> 0 | R72: =J72+K72+Q72 -> 1434863.6 | S72: =1/(1+$B$25)^(A72-2026) -> 0.50834929 | T72: =T71+R72 -> -2691069.5 | U72: =U71+R72*S72 -> -5668932.1
A73: 2037 | B73: =IF(AND(A73>=$B$26,A73<$B$26+$B$23),1,0) -> 1 | C73: =(1+$B$27)^(A73-2026) -> 1.2433743 | D73: =B73*$B$6*$B$12*C73 -> 2020483.3 | E73: =D73*$B$13 -> 1616386.6 | F73: =D73-E73 -> 404096.65 | G73: =-D73*$B$19 -> -161638.66 | H73: =-B73*($B$20*$B$6+$B$14*$B$7*$B$21+$B$14*$B$7*$B$15*$B$22)*C73 -> -127647.37 | I73: =-B73*$B$18*$B$29*C73 -> -267636.32 | J73: =D73+G73+H73+I73 -> 1463560.9 | K73: =-IF(A73=$B$26-1,$B$29*C73,0) -> 0 | L73: =IF(B73=1,IF(A73=$B$26+$B$23-1,M72-K73,(M72-K73)*$B$24),0) -> 274753.64 | M73: =M72-K73-L73 -> 824260.91 | N73: =J73-L73 -> 1188807.3 | O73: =MAX(0,O72-N73) -> 403247.68 | P73: =MAX(0,N73-O72) -> 0 | Q73: =-P73*$B$28 -> 0 | R73: =J73+K73+Q73 -> 1463560.9 | S73: =1/(1+$B$25)^(A73-2026) -> 0.4750928 | T73: =T72+R73 -> -1227508.6 | U73: =U72+R73*S73 -> -4973604.9
A74: 2038 | B74: =IF(AND(A74>=$B$26,A74<$B$26+$B$23),1,0) -> 1 | C74: =(1+$B$27)^(A74-2026) -> 1.2682418 | D74: =B74*$B$6*$B$12*C74 -> 2060892.9 | E74: =D74*$B$13 -> 1648714.3 | F74: =D74-E74 -> 412178.58 | G74: =-D74*$B$19 -> -164871.43 | H74: =-B74*($B$20*$B$6+$B$14*$B$7*$B$21+$B$14*$B$7*$B$15*$B$22)*C74 -> -130200.32 | I74: =-B74*$B$18*$B$29*C74 -> -272989.05 | J74: =D74+G74+H74+I74 -> 1492832.1 | K74: =-IF(A74=$B$26-1,$B$29*C74,0) -> 0 | L74: =IF(B74=1,IF(A74=$B$26+$B$23-1,M73-K74,(M73-K74)*$B$24),0) -> 206065.23 | M74: =M73-K74-L74 -> 618195.69 | N74: =J74-L74 -> 1286766.9 | O74: =MAX(0,O73-N74) -> 0 | P74: =MAX(0,N74-O73) -> 883519.21 | Q74: =-P74*$B$28 -> -176703.84 | R74: =J74+K74+Q74 -> 1316128.3 | S74: =1/(1+$B$25)^(A74-2026) -> 0.44401196 | T74: =T73+R74 -> 88619.679 | U74: =U73+R74*S74 -> -4389228.2
... A94: 2058 | B94: =IF(AND(A94>=$B$26,A94<$B$26+$B$23),1,0) -> 0 | C94: =(1+$B$27)^(A94-2026) -> 1.8845406 | D94: =B94*$B$6*$B$12*C94 -> 0 | E94: =D94*$B$13 -> 0 | F94: =D94-E94 -> 0 | G94: =-D94*$B$19 -> 0 | H94: =-B94*($B$20*$B$6+$B$14*$B$7*$B$21+$B$14*$B$7*$B$15*$B$22)*C94 -> 0 | I94: =-B94*$B$18*$B$29*C94 -> 0 | J94: =D94+G94+H94+I94 -> 0 | K94: =-IF(A94=$B$26-1,$B$29*C94,0) -> 0 | L94: =IF(B94=1,IF(A94=$B$26+$B$23-1,M93-K94,(M93-K94)*$B$24),0) -> 0 | M94: =M93-K94-L94 -> 0 | N94: =J94-L94 -> 0 | O94: =MAX(0,O93-N94) -> 0 | P94: =MAX(0,N94-O93) -> 0 | Q94: =-P94*$B$28 -> 0 | R94: =J94+K94+Q94 -> 0 | S94: =1/(1+$B$25)^(A94-2026) -> 0.11474113 | T94: =T93+R94 -> 5232999.8 | U94: =U93+R94*S94 -> -2458845.9

Sheet Checks
A1: CHECKS
A3: MODEL INTEGRITY
A4: Check | B4: Result | C4: Status | D4: Comment | F4: Overall status | G4: =IF(COUNTIF(C5:C27,"ACTION")>0,"ACTION REQUIRED",IF(COUNTIF(C5:C27,"INFO")>0,"TEMPLATE / INFO","PASS")) -> TEMPLATE / INFO
A5: Missing core CAPEX input | B5: =IF(Inputs!B14="","MISSING","OK") -> OK | C5: =IF(B5="OK","PASS",IF(OR(B5="MISSING",B5="ERROR"),"ACTION","INFO")) -> PASS | D5: CAPEX should be sourced before valuation.
A6: Missing fixed OPEX input | B6: =IF(Inputs!B19="","MISSING","OK") -> OK | C6: =IF(B6="OK","PASS",IF(OR(B6="MISSING",B6="ERROR"),"ACTION","INFO")) -> PASS | D6: OPEX should be sourced before valuation.
A7: Missing market prices (selected scenario) | B7: =IF(COUNT(Inputs!B68,Inputs!B70:B78)<10,"MISSING","OK") -> OK | C7: =IF(B7="OK","PASS",IF(OR(B7="MISSING",B7="ERROR"),"ACTION","INFO")) -> PASS | D7: Price anchors in Inputs 68 and 70-78 (start value, 2030/2040/2050 for Low/Base/High). The 2028 anchor (row 69) is optional.
A8: Missing capture rates | B8: =IF(COUNT(Inputs!B79:B81)<3,"MISSING","OK") -> OK | C8: =IF(B8="OK","PASS",IF(OR(B8="MISSING",B8="ERROR"),"ACTION","INFO")) -> PASS | D8: Low/Base/High capture rates in Inputs 79-81.
A9: Tax rate populated | B9: =IF(Inputs!B29="","MISSING","OK") -> OK | C9: =IF(B9="OK","PASS",IF(OR(B9="MISSING",B9="ERROR"),"ACTION","INFO")) -> PASS | D9: Verify Finnish tax rate.
A10: Debt schedule repaid | B10: =IF(Financing!B8=0,"INFO",IF(ABS(Financing!H46)<1,"OK","ERROR")) -> OK | C10: =IF(B10="OK","PASS",IF(OR(B10="MISSING",B10="ERROR"),"ACTION","INFO")) -> PASS | D10: DSCR-sculpted schedule; closing debt at the end of the horizon must be zero (INFO while no debt is sized).
A11: PPA indifference price | B11: =IF(ISNUMBER(Outputs!I10),"OK","MISSING") -> OK | C11: =IF(B11="OK","PASS",IF(OR(B11="MISSING",B11="ERROR"),"ACTION","INFO")) -> PASS | D11: PV-based price (excl. debt-sizing effect). Break-even incl. debt effect: Outputs rows 28-32 (snapshot).
A12: Timeline fits model horizon | B12: =IF(AND(Inputs!B9>=Production!A5+1,Inputs!B9+Inputs!B8-1<=Production!A37),"OK","ERROR") -> OK | C12: =IF(B12="OK","PASS",IF(OR(B12="MISSING",B12="ERROR"),"ACTION","INFO")) -> PASS | D12: COD >= 2027 and last operating year <= 2058 (horizon 2026-2058).
A13: Revenue volumes reconcile | B13: =IF(ABS(SUM(Revenue!B5:B37)-SUM(Production!J5:J37))<1,"OK","ERROR") -> OK | C13: =IF(B13="OK","PASS",IF(OR(B13="MISSING",B13="ERROR"),"ACTION","INFO")) -> PASS | D13: Revenue-tab MWh must equal Production-tab net exported MWh.
A14: Sources = uses | B14: =IF(ABS(Financing!B8+Financing!B9-Financing!G5)<1,"OK","ERROR") -> OK | C14: =IF(B14="OK","PASS",IF(OR(B14="MISSING",B14="ERROR"),"ACTION","INFO")) -> PASS | D14: Debt + equity must equal initial CAPEX.
A15: DSCR at or above target | B15: =IF(COUNT(Financing!I14:I46)=0,"INFO",IF(MIN(Financing!I14:I46)>=Inputs!B32-0.0001,"OK","ERROR")) -> OK | C15: =IF(B15="OK","PASS",IF(OR(B15="MISSING",B15="ERROR"),"ACTION","INFO")) -> PASS | D15: Minimum DSCR vs target (INFO while no debt is sized).
A16: No negative amortisation | B16: =IF(COUNTIF(Financing!F14:F46,"<-0.5")=0,"OK","ERROR") -> OK | C16: =IF(B16="OK","PASS",IF(OR(B16="MISSING",B16="ERROR"),"ACTION","INFO")) -> PASS | D16: Sculpted principal must not be negative (debt service must cover interest).
A17: Debt tenor within asset life | B17: =IF(MIN(Inputs!B34,Inputs!B35)<=Inputs!B8,"OK","ERROR") -> OK | C17: =IF(B17="OK","PASS",IF(OR(B17="MISSING",B17="ERROR"),"ACTION","INFO")) -> PASS | D17: Debt repayment window must not exceed the economic life.
A18: Capture rates plausible | B18: =IF(COUNT(Prices!C8:E40)=0,"INFO",IF(AND(MIN(Prices!C8:E40)>=0,MAX(Prices!C8:E40)<=1.5),"OK","ERROR")) -> OK | C18: =IF(B18="OK","PASS",IF(OR(B18="MISSING",B18="ERROR"),"ACTION","INFO")) -> PASS | D18: Capture rates are fractions (0.65 = 65 %), range 0 to 1.5.
A19: PPA price entered | B19: =IF(Cover!B15="Yes",IF(Inputs!B40="","MISSING","OK"),"OK") -> OK | C19: =IF(B19="OK","PASS",IF(OR(B19="MISSING",B19="ERROR"),"ACTION","INFO")) -> PASS | D19: Required when PPA mode = Yes.
A20: BESS inputs consistent | B20: =IF(Inputs!B24=0,"OK",IF(OR(Inputs!B47=0,Inputs!B15=""),"MISSING","OK")) -> OK | C20: =IF(B20="OK","PASS",IF(OR(B20="MISSING",B20="ERROR"),"ACTION","INFO")) -> PASS | D20: If BESS MWh > 0, BESS power (MW) and BESS CAPEX are required.
A21: Tax losses used by end of horizon | B21: =IF(Taxes!I37>0.5,"INFO","OK") -> OK | C21: =IF(B21="OK","PASS",IF(OR(B21="MISSING",B21="ERROR"),"ACTION","INFO")) -> PASS | D21: Unused tax losses remain at the end of the horizon; loss expiry is not modelled.
A22: Inputs marked 'to verify' | B22: =IF(COUNTIF(Inputs!E7:E90,"to verify")=0,"OK","INFO") -> OK | C22: =IF(B22="OK","PASS",IF(OR(B22="MISSING",B22="ERROR"),"ACTION","INFO")) -> PASS | D22: ="Open items: "&COUNTIF(Inputs!E7:E90,"to verify")&" parameters still marked to verify (Inputs!E)." -> Open items: 0 parameters still marked to verify (Inputs!E).
A23: Equity IRR vs target | B23: =IF(NOT(ISNUMBER(Outputs!E6)),"INFO",IF(Outputs!E6>=Inputs!B39,"OK","INFO")) -> INFO | C23: =IF(B23="OK","PASS",IF(OR(B23="MISSING",B23="ERROR"),"ACTION","INFO")) -> INFO | D23: Result flag, not an integrity check: equity IRR compared with the target equity IRR.
A24: Inflation assumption entered | B24: =IF(Inputs!B63="","MISSING","OK") -> OK | C24: =IF(B24="OK","PASS",IF(OR(B24="MISSING",B24="ERROR"),"ACTION","INFO")) -> PASS | D24: Real 2026 inputs are indexed with this rate; WACC and debt rate must be nominal.
A25: Snapshot PPA grid current | B25: =IF(AND(Cover!B15="Yes",Cover!B16="Base",Cover!B17="Base",Inputs!B40=50,Inputs!B43=1,Inputs!B32=1.3,Inputs!B38=0.06),IF(ABS(Outputs!I6-Outputs!H17)<2,"OK","STALE"),"N/A") -> OK | C25: =IF(B25="OK","PASS",IF(B25="STALE","ACTION","INFO")) -> PASS | D25: Compares live NPV with Outputs H17 (Base/Base, 100 % PPA at 50 EUR/MWh, DSCR 1.30, WACC 6 %). STALE: an input changed since the snapshot; re-run Outputs rows 14-32. N/A in other settings.
A26: Snapshot merchant grid current | B26: =IF(AND(Cover!B15="No",Cover!B16="Base",Cover!B17="Base",Inputs!B32=1.6,Inputs!B38=0.07),IF(ABS(Outputs!I6-Outputs!H24)<2,"OK","STALE"),"N/A") -> N/A | C26: =IF(B26="OK","PASS",IF(B26="STALE","ACTION","INFO")) -> INFO | D26: Compares live NPV with Outputs H24 (Base/Base merchant, DSCR 1.60, WACC 7 %). STALE: re-run the merchant grid. N/A in other settings.
A27: Snapshot BESS current | B27: =IF(AND(BESS!B8="Base",BESS!B10=65000,BESS!B17=0),IF(ABS(BESS!B33-BESS!C42)<2,"OK","STALE"),"N/A") -> OK | C27: =IF(B27="OK","PASS",IF(B27="STALE","ACTION","INFO")) -> PASS | D27: Compares live BESS NPV with BESS C42 (Base, no CAPEX saving). STALE: re-run BESS rows 41-56. N/A in other settings.
A30: SOURCE / ASSUMPTION STATUS LEGEND
A31: Verified / source-based
A32: Own assumption / to verify
A33: User input
A34: Formula

Sheet Sources & Checks
A1: SOURCES & CHECKS
A2: Validation of inputs and results against independent sources and hand calculations, plus a log of how AI was used. Status categories as in Inputs column E: verified / source-based / own assumption / to verify. Model v1.8, Oct 2026.
A4: A. VALIDATION CHECKS
A5: # | B5: Check | C5: Comparison / method | D5: Result | E5: Conclusion for the model | F5: Source(s) | G5: Status
A6: 1 | B6: Wind data: Fingrid vs ENTSO-E | C6: Finnish wind generation from Fingrid open data (dataset 75) compared with ENTSO-E Actual Generation per Production Type (FI, wind onshore), 15-minute and hourly, 2023 to Sep 2026: deviation, correlation, share of identical values, runs of repeated values. | D6: 2024-2026: deviation about 0.5-1.6 %, correlation > 0.999, no break at 21 Feb 2024. 2023: Fingrid shows frozen values Jun-Sep (up to 65 % of hours in July; ENTSO-E 0-0.4 %). Impact: capture rate 2023 72.3 % vs 71.6 %, capacity factor 2023 26.9 % vs 27.4 %; 2024-2026 unchanged. | E6: ENTSO-E used as primary wind source (no missing hours or quarter-hours; Fingrid series had 358 gaps), Fingrid as cross-check. Base capture rate (2025 and last 12 months) not affected. The sources are not independent: ENTSO-E data for Finland are reported by Fingrid as TSO (identical values 58 % in 2025, 72 % in 2026), so the check detects transfer errors but not errors in Fingrid's own measurement. | F6: Fingrid open data, dataset 75 (data.fingrid.fi); ENTSO-E Transparency Platform, Actual Generation per Production Type (transparency.entsoe.eu); both accessed 1 Oct 2026. Own Python analysis. | G6: source-based
A7: 2 | B7: Capture rate vs KYOS | C7: KYOS fundamental model, Finland 2027-2036: onshore wind capture price divided by baseload price, compared with model base capture rate. KYOS baseload compared with the model base price path (Prices B, average 2027-2036). | D7: 36.1 / 60.0 EUR/MWh = implied capture rate 60.2 % vs model base 60 % (own calculation). KYOS baseload about 6-12 EUR/MWh above the model base path (48.2 EUR/MWh real 2026, 53.6 nominal; own calculation); range depends on the KYOS price basis, which is not stated. | E7: Base capture rate consistent with an independent fundamental model. Model base price path is conservative relative to KYOS | F7: KYOS PPA Insights No. 19 (Jun 2026), Finland, 2027-2036; model Prices B8:B40 | G7: source-based
A8: 3 | B8: Futures vs Lampela (2030) | C8: EEX Cal-30 FI base future converted to real 2026 EUR vs Lampela (2023) Base 2030 (model v27, scenario x1,2). | D8: 48.67 vs 39.0 EUR/MWh: futures about 10 EUR/MWh higher. | E8: Near-term path uses futures (market view), Lampela only from 2040; the thesis likely understates today's price level (see Inputs A83). | F8: EEX market data, trading day 1 Oct 2026; Lampela, S. (2023), Tampere University, Table 5.2. | G8: source-based
A9: 4 | B9: LCOE bridge to IRENA | C9: Model LCOE bridged to IRENA (2026) Finland onshore wind 2025 by replacing model inputs step by step with IRENA values (real annuity formula, see #5). EUR/USD 1.1308 (2025 average) | D9: Model 47.9 -> TIC 1,480 USD/kW = 1,309 EUR/kW: 43.6 -> capacity factor 34 %: 42.7 -> real WACC 3.0 %: 40.0 EUR/MWh vs IRENA 44 USD/MWh = 38.9 EUR/MWh; residual 1.1 EUR/MWh (own calculation) | E9: Difference fully explained by assumptions, no model error. Model is about 9 EUR/MWh above IRENA mainly due to higher CAPEX (2026 FID level vs 2025 commissioning) and higher WACC: conservative. Residual consistent with implied IRENA O&M of about 41 EUR/kW/yr (model 44), price year (2025 USD vs real 2026 EUR) and lifetime. IRENA WACC for Finland and economic life not stated in the report; 3 % real (IRENA ch. 1, fully contracted projects in mature markets) and 25 years assumed (to verify) | F9: IRENA (2026), Renewable power generation costs in 2025, Fig. 2.4 (p. 47), Fig. 2.8 (p. 53), Fig. 2.11 (p. 57), ch. 1 (p. 29); EUR/USD 2025 average 1.1308 (poundsterlinglive.com, accessed 2 Oct 2026). | G9: source-based
A10: 5 | B10: LCOE hand calculation | C10: Real annuity: CAPEX 1,500 EUR/kW x CRF (25 years, real WACC (1.06/1.02 - 1) = 3.92 %) = 95.2 EUR/kW/yr, plus OPEX and lease 44 EUR/kW/yr; divided by 8,760 h x 35 % x (1 - 5 %) = 2.91 MWh/kW/yr. Decommissioning and construction-year indexation ignored. | D10: About 47.8 vs model 47.9 EUR/MWh (Outputs E10). | E10: LCOE formula in Outputs E10 confirmed. Earlier hand check (about 54 EUR/MWh) related to a previous input set and is superseded. | F10: Own calculation from Inputs B8, B10, B11, B14, B19, B21, B38, B63. | G10: verified
A11: 6 | B11: Back-calculation OX2 | C11: Model run with OX2 parameters (CAPEX about 1.48 EUR m/MW, capacity factor 38.7 %) to find the PPA price that meets the target return. | D11: Required PPA price about 62-67 EUR/MWh. | E11: Indicates the price level of the hyperscaler PPAs behind recent Finnish FIDs. Own derivation, actual PPA prices not published. | F11: OX2 press releases 1 Apr 2025 and 16 Dec 2025 (see Inputs D10, D14, D43); own model runs. | G11: own assumption
A12: 7 | B12: WACC via CAPM | C12: CAPM cost of equity plus after-tax cost of debt at 47 % gearing. | D12: About 5.9 % nominal after tax. | E12: 6 % used for the PPA case, 7 % for merchant. Cross-check IRENA (2026): about 3 % real for contracted projects. | F12: Trading Economics (FI 10Y, 18 Aug 2026); Damodaran (ERP and unlevered beta, Jan 2026); see Inputs D38. | G12: source-based
A13: 8 | B13: Curtailment vs contract structure | C13: Value of 5 % curtailment at the PPA price compared with the price difference between PPAs with and without settlement in negative-price hours. | D13: 5 % x 50 EUR/MWh = about 2.5 EUR/MWh vs at least about 3 EUR/MWh (Modo) and 2-5 % of the PPA price = about 1-2.5 EUR/MWh at 50 EUR/MWh (Ecohz; own conversion). | E13: 5 % curtailment is a reasonable proxy for a PPA without settlement in negative-price hours; vary curtailment only together with a lower PPA price. Both references are Spanish solar PPAs; the Nordic effect may be smaller (hydro flexibility, Volt Power Analytics via Ecohz), although Finland had the most negative-price hours in the EU in 2023 and 2024 (Montel via Ecohz). Proxy only | F13: Modo Energy, 'PPAs in a time of negative prices: Lessons from Spain', 22 Oct 2025, https://modoenergy.com/research/en/ppa-contracts-spain-negative-prices-settlement-zero-floor-remuneration; Ecohz, 'Negative electricity prices: what is their impact on PPAs?', 29 Jan 2025 (updated 25 Nov 2025), https://www.ecohz.com/blog/negative-electricity-prices-impact-on-ppa; both accessed 2 Oct 2026. | G13: source-based
A14: 9 | B14: Break-even PPA price vs OX2 | C14: Break-even PPA price of the model (Outputs rows 28-32) compared with the OX2 back-calculation (#6). | D14: Model: 70.35 (NPV = 0) and 73.94 EUR/MWh (equity IRR 10 %) vs OX2 about 62-67 EUR/MWh. | E14: Gap explained by higher CAPEX (1,500 vs about 1,480 EUR/kW), lower capacity factor (35 % vs 38.7 %) and the scale of a 472 MW portfolio. Deck wording: 100 MW greenfield needs about 70-74 EUR/MWh. | F14: Own model runs (v1.5 Base/Base, 2 Oct 2026); #6. | G14: own assumption
A15: 10 | B15: Recalculation reproduces Excel | C15: Full recalculation of the workbook in LibreOffice compared with the values cached by Excel. | D15: Identical (Base/Base NPV EUR -46,455,203; equity IRR -0.31 %). | E15: Scripted scenario runs give the same results as Excel. | F15: Own check, v1.5 file of 2 Oct 2026. | G15: verified
A16: 11 | B16: IRR cross-check | C16: Excel IRR() compared with an independent root search on the same cash flows (Python, Brent method). | D16: Identical in all cases where Excel converged; without a start value Excel returned no IRR in 7 of 18 scenario runs. | E16: Start value -5 % added to Outputs A6/E6 (Changelog #21); all 18 runs now converge in Excel. Merchant Low/Low has two roots; -12.1 % is the relevant one. | F16: Own check, 2 Oct 2026. | G16: verified
A17: 12 | B17: Plausibility of break-even | C17: At NPV = 0 the project IRR must equal the WACC; equity IRR compared with the CAPM cost of equity. | D17: Project IRR 6.0 % = WACC; equity IRR 7.5 % vs cost of equity about 7.0 %. At 10 % equity IRR the gearing cap binds (min. DSCR 1.33x). | E17: Break-even results are internally consistent. Above a project IRR of 5.75 % (debt rate) leverage becomes positive. | F17: Own check; Inputs D38, D39. | G17: verified
... A21: 16 | B21: Break-even PPA price vs CAPEX and capacity factor | C21: 12 points (CAPEX 1,250–1,650 EUR/kW × CF 35 % / 38.7 %), secant iteration on Inputs!B40 to NPV = 0 with full recalculation | D21: CF 35 %: 60.8–76.1 EUR/MWh; CF 38.7 %: 53.8–67.7 EUR/MWh; OX2-type about 62 | E21: −100 EUR/kW CAPEX ≈ −3.5 to −3.8 EUR/MWh; CF +3.7 pp ≈ −8 EUR/MWh | F21: Own model runs, 4 Oct 2026 | G21: verified
A23: B. AI USE AND VALIDATION
A24: # | B24: Area | C24: How AI was used (Claude, Anthropic) | D24: How the output was validated | E24: Responsibility
A25: a | B25: Model structure and formulas | C25: Review of the template, proposals and implementation of structural corrections in agreed versions (see Changelog). | D25: Integrity checks (Checks tab), full recalculation with 0 formula errors, hand calculation of LCOE (#5), recalculation test (#10). | E25: Each structural change approved by the author before a new version was built.
A26: b | B26: Source research | C26: Web search for market data, regulation, cost and financing references. | D26: Values entered by the author after reading the source; source and access date in Inputs D, status in Inputs E; unconfirmed figures marked own assumption or to verify. | E26: Author.
A27: c | B27: Data analysis (prices, wind) | C27: Mainly AI coded python scripts | D27: Checked if python scripts perform intended calculations, by spotchecking numbers manually where possible and checking the code. Cross-check of data sources (#1) and against KYOS (#2). | E27: Claude for code, Author for input data and results
A28: d | B28: Scenario runs and break-even | C28: Scripted model runs (Python/openpyxl with LibreOffice recalculation): 18 scenario snapshots and the break-even iteration. | D28: Reproduction of Excel results (#10), independent IRR check (#11), plausibility (#12), integrity (#13). PPA grid entered by the author; merchant grid and break-even written in v1.6 and recalculated live in Excel.BESS snapshots and CAPEX-saving grid (v1.7/v1.8) cross-checked against an independent Python replica (identical to the euro) | E28: Author reviews all figures before use in deck and memo.
A29: e | B29: Text in the model | C29: Drafting of notes, check descriptions and changelog entries in English. | D29: Every figure in the notes traced to a cell or a cited source. | E29: Author.

Sheet Changelog
A1: CHANGELOG
A3: # | B3: Tab / range | C3: Issue found in v1.0 / change request | D3: Change
A4: 1 | B4: Revenue!B5:B34 | C4: Generation linked to Production rows offset by 3 years (e.g. 2027 pulled 2030); last 3 years had 0 MWh. | D4: Rows aligned one-to-one (Revenue row r = Production row r).
A5: 2 | B5: Taxes!B | C5: 'EBITDA' column pulled Cashflow revenue (column B). | D5: Now links to Cashflow EBITDA (column D).
A6: 3 | B6: Cashflow!F, I | C6: CFADS was already after tax, then tax was deducted again in Project FCF; Project FCF also deducted debt service. | D6: Project FCF = EBITDA - unlevered tax - CAPEX. Equity FCF = EBITDA - tax - CAPEX - debt service + drawdown.
A7: 4 | B7: Outputs!G26:G55 | C7: DSCR chart column contained invalid references and showed name errors. | D7: Linked to Financing DSCR column, one row per year.
A8: 5 | B8: Outputs!I10 | C8: PPA indifference price was a hard NA() placeholder that showed a not-available error. | D8: PV-based indifference price (excl. debt-sizing effect); 'n/a' while prices are missing.
A9: 6 | B9: All time-series tabs | C9: No construction year, CAPEX and depreciation fixed at 0, lifetime and COD not used. | D9: Horizon 2026-2056 (31 rows). Construction year = COD - 1; operating flags driven by COD and lifetime; CAPEX, replacement and decommissioning in Cashflow.
A10: 7 | B10: Prices, Inputs | C10: PPA was a Yes/No switch only. | D10: PPA volume share and tenor added (Inputs 43-44); blended revenue price.
A11: 8 | B11: Production, Revenue, Inputs | C11: BESS had MWh only, no power, revenue or lifetime. | D11: Simplified BESS stack (arbitrage margin, reserve revenue, OPEX, life, replacement); grid-charged, memo volumes.
A12: 9 | B12: Financing | C12: Debt schedule was a placeholder with zero debt. | D12: DSCR-sculpted sizing on CFADS with unlevered tax (non-circular), gearing cap, schedule, DSCR.
A13: 10 | B13: Taxes | C13: Interest fully deductible; depreciation 0. | D13: Declining-balance depreciation, interest deduction cap (25 % of EBITDA above EUR 500k), unlevered tax block.
A14: 11 | B14: Production!D | C14: 8760 hours in every year. | D14: Leap years use 8784 hours.
A15: 12 | B15: Outputs | C15: LCOE was undiscounted; DSCR showed 0.0x without debt; IRR cells unformatted. | D15: Discounted wind-only LCOE; 'n/a' without debt; percent formats.
... A36: 33 | B36: BESS A16, A36, B45/C45 | C36: CAPEX label ambiguous; payback label incomplete; break-even row showed a rounded run (NPV -2,915). | D36: Labels clarified; break-even row shows the solved value 77,815 EUR/MW/yr with NPV 0.
A37: Open | B37: Not yet in the model
A38: a | B38: Tax | C38: Loss expiry (10 years; 25 years proposed from 2026 losses), carry-forward of disallowed interest, tax rate 18 % from 2027 (proposal of 17 Sep 2026, to verify).
A39: b | B39: Financing | C39: Interest during construction, fees, DSRA, tax-adjusted sculpting, refinancing.
A40: c | B40: Revenue | C40: PPA break-even as a live calculation (currently snapshot), BESS dispatch optimisation (Phase 2), degradation.
A41: d | B41: Outputs | C41: Tornado computed outside the model (Sources & Checks #15); scenario grids done (v1.6).
